Workbook
Name BASE_PORCENTAJES: 'PORCENTAJES FACTORES'!$B$1:$N$981
Name DTS: #REF!
Name DTS: #REF!
Name DTS: #REF!
Name DTS: #REF!
Name PLANTA_PERNO: 'PLANTA PERNO'!$A$9:$AP$828
Name PLANTA_PERSONAL_SJD: 'PLANTA SJD (2)'!$A$4:$AR$174
Name PLANTA_PERSONAL_SJD: 'PLANTA SJD'!$A$4:$AP$174

Sheet Hoja4 (2)
A1: CEDULA | B1: APELLIDOS Y NOMBRES | C1: TIPO DE VINCULACIÓN A LA ENTIDAD | D1: CEDULA | E1: TITULAR CARGO | F1: NIVEL | G1: NOMENCLATURA_ADMIN | H1: CÓDIGO | I1: GRADO | J1: U | K1: DEPENDENCIA DEL CARGO | L1: PROPOSITO | M1: FUNCIONES | N1: REQUISITOS | O1: Páginas Manual de Funciones
A2: 33368317 | B2: ZULY NATALIA NANDAR CASTAÑEDA | C2: PROVISIONALIDAD | E2: VACANTE DEFINITIVA | F2: ASISTENCIAL | G2: SECRETARIO | H2: 440 | I2: 9 | J2: 440-9 | K2: DIRECCIÓN DISTRITAL DE POLÍTICA JURÍDICA | L2: Realizar las labores secretariales como apoyo a la gestión de la dependencia, con oportunidad y eficiencia para satisfacer las necesidades. | M2: 1. Efectuar el envío y la recepción de los documentos y de la correspondencia relacionados con asuntos de competencia del área de trabajo, de acuerdo con las normas y procedimientos respectivos. 2. Custodiar y actualizar el archivo asignado conforme a instrucciones recibidas y con la eficiencia y oportunidad requerida. 3. Elaborar oficios y memorandos para dar trámite a las solicitudes presentadas, conforme a las instrucciones impartidas por el jefe inmediato. 4. Elaborar los informes que le sean requeridos por el jefe inmediato con criterios de oportunidad y efectividad. 5. Prestar atención telefónica y presencial sobre los trámites que adelanta la dependencia con oportunidad y veracidad 6. Desempeñar las demás funciones que le asigne el superior inmediato de acuerdo a la naturaleza del cargo. | N2: Estudio: Aprobación de cuatro (4) años de educación básica secundaria. | O2: 310-311 RES. 020 de 2019
A3: 52699744 | B3: MARIA CATALINA JARAMILLO GONZALEZ | C3: LIBRE NOMBRAMIENTO Y REMOCIÓN | D3: 52699744 | E3: MARIA CATALINA JARAMILLO GONZALEZ | F3: DIRECTIVO | G3: DIRECTOR TÉCNICO | H3: 9 | I3: 7 | J3: 9-7 | K3: DIRECCIÓN DISTRITAL DE POLÍTICA JURÍDICA | L3: Dirigir y coordinar la elaboración de estudios, diagnósticos y análisis jurídicos y jurisprudenciales que se adelanten, así como efectuar su revisión y proponer la adopción de políticas y lineamientos jurídicos, de impacto para el Distrito Capital. | M3: 1. Dirigir en la definición y coordinación de la gestión jurídica Distrital en materia de estudios y análisis especializados, coordinación del cuerpo de abogados del Distrito Capital y gestión de la información jurídica con la oportunidad requerida. 2. Dirigir los estudios, análisis jurisprudenciales y doctrinales, e investigaciones jurídicas en temáticas de interés para el Distrito Capital, en beneficio de la gestión de las oficinas jurídicas o las dependencias que hagan sus veces, en las entidades y organismos distritales con criterios de oportunidad y efectividad. 3. Coordinar la realización de actividades académicas y de formación para el fortalecimiento de las competencias jurídicas del Cuerpo de Abogados del Distrito Capital con la eficacia y oportunidad requerida 4. Asesorar a la Secretaría Jurídica Distrital en la formulación y desarrollo de la política de coordinación jurídica de las entidades y organismos del Distrito Capital. 5. Dirigir la elaboración de los proyectos de política en materia de contratación y demás temas jurídicos de interés para el Distrito, buscando la unificación de criterios para la aplicación de las normas y la ejecución concertada de acciones en esta materia, para que sean adoptados por la Secretaría Jurídica Distrital. 6. Coordinar el diseño e implementación de las políticas de divulgación del ordenamiento normativo y de acceso a la información jurídica promoviendo información veraz y actualizada.. 7. Orientar en el desarrollo, mantenimiento e implementación de los sistemas de información jurídica, en procura que los mismos estén permanentemente actualizados y disponibles para las entidades y organismos distritales y la ciudadanía en general. 8. Asistir al/la Secretario/a Jurídico/a Distrital y al/la Subsecretario/a Jurídico/a Distrital en todos los trámites, requisitos y procedimientos relacionados con las Asociaciones Público Privadas. 9. Dirigir y proponer lineamientos de unificación jurídica cuando exista disparidad de criterios en las entidades distritales con la eficacia requerida. 10. Administrar y dirigir la actualización y operación de los sistemas de información jurídica que la Secretaría Jurídica Distrital establezca para el control y operatividad de la gestión jurídica distrital, que no se encuentren a cargo de otra Dirección. 11. Asistir y apoyar a la Secretaría Jurídica Distrital y la Subsecretaría Jurídica Distrital en el ejercicio de sus funciones y atribuciones legales 12. Dirigir estudios, investigaciones y estrategias para el diseño de políticas en materia de prevención del daño antijurídico que se relacionen con los temas competencia de la dirección con la oportunidad requerida. 13. Dirigir el análisis y determinar la vigencia de los actos administrativos y directrices expedidos por el Alcalde Mayor, conforme al procedimiento establecido por la Secretaría Jurídica Distrital. 14. Asesorar jurídicamente a las dependencias de la Secretaría Jurídica Distrital en los temas de su competencia. 15. Desempeñar las demás funciones que le asigne el superior inmediato de acuerdo a la naturaleza del cargo. | N3: Titulo profesional en disciplina academica del núcleo básico de conocimiento en Derecho y afines. Titulo de posgrado en áreas relacionadas con la funciones del cargo. Tarjeta o matrícula profesional en los casos reglamentados por la Ley. | O3: 20-23 RES. 085 de 2020
A4: 52363895 | B4: ELVIRA LILIANA HERNANDEZ LIBREROS | C4: CARRERA ADMINISTRATIVA | D4: 52363895 | E4: ELVIRA LILIANA HERNANDEZ LIBREROS | F4: PROFESIONAL | G4: PROFESIONAL ESPECIALIZADO | H4: 222 | I4: 27 | J4: 222-27 | K4: DIRECCIÓN DISTRITAL DE POLÍTICA JURÍDICA | L4: Realizar los estudios, diagnósticos y análisis normativos, jurisprudenciales y doctrinales en temas de relevancia o de interés Distrital con el fin de contribuir en la formulación de alternativas jurídicas viables que contribuyan al fortalecimiento de la defensa judicial, la prevención del daño antijurídico y la estructuración de fórmulas tendientes a la materialización de la gestión jurídica pública. | M4: 1. Asesorar y elaborar los estudios para la formulación de los lineamientos de política en gerencia jurídica que contribuyan a la prevención del daño antijurídico. 2. Realizar investigaciones, estudios, diagnósticos en derecho público sobre temáticas de alto impacto para la ciudad, que le sean asignados y presentar los informes y evaluaciones correspondientes, con criterios de calidad y oportunidad. 3. Realizar análisis jurisprudencial de las decisiones judiciales en temáticas de derecho público asignadas y elaborar las fichas correspondientes en los sistemas de información jurídica, con eficacia y oportunidad. 4. Elaborar las recomendaciones tendientes a fortalecer la defensa judicial y la prevención del daño antijurídico en el Distrito Capital, acorde con la normatividad vigente. 5. Realizar seguimiento a las iniciativas, decisiones judiciales o temáticas jurídicas de interés para el Distrito capital, a fin de prevenir situaciones críticas que puedan ser atendidas oportunamente. 6. Proyectar conceptos jurídicos solicitados por las entidades u organismos Distritales y el superior inmediato, de acuerdo con la normatividad y jurisprudencia vigente y dentro de la oportunidad requerida. 7. Elaborar anteproyectos de ley, acuerdos, decretos, resoluciones y demás actos administrativos de manera oportuna, que se deriven como producto de los estudios e investigaciones jurídicas que se realicen. 8. Elaborar informes que se soliciten, sobre las actividades desarrolladas con la oportunidad y periodicidad requerida. 9. Participar en los mesas de trabajos, consejos, y/o comités, levantar las actas correspondientes, e informar al jefe inmediato sobre las conclusiones del mismo. 10. Desempeñar las demás funciones que le asigne el superior inmediato de acuerdo a la naturaleza del cargo. | N4: Estudio: Título profesional en: Derecho; Derecho y Ciencias Sociales; Derecho y Ciencias Políticas; Derecho y Ciencias Humanas; Derecho y Ciencias Administrativas; Derecho Ciencias Políticas y Relaciones Internacionales; Jurisprudencia; Justicia y Derecho; ó Leyes y Jurisprudencia; del núcleo básico de conocimiento en Derecho y afines. Título de postgrado en áreas relacionadas con las funciones del cargo. Tarjeta o matricula profesional en los casos reglamentados por la Ley. | O4: 66-68 RES. 020 de 2019
A5: 64586540 | B5: ALMA ROSA RAMOS MARIA | C5: CARRERA ADMINISTRATIVA | D5: 64586540 | E5: ALMA ROSA RAMOS MARIA | F5: PROFESIONAL | G5: PROFESIONAL ESPECIALIZADO | H5: 222 | I5: 27 | J5: 222-27 | K5: DIRECCIÓN DISTRITAL DE POLÍTICA JURÍDICA | L5: realizar los estudios, diagnósticos y análisis normativos, jurisprudenciales y doctrinales en temas de relevancia o de interés distrital con el fin de contribuir en la formulación de alternativas jurídicas viables que contribuyan al fortalecimiento de la defensa judicial, la prevención del daño antijurídico y la estructuración de fórmulas tendientes a la materialización de la gestión jurídica pública. | M5: 1.Asesorar y elaborar los estudios para la formulación de los lineamientos de política en gerencia jurídica que contribuyan a la prevención del daño antijurídico. 2.Realizar investigaciones, estudios, diagnósticos en derecho público sobre temáticas de alto impacto para la ciudad, que le sean asignados y presentar los informes y evaluaciones correspondientes, con criterios de calidad y oportunidad. 3.Realizar análisis jurisprudencial de las decisiones judiciales en temáticas de derecho público asignadas y elaborar las fichas correspondientes en los sistemas de información jurídica, con eficacia y oportunidad. 4.Elaborar las recomendaciones tendientes a fortalecer la defensa judicial y la prevención del daño antijurídico en el Distrito Capital, acorde con la normatividad vigente. 5.Realizar seguimiento a las iniciativas, decisiones judiciales o temáticas jurídicas de interés para el Distrito capital, a fin de prevenir situaciones críticas que puedan ser atendidas oportunamente. 6.Proyectar conceptos jurídicos solicitados por las entidades u organismos Distritales y el superior inmediato, de acuerdo con la normatividad y jurisprudencia vigente y dentro de la oportunidad requerida. 7.Elaborar anteproyectos de ley, acuerdos, decretos, resoluciones y demás actos administrativos de manera oportuna, que se deriven como producto de los estudios e investigaciones jurídicas que se realicen. 8.Elaborar informes que se soliciten, sobre las actividades desarrolladas con la oportunidad y periodicidad requerida. 9.Participar en los mesas de trabajos, consejos, y/o comités, levantar las actas correspondientes, e informar al jefe inmediato sobre las conclusiones del mismo. 10.Desempeñar las demás funciones que le asigne el superior inmediato de acuerdo a la naturaleza del cargo. | N5: Estudio: Título profesional en: Derecho; Derecho y Ciencias Sociales; Derecho y Ciencias Políticas; Derecho y Ciencias Humanas; Derecho y Ciencias Administrativas; Derecho Ciencias Políticas y Relaciones Internacionales; Jurisprudencia; Justicia y Derecho; ó Leyes y Jurisprudencia; del núcleo básico de conocimiento en Derecho y afines. Título de postgrado en áreas relacionadas con las funciones del cargo. Tarjeta o matricula profesional en los casos reglamentados por la Ley. | O5: 66-68 RES. 020 de 2019
A6: 73155098 | B6: FERNAN ENRIQUE PEREZ FORTICH | C6: CARRERA ADMINISTRATIVA | D6: 53015269 | E6: JOHANA PATRICIA GAMEZ GOMEZ | F6: PROFESIONAL | G6: PROFESIONAL ESPECIALIZADO | H6: 222 | I6: 22 | J6: 222-22 | K6: DIRECCIÓN DISTRITAL DE POLÍTICA JURÍDICA | L6: desarrollar estudios jurídicos en temas de impacto distrital y proponer alternativas de solución en el marco de la coordinación jurídica distrital para el fortalecimiento de la gestión jurídica pública en bogotá, d.c. | M6: 1.Realizar el seguimiento a las actividades de implementación de los lineamientos de política en gerencia jurídica, con la oportunidad y periodicidad requerida. 2.Realizar investigaciones jurídicas en derecho público sobre temáticas de mediano y bajo impacto para la ciudad, que le sean asignados y presentar los informes y evaluaciones correspondientes, con criterios de calidad y oportunidad. 3.Elaborar análisis jurisprudencial de las decisiones judiciales de mediano y bajo impacto en temáticas de derecho público, que le sean asignadas y elaborar las fichas correspondientes en los sistemas de información jurídica, para que aporten a la prevención del daño antijurídico. 4.Realizar las actividades para formular y desarrollar las alternativas de Coordinación Jurídica y de Gestión Jurídica Pública para el Distrito Capital, en el marco de la normatividad vigente. 5.Proyectar conceptos jurídicos de mediano impacto, solicitados por las entidades u organismos Distritales y el superior inmediato, con criterios de oportunidad y efectividad. 6.Elaborar anteproyectos de ley, acuerdos, decretos, resoluciones y demás actos administrativos, que se deriven como producto de los estudios e investigaciones jurídicas que se realicen, teniendo en cuenta las normas jurídicas y la jurisprudencia en cada caso. 7.Desempeñar las demás funciones que le asigne el superior inmediato de acuerdo a la naturaleza del cargo. | N6: Estudio: Título profesional en: Derecho; Derecho y Ciencias Sociales; Derecho y Ciencias Políticas; Derecho y Ciencias Humanas; Derecho y Ciencias Administrativas; Derecho Ciencias Políticas y Relaciones Internacionales; Jurisprudencia; Justicia y Derecho; ó Leyess y Jurisprudencia; del núcleo básico de conocimiento en Derecho y afines. Título de postgrado en áreas relacionadas con las funciones del cargo. Tarjeta o matricula profesional en los casos reglamentados por la Ley. | O6: 118-120 RES. 020 de 2019
B7: VACANTE TEMPORAL | D7: 53001416 | E7: DIANA MARIA MORENO VARGAS | F7: PROFESIONAL | G7: PROFESIONAL UNIVERSITARIO | H7: 219 | I7: 18 | J7: 219-18 | K7: DIRECCIÓN DISTRITAL DE POLÍTICA JURÍDICA | L7: realizar el análisis jurídico y jurisprudencial de impacto distrital e incorporar la normatividad, doctrina y jurisprudencia a los sistemas de información jurídica a cargo de la dependencia, adoptando estrategias para la defensa de los intereses públicos y la prevención del daño antijurídico. | M7: 1.Administrar y actualizar la información normativa, doctrinal y jurisprudencial en los sistemas de información jurídica para proporcionar información veraz y oportuna a las entidades, servidores públicos y la ciudadanía en general. 2.Realizar el seguimiento y control a la información contenida en los sistemas de información jurídica, con el fin de adoptar e implementar las acciones de mejora correspondientes, para la defensa de los intereses públicos y la prevención del daño antijurídico. 3.Incorporar documentos jurídicos en los sistemas de información para el ejercicio de la abogacía general del servicio jurídico del Distrito capital con calidad. 4.Realizar informes, estadísticas y análisis de información jurídica contenida en los sistemas de información jurídicos, con calidad, oportunidad y efectividad. 5.Elaborar documentos y boletines jurídicos para que sean publicados en los sistemas de información jurídica con criterios de oportunidad, calidad y efectividad. 6.Proyectar conceptos jurídicos de bajo impacto, solicitados por las entidades u organismos Distritales y asignados por el superior inmediato, de acuerdo a la normatividad vigente. 7.Diseñar la programación y organización de los eventos de orientación y actualización jurídica, para el fortalecimiento del cuerpo de abogados del Distrito capital. 8.Proyectar las respuestas a los requerimientos y/o derechos de petición de alto impacto, que sean asignados a la dependencia, con calidad, oportunidad y efectividad. 9.Desempeñar las demás funciones que le asigne el superior inmediato de acuerdo a la naturaleza del cargo. | N7: Estudio: Título profesional en: Derecho, Derecho y Ciencias Sociales, Derecho y Ciencias Políticas, Derecho y Ciencias Humanas, Derecho y Ciencias Administrativas, Derecho y Ciencias Sociales Derecho, Ciencias Políticas y Relaciones Internacionales, Jurisprudencia, Justicia y Derecho, o Leyes y Jurisprudencia; del núcleo básico de conocimiento en Derecho y afines. Tarjeta o matricula profesional en los casos reglamentados por la Ley. | O7: 165-167 RES. 020 de 2019
B8: VACANTE DEFINITIVA | E8: VACANTE DEFINITIVA | F8: PROFESIONAL | G8: PROFESIONAL UNIVERSITARIO | H8: 219 | I8: 18 | J8: 219-18 | K8: DIRECCIÓN DISTRITAL DE POLÍTICA JURÍDICA | L8: realizar el análisis jurídico y jurisprudencial de impacto distrital e incorporar la normatividad, doctrina y jurisprudencia a los sistemas de información jurídica a cargo de la dependencia, adoptando estrategias para la defensa de los intereses públicos y la prevención del daño antijurídico. | M8: 1.Administrar y actualizar la información normativa, doctrinal y jurisprudencial en los sistemas de información jurídica para proporcionar información veraz y oportuna a las entidades, servidores públicos y la ciudadanía en general. 2.Realizar el seguimiento y control a la información contenida en los sistemas de información jurídica, con el fin de adoptar e implementar las acciones de mejora correspondientes, para la defensa de los intereses públicos y la prevención del daño antijurídico. 3.Incorporar documentos jurídicos en los sistemas de información para el ejercicio de la abogacía general del servicio jurídico del Distrito capital con calidad. 4.Realizar informes, estadísticas y análisis de información jurídica contenida en los sistemas de información jurídicos, con calidad, oportunidad y efectividad. 5.Elaborar documentos y boletines jurídicos para que sean publicados en los sistemas de información jurídica con criterios de oportunidad, calidad y efectividad. 6.Proyectar conceptos jurídicos de bajo impacto, solicitados por las entidades u organismos Distritales y asignados por el superior inmediato, de acuerdo a la normatividad vigente. 7.Diseñar la programación y organización de los eventos de orientación y actualización jurídica, para el fortalecimiento del cuerpo de abogados del Distrito capital. 8.Proyectar las respuestas a los requerimientos y/o derechos de petición de alto impacto, que sean asignados a la dependencia, con calidad, oportunidad y efectividad. 9.Desempeñar las demás funciones que le asigne el superior inmediato de acuerdo a la naturaleza del cargo. | N8: Estudio: Título profesional en: Derecho, Derecho y Ciencias Sociales, Derecho y Ciencias Políticas, Derecho y Ciencias Humanas, Derecho y Ciencias Administrativas, Derecho y Ciencias Sociales Derecho, Ciencias Políticas y Relaciones Internacionales, Jurisprudencia, Justicia y Derecho, o Leyes y Jurisprudencia; del núcleo básico de conocimiento en Derecho y afines. Tarjeta o matricula profesional en los casos reglamentados por la Ley. | O8: 165-167 RES. 020 de 2019
A9: 37625914 | B9: MARY DAYANA SANCHEZ ROJAS | C9: CARRERA ADMINISTRATIVA | D9: 52486713 | E9: CLAUDIA MARCELA CAMARGO CASTRO | F9: PROFESIONAL | G9: PROFESIONAL UNIVERSITARIO | H9: 219 | I9: 13 | J9: 219-13 | K9: DIRECCIÓN DISTRITAL DE POLÍTICA JURÍDICA | L9: proyectar y atender los derechos de petición y solicitudes formuladas, así como realizar análisis de la información contenida en los sistemas de información jurídica, de manera oportuna. | M9: 1.Incorporar los documentos jurídicos en los sistemas de información para la abogacía general del servicio jurídico del Distrito capital, con calidad y oportunidad. 2.Realizar el análisis de información jurídica contenida en los sistemas de información jurídicos, que le sean asignados con criterios de calidad y de veracidad de información. 3.Proyectar las respuestas a los requerimientos y/o derechos de petición de mediano impacto, que sean asignados a la dependencia. 4.Realizar la actualización y/o elaboración de los documentos de relatoría en asuntos de complejidad alta, que permitan la compilación en temáticas afines o de impacto para la ciudad. 5.Desempeñar las demás funciones que le asigne el superior inmediato de acuerdo a la naturaleza del cargo. | N9: Estudio: Título profesional en: Derecho; Derecho y Ciencias Sociales; Derecho y Ciencias Políticas; Derecho y Ciencias Humanas; Derecho y Ciencias Administrativas; Derecho Ciencias Políticas y Relaciones Internacionales; Jurisprudencia; Justicia y Derecho; ó Leyes y Jurisprudencia; del núcleo básico de conocimiento en Derecho y afines. Tarjeta o matricula profesional en los casos reglamentados por la Ley. | O9: 208-209 RES. 020 de 2019
B10: VACANTE TEMPORAL | D10: 86058268 | E10: IAM ALEXANDER OJEDA CARDENAS | F10: PROFESIONAL | G10: PROFESIONAL UNIVERSITARIO | H10: 219 | I10: 13 | J10: 219-13 | K10: DIRECCIÓN DISTRITAL DE POLÍTICA JURÍDICA | L10: realizar la administración de los sistemas de información jurídica, de acuerdo con los lineamientos y parámetros establecidos. | M10: 1.Recopilar y analizar la información registrada en los Sistemas de Información Jurídica en procura de la gestión de la información de manera oportuna y veraz. 2.Generar los informes requeridos, en relación con los Sistemas de Información Jurídica, de manera oportuna. 3.Efectuar las capacitaciones periódicas a los usuarios sobre el manejo de los Sistemas de Información Jurídica de tal forma que les permitan tener las herramientas para la consulta y/o funcionamiento de los mismos. 4.Realizar la orientación sobre el registro de la información y el manejo de los Sistemas de Información Jurídica de manera eficiente y efectiva. 5.Realizar el seguimiento y control técnico de los Sistemas de Información Jurídica, con el fin de identificar los problemas presentados en la operación y solicitar las mejoras correspondientes a la dependencia competente. 6.Establecer alternativas de solución a las problemáticas técnicas presentadas en los Sistemas de Información Jurídica para que contribuya al fortalecimiento de la función pública. 7.Desempeñar las demás funciones que le asigne el superior inmediato de acuerdo a la naturaleza del cargo. | N10: Estudio: Título profesional en: Ingeniería de Sistemas, Ingeniería Telemática, o Ingeniería Informática; del núcleo básico de conocimiento en Ingeniería de Sistemas, Telemática y afines. Tarjeta o matricula profesional en los casos reglamentados por la Ley. | O10: 210-211 RES. 020 de 2019
A11: 22446641 | B11: ROSA ISABEL SIERRA LABORDE | C11: CARRERA ADMINISTRATIVA | D11: 1013608357 | E11: MONICA JULIANA SANMIGUEL ROJAS | F11: PROFESIONAL | G11: PROFESIONAL UNIVERSITARIO | H11: 219 | I11: 3 | J11: 219-3 | K11: DIRECCIÓN DISTRITAL DE POLÍTICA JURÍDICA | L11: proyectar los derechos de petición y solicitudes formuladas a la dependencia, así como realizar el análisis de la información contenida en los sistemas de información jurídica, de manera oportuna y en concordancia con la normatividad vigente. | M11: 1.Proyectar las respuestas a la solicitudes, derechos de petición en asuntos de complejidad baja, acorde con los tiempos estipulados por ley. 2.Realizar el análisis de la información contenida en los sistemas de información jurídicos, que le sean asignados, con criterios eficacia y oportunidad. 3.Realizar la actualización y/o elaboración de los documentos de relatoría en asuntos de complejidad media, con la oportunidad requerida. 4.Efectuar el seguimiento a las jornadas de actualización jurídica del cuerpo de abogados del Distrito Capital y presentar los informes correspondientes para la toma de decisiones por parte del jefe de la dependencia. 5.Desempeñar las demás funciones que le asigne el superior inmediato de acuerdo a la naturaleza del cargo. | N11: Estudio: Título profesional en: Derecho; Derecho y Ciencias Sociales; Derecho y Ciencias Políticas; Derecho y Ciencias Humanas; Derecho y Ciencias Administrativas; Derecho Ciencias Políticas y Relaciones Internacionales; Jurisprudencia; Justicia y Derecho; ó Leyes y Jurisprudencia; del núcleo básico de conocimiento en Derecho y afines. Tarjeta o matricula profesional en los casos reglamentados por la Ley. | O11: 230-232 RES. 020 de 2019
A12: 79894605 | B12: JHON ALEXANDER TIBADUIZA CASTAÑEDA | C12: PROVISIONALIDAD | D12: 1032489040 | E12: LEIDY JOHANNA ALONSO GUTIERREZ | F12: PROFESIONAL | G12: PROFESIONAL UNIVERSITARIO | H12: 219 | I12: 1 | J12: 219-1 | K12: DIRECCIÓN DISTRITAL DE POLÍTICA JURÍDICA | L12: Realizar los procesos de análisis de la información jurídica e incorporarlos en los sistemas jurídicos, así como las actividades requeridas para los eventos de orientación y actualización jurídica al cuerpo de abogados del distrito capital. | M12: 1.Realizar las actividades requeridas para los eventos de orientación y actualización jurídica al cuerpo de Abogados del Distrito Capital, con criterios de eficacia y oportunidad. 2.Realizar la tabulación y el análisis de las encuestas de satisfacción de los eventos de orientación y actualización jurídica al cuerpo de Abogados del Distrito Capital, de manera oportuna. 3.Realizar la publicación de las memorias correspondientes a los eventos y/o la difusión web de las conferencias realizadas, con el fin de mantener actualizada la información. 4.Realizar el análisis de la información jurídica contenida en los sistemas de información jurídicos, que le sean asignados, con criterios de eficacia y oportunidad. 5.Realizar la actualización y/o elaboración de los documentos de relatoría en asuntos de complejidad baja, de manera oportuna. 6.Incorporar los documentos jurídicos en los sistemas de información jurídica, con calidad y oportunidad. 7.Desempeñar las demás funciones que le asigne el superior inmediato de acuerdo a la naturaleza del cargo. | N12: Estudio: Título profesional en: Derecho; Derecho y Ciencias Sociales; Derecho y Ciencias Políticas; Derecho y Ciencias Humanas; Derecho y Ciencias Administrativas; Derecho Ciencias Políticas y Relaciones Internacionales; Jurisprudencia; Justicia y Derecho; ó Leyes y Jurisprudencia; del núcleo básico de conocimiento en Derecho y afines. Tarjeta o matricula profesional en los casos reglamentados por la Ley. | O12: 232-234 RES. 020 de 2019
A13: 30333406 | B13: ALEXANDRA AVILA MARIN | C13: CARRERA ADMINISTRATIVA | D13: 30333406 | E13: ALEXANDRA AVILA MARIN | F13: PROFESIONAL | G13: PROFESIONAL UNIVERSITARIO | H13: 219 | I13: 1 | J13: 219-1 | K13: DIRECCIÓN DISTRITAL DE POLÍTICA JURÍDICA | L13: realizar la incorporación y catalogación de publicaciones y documentos jurídicos en los sistemas de información jurídica, de acuerdo con los parámetros establecidos. | M13: 1.Realizar el trámite de los registros del ISBN y/o ISSN, de acuerdo a los lineamientos técnicos. 2.Proyectar la solicitud de artes gráficas y/o enviar el documento a impresión cuando sea requerido, de conformidad con los requerimientos de las dependencias. 3.Elaborar el plan operativo del Sistema de Información Biblioteca Virtual de Bogotá o el que haga sus veces, de acuerdo con las necesidades y presentar los informes correspondientes dentro de la oportunidad requerida. 4.Establecer y orientar los servicios técnicos y administrativos del Sistema de Información Biblioteca Virtual de Bogotá o el que haga sus veces, para la implementación y desarrollo del mismo. 5.Catalogar, clasificar, analizar y publicar los libros y documentos jurídicos en los Sistemas de Información Jurídica, de acuerdo con los parámetros establecidos. 6.Orientar a los/as funcionarios/as del Distrito Capital en el uso de las fuentes de información y contenidos del Sistema de Información Biblioteca Virtual de Bogotá o el que haga sus veces, para la correcta incorporación de la información, consulta y uso del Sistema. 7.Desempeñar las demás funciones que le asigne el superior inmediato de acuerdo a la naturaleza del cargo. | N13: Estudio: Título profesional en disciplina académica: Ciencias de la Información y la Documentación Bibliotecología y Archivística, Ciencia de la Información – Bibliotecología, Bibliotecología y Archivística, Archivística, Bibliotecología; del núcleo básico de conocimiento en Bibliotecología, otros de Ciencias Sociales y Humanas. Tarjeta o matricula profesional en los casos reglamentados por la Ley. | O13: 232-234 RES. 020 de 2019
A14: 1018499480 | B14: DAYANNA LORENA VELASQUEZ FLOREZ | C14: PROVISIONALIDAD | D14: 22446641 | E14: ROSA ISABEL SIERRA LABORDE | F14: TÉCNICO OPERATIVO | G14: TÉCNICO OPERATIVO | H14: 314 | I14: 15 | J14: 314-15 | K14: DIRECCIÓN DISTRITAL DE POLÍTICA JURÍDICA | L14: asistir en labores técnicas con oportunidad y eficiencia en relación con las actividades misionales de la dependencia, de conformidad con los lineamientos institucionales y la normatividad vigente. | M14: 1.Incorporar la información a los sistemas de información jurídica de la dependencia, verificando la autenticidad de la misma y con la oportunidad requerida. 2.Elaborar dentro de los sistemas de información los vínculos de las normas y las notas de vigencia que le sean solicitados con la oportunidad y precisión requerida. 3.Actualizar la información contenida en los sistemas de información jurídica de la dependencia oportunamente. 4.Revisar la información incorporada al Sistema Régimen Legal de Bogotá – RLB de baja y media complejidad. 5.Analizar y determinar las causas de las no conformidades detectadas en los Sistemas de Información Jurídica y realizar los correctivos necesarios, generando información confiable. 6.Elaborar los documentos que deba presentar en razón a los asuntos de la dependencia, de forma oportuna. 7.Desempeñar las demás funciones que le asigne el superior inmediato de acuerdo a la naturaleza del cargo. | N14: Estudio: Título de formación técnica profesional o tecnológica o terminación y aprobación del pénsum académico de educación superior en formación profesional en: Derecho, Jurídica, Gestión Judicial, Investigación Judicial, Procedimientos Judiciales, Procedimientos Jurídicos, o Proceso Judicial; del núcleo básico de Derecho y afines. | O14: 266-267 RES. 020 de 2019
A15: 1010176886 | B15: JOAN SEBASTIAN FLECHAS ALONSO | C15: CARRERA ADMINISTRATIVA | D15: 1010176886 | E15: JOAN SEBASTIAN FLECHAS ALONSO | F15: TÉCNICO OPERATIVO | G15: TÉCNICO OPERATIVO | H15: 314 | I15: 15 | J15: 314-15 | K15: DIRECCIÓN DISTRITAL DE POLÍTICA JURÍDICA | L15: asistir en labores técnicas con oportunidad y eficiencia en relación con las actividades misionales de la dependencia, de conformidad con los lineamientos institucionales y la normatividad vigente. | M15: 1.Incorporar la información a los sistemas de información jurídica de la dependencia, verificando la autenticidad de la misma y con la oportunidad requerida. 2.Elaborar dentro de los sistemas de información los vínculos de las normas y las notas de vigencia que le sean solicitados con la oportunidad y precisión requerida. 3.Actualizar la información contenida en los sistemas de información jurídica de la dependencia oportunamente. 4.Revisar la información incorporada al Sistema Régimen Legal de Bogotá – RLB de baja y media complejidad. 5.Analizar y determinar las causas de las no conformidades detectadas en los Sistemas de Información Jurídica y realizar los correctivos necesarios, generando información confiable. 6.Elaborar los documentos que deba presentar en razón a los asuntos de la dependencia, de forma oportuna. 7.Desempeñar las demás funciones que le asigne el superior inmediato de acuerdo a la naturaleza del cargo. | N15: Estudio: Título de formación técnica profesional o tecnológica o terminación y aprobación del pénsum académico de educación superior en formación profesional en: Derecho, Jurídica, Gestión Judicial, Investigación Judicial, Procedimientos Judiciales, Procedimientos Jurídicos, o Proceso Judicial; del núcleo básico de Derecho y afines. | O15: 266-267 RES. 020 de 2019

Sheet PLANTA INICIAL
B1: CC | C1: NOMBRE | D1: N | E1: NIVEL | F1: NOMENCLATURA_ADMIN | G1: CÓDIGO | H1: GRADO | J1: DEPENDENCIA | K1: NOMBRAMIENTO
A2: 1 | C2: VACANTE DEFINITIVA | D2: 1 | E2: DIRECTIVO | F2: DIRECTOR TÉCNICO | G2: 9 | H2: 7 | I2: =G2&"-"&H2 -> 9-7 | J2: DIRECCIÓN CORPORATIVA | L2: =C2=P2 -> FALSE | M2: =J2=AH2 -> TRUE | O2: 39546837 | P2: VÁSQUEZ ROJAS ETHEL | Q2: LIBRE NOMBRAMIENTO Y REMOCIÓN | R2: NOMBRAMIENTO ORDINARIO | S2: 42621 | T2: 42622 | U2: MUJER | V2: 53 | X2: VACANTE DEFINITIVA | AB2: OCUPADO | AC2: DIRECTIVO | AD2: DIRECTOR TÉCNICO | AE2: 9 | AF2: 7 | AG2: =AE2&"-"&AF2 -> 9-7 | AH2: DIRECCIÓN CORPORATIVA | AI2: =AG2=I2 -> TRUE
A3: 2 | C3: VACANTE DEFINITIVA | D3: 1 | E3: DIRECTIVO | F3: DIRECTOR TÉCNICO | G3: 9 | H3: 7 | I3: =G3&"-"&H3 -> 9-7 | J3: DIRECCIÓN DISTRITAL DE ASUNTOS DISCIPLINARIOS | K3: LIBRE NOMBRAMIENTO | L3: =C3=P3 -> FALSE | M3: =J3=AH3 -> TRUE | O3: 52394165 | P3: TOBÓN DÍAZ ALEJANDRA | Q3: LIBRE NOMBRAMIENTO Y REMOCIÓN | R3: EN ENCARGO | S3: 42585 | T3: 42404 | U3: MUJER | V3: 43 | W3: ENCARGO | X3: VACANTE DEFINITIVA | Y3: E02 | Z3: 1 | AB3: OCUPADO | AC3: DIRECTIVO | AD3: DIRECTOR TÉCNICO | AE3: 9 | AF3: 7 | AG3: =AE3&"-"&AF3 -> 9-7 | AH3: DIRECCIÓN DISTRITAL DE ASUNTOS DISCIPLINARIOS | AI3: =AG3=I3 -> TRUE
A4: 3 | B4: 28915546 | C4: RODRIGUEZ QUIMBAYO LUZ ELENA | D4: 1 | E4: DIRECTIVO | F4: DIRECTOR TÉCNICO | G4: 9 | H4: 7 | I4: =G4&"-"&H4 -> 9-7 | J4: DIRECCIÓN DISTRITAL DE DEFENSA JUDICIAL Y PREVENCIÓN DEL DAÑO ANTIJURÍDICO | K4: LIBRE NOMBRAMIENTO | L4: =C4=P4 -> TRUE | M4: =J4=AH4 -> TRUE | O4: 28915546 | P4: RODRIGUEZ QUIMBAYO LUZ ELENA | Q4: LIBRE NOMBRAMIENTO Y REMOCIÓN | R4: NOMBRAMIENTO ORDINARIO | S4: 42585 | T4: 42493 | U4: MUJER | V4: 52 | AB4: OCUPADO | AC4: DIRECTIVO | AD4: DIRECTOR TÉCNICO | AE4: 9 | AF4: 7 | AG4: =AE4&"-"&AF4 -> 9-7 | AH4: DIRECCIÓN DISTRITAL DE DEFENSA JUDICIAL Y PREVENCIÓN DEL DAÑO ANTIJURÍDICO | AI4: =AG4=I4 -> TRUE
A5: 4 | C5: VACANTE DEFINITIVA | D5: 1 | E5: DIRECTIVO | F5: DIRECTOR TÉCNICO | G5: 9 | H5: 7 | I5: =G5&"-"&H5 -> 9-7 | J5: DIRECCIÓN DISTRITAL DE DOCTRINA JURÍDICA | L5: =C5=P5 -> FALSE | M5: =J5=AH5 -> TRUE | O5: 51743499 | P5: ANA LUCY CASTRO CASTRO | Q5: LIBRE NOMBRAMIENTO Y REMOCIÓN | R5: NOMBRAMIENTO ORDINARIO | S5: 42607 | T5: 42461 | U5: MUJER | V5: 58 | AB5: OCUPADO | AC5: DIRECTIVO | AD5: DIRECTOR TÉCNICO | AE5: 9 | AF5: 7 | AG5: =AE5&"-"&AF5 -> 9-7 | AH5: DIRECCIÓN DISTRITAL DE DOCTRINA JURÍDICA | AI5: =AG5=I5 -> TRUE
A6: 5 | B6: 35521959 | C6: MARTÍNEZ SIERRA GLORIA EDITH | D6: 1 | E6: DIRECTIVO | F6: DIRECTOR TÉCNICO | G6: 9 | H6: 7 | I6: =G6&"-"&H6 -> 9-7 | J6: DIRECCIÓN DISTRITAL DE POLÍTICA E INFORMÁTICA JURÍDICA | K6: LIBRE NOMBRAMIENTO | L6: =C6=P6 -> TRUE | M6: =J6=AH6 -> TRUE | O6: 35521959 | P6: MARTÍNEZ SIERRA GLORIA EDITH | Q6: LIBRE NOMBRAMIENTO Y REMOCIÓN | R6: NOMBRAMIENTO ORDINARIO | S6: 42585 | T6: 42461 | U6: MUJER | V6: 53 | AB6: OCUPADO | AC6: DIRECTIVO | AD6: DIRECTOR TÉCNICO | AE6: 9 | AF6: 7 | AG6: =AE6&"-"&AF6 -> 9-7 | AH6: DIRECCIÓN DISTRITAL DE POLÍTICA E INFORMÁTICA JURÍDICA | AI6: =AG6=I6 -> TRUE
A7: 6 | B7: 39742375 | C7: ROBAYO ALFONSO ANDREA | D7: 1 | E7: DIRECTIVO | F7: DIRECTOR TÉCNICO | G7: 9 | H7: 7 | I7: =G7&"-"&H7 -> 9-7 | J7: DIRECCIÓN DISTRITAL DE INSPECCIÓN VIGILANCIA Y CONTROL DE LAS ENTIDADES SIN ÁNIMO DE LUCRO | K7: LIBRE NOMBRAMIENTO | L7: =C7=P7 -> TRUE | M7: =J7=AH7 -> TRUE | O7: 39742375 | P7: ROBAYO ALFONSO ANDREA | Q7: LIBRE NOMBRAMIENTO Y REMOCIÓN | R7: NOMBRAMIENTO ORDINARIO | S7: 42585 | T7: 42523 | U7: MUJER | V7: 45 | AB7: OCUPADO | AC7: DIRECTIVO | AD7: DIRECTOR TÉCNICO | AE7: 9 | AF7: 7 | AG7: =AE7&"-"&AF7 -> 9-7 | AH7: DIRECCIÓN DISTRITAL DE INSPECCIÓN VIGILANCIA Y CONTROL DE LAS ENTIDADES SIN ÁNIMO DE LUCRO | AI7: =AG7=I7 -> TRUE
A8: 7 | C8: VACANTE DEFINITIVA | D8: 1 | E8: DIRECTIVO | F8: JEFE DE OFICINA | G8: 6 | H8: 6 | I8: =G8&"-"&H8 -> 6-6 | J8: OFICINA DE CONTROL INTERNO | L8: =C8=P8 -> TRUE | M8: =J8=AH8 -> TRUE | P8: VACANTE DEFINITIVA | R8: VACANTE DEFINITIVA | X8: VACANTE DEFINITIVA | AB8: VACANTE DEFINITIVA | AC8: DIRECTIVO | AD8: JEFE DE OFICINA | AE8: 6 | AF8: 6 | AG8: =AE8&"-"&AF8 -> 6-6 | AH8: OFICINA DE CONTROL INTERNO | AI8: =AG8=I8 -> TRUE
A9: 8 | B9: 51740995 | C9: HERNANDEZ CORZO DALILA ASTRID | D9: 1 | E9: DIRECTIVO | F9: SECRETARIA JURIDICA | G9: 20 | H9: 9 | I9: =G9&"-"&H9 -> 20-9 | J9: DESPACHO | K9: LIBRE NOMBRAMIENTO | L9: =C9=P9 -> TRUE | M9: =J9=AH9 -> TRUE | O9: 51740995 | P9: HERNANDEZ CORZO DALILA ASTRID | Q9: LIBRE NOMBRAMIENTO Y REMOCIÓN | R9: NOMBRAMIENTO ORDINARIO | S9: 42585 | T9: 42394 | U9: MUJER | V9: 57 | AB9: OCUPADO | AC9: DIRECTIVO | AD9: SECRETARIA JURIDICA | AE9: 20 | AF9: 9 | AG9: =AE9&"-"&AF9 -> 20-9 | AH9: DESPACHO | AI9: =AG9=I9 -> TRUE
A10: 9 | B10: 79543049 | C10: BURGOS DURANGO WILLIAM ANTONIO | D10: 1 | E10: DIRECTIVO | F10: SUBSECRETARIO | G10: 45 | H10: 8 | I10: =G10&"-"&H10 -> 45-8 | J10: SUBSECRETARÍA JURÍDICA | K10: LIBRE NOMBRAMIENTO | L10: =C10=P10 -> TRUE | M10: =J10=AH10 -> TRUE | O10: 79543049 | P10: BURGOS DURANGO WILLIAM ANTONIO | Q10: LIBRE NOMBRAMIENTO Y REMOCIÓN | R10: NOMBRAMIENTO ORDINARIO | S10: 42585 | T10: 42403 | U10: HOMBRE | V10: 51 | AB10: OCUPADO | AC10: DIRECTIVO | AD10: SUBSECRETARIO | AE10: 45 | AF10: 8 | AG10: =AE10&"-"&AF10 -> 45-8 | AH10: SUBSECRETARÍA JURÍDICA | AI10: =AG10=I10 -> TRUE
A11: 10 | B11: 1085262099 | C11: BURBANO SÁNCHEZ MARÍA ANGÉLICA | D11: 2 | E11: ASESOR | F11: ASESOR | G11: 105 | H11: 5 | I11: =G11&"-"&H11 -> 105-5 | J11: DESPACHO | K11: LIBRE NOMBRAMIENTO | L11: =C11=P11 -> FALSE | M11: =J11=AH11 -> TRUE | O11: 79317479 | P11: CORDOBA DELGADO JOSE IGNACIO | Q11: LIBRE NOMBRAMIENTO Y REMOCIÓN | R11: NOMBRAMIENTO ORDINARIO | S11: 42632 | T11: 42632 | U11: HOMBRE | V11: 60 | X11: VACANTE DEFINITIVA | AB11: OCUPADO | AC11: ASESOR | AD11: ASESOR | AE11: 105 | AF11: 5 | AG11: =AE11&"-"&AF11 -> 105-5 | AH11: DESPACHO | AI11: =AG11=I11 -> TRUE
A12: 11 | B12: 80040965 | C12: CUELLAR TRUJILLO PEDRO ANDRÉS | D12: 2 | E12: ASESOR | F12: ASESOR | G12: 105 | H12: 5 | I12: =G12&"-"&H12 -> 105-5 | J12: DESPACHO | K12: LIBRE NOMBRAMIENTO | L12: =C12=P12 -> TRUE | M12: =J12=AH12 -> TRUE | O12: 80040965 | P12: CUELLAR TRUJILLO PEDRO ANDRÉS | Q12: LIBRE NOMBRAMIENTO Y REMOCIÓN | R12: NOMBRAMIENTO ORDINARIO | S12: 42585 | T12: 42401 | U12: HOMBRE | V12: 39 | AB12: OCUPADO | AC12: ASESOR | AD12: ASESOR | AE12: 105 | AF12: 5 | AG12: =AE12&"-"&AF12 -> 105-5 | AH12: DESPACHO | AI12: =AG12=I12 -> TRUE
A13: 12 | B13: 72291125 | C13: ESPINOSA OTERO ANDRES MAURICIO | D13: 2 | E13: ASESOR | F13: ASESOR | G13: 105 | H13: 5 | I13: =G13&"-"&H13 -> 105-5 | J13: DESPACHO | K13: LIBRE NOMBRAMIENTO | L13: =C13=P13 -> TRUE | M13: =J13=AH13 -> TRUE | O13: 72291125 | P13: ESPINOSA OTERO ANDRES MAURICIO | Q13: LIBRE NOMBRAMIENTO Y REMOCIÓN | R13: NOMBRAMIENTO ORDINARIO | S13: 42585 | T13: 42468 | U13: HOMBRE | V13: 38 | AB13: OCUPADO | AC13: ASESOR | AD13: ASESOR | AE13: 105 | AF13: 5 | AG13: =AE13&"-"&AF13 -> 105-5 | AH13: DESPACHO | AI13: =AG13=I13 -> TRUE
A14: 13 | B14: 52233911 | C14: RODRÍGUEZ BARRERA NOHORA PATRICIA | D14: 2 | E14: ASESOR | F14: ASESOR | G14: 105 | H14: 5 | I14: =G14&"-"&H14 -> 105-5 | J14: DESPACHO | K14: LIBRE NOMBRAMIENTO | L14: =C14=P14 -> TRUE | M14: =J14=AH14 -> TRUE | O14: 52233911 | P14: RODRÍGUEZ BARRERA NOHORA PATRICIA | Q14: LIBRE NOMBRAMIENTO Y REMOCIÓN | R14: NOMBRAMIENTO ORDINARIO | S14: 42585 | T14: 35900 | U14: MUJER | V14: 44 | AB14: OCUPADO | AC14: ASESOR | AD14: ASESOR | AE14: 105 | AF14: 5 | AG14: =AE14&"-"&AF14 -> 105-5 | AH14: DESPACHO | AI14: =AG14=I14 -> TRUE
A15: 14 | B15: 52394165 | C15: TOBÓN DÍAZ ALEJANDRA | D15: 2 | E15: ASESOR | F15: ASESOR | G15: 105 | H15: 5 | I15: =G15&"-"&H15 -> 105-5 | J15: DESPACHO | K15: LIBRE NOMBRAMIENTO | L15: =C15=P15 -> FALSE | M15: =J15=AH15 -> TRUE | P15: VACANTE TEMPORAL | R15: VACANTE TEMPORAL | X15: TOBÓN DÍAZ ALEJANDRA | Y15: E02 | Z15: VT | AB15: OCUPADO | AC15: ASESOR | AD15: ASESOR | AE15: 105 | AF15: 5 | AG15: =AE15&"-"&AF15 -> 105-5 | AH15: DESPACHO | AI15: =AG15=I15 -> TRUE
A16: 15 | C16: VACANTE DEFINITIVA | D16: 2 | E16: ASESOR | F16: JEFE DE OFICINA | G16: 115 | H16: 6 | I16: =G16&"-"&H16 -> 115-6 | J16: OFICINA ASESORA DE PLANEACIÓN | L16: =C16=P16 -> TRUE | M16: =J16=AH16 -> TRUE | P16: VACANTE DEFINITIVA | R16: VACANTE DEFINITIVA | X16: VACANTE DEFINITIVA | AB16: VACANTE DEFINITIVA | AC16: ASESOR | AD16: JEFE DE OFICINA | AE16: 115 | AF16: 6 | AG16: =AE16&"-"&AF16 -> 115-6 | AH16: OFICINA ASESORA DE PLANEACIÓN | AI16: =AG16=I16 -> TRUE
A17: 16 | C17: VACANTE DEFINITIVA | D17: 2 | E17: ASESOR | F17: JEFE DE OFICINA | G17: 115 | H17: 6 | I17: =G17&"-"&H17 -> 115-6 | J17: OFICINA DE TECNOLOGÍA DE LA INFORMACIÓN, SISTEMAS Y COMUNICACIONES | L17: =C17=P17 -> FALSE | M17: =J17=AH17 -> TRUE | O17: 19498970 | P17: OJEDA MONCAYO DIEGO EMILIO | Q17: LIBRE NOMBRAMIENTO Y REMOCIÓN | R17: NOMBRAMIENTO ORDINARIO | S17: 42622 | T17: 42622 | U17: HOMBRE | V17: 59 | X17: VACANTE DEFINITIVA | AB17: OCUPADO | AC17: ASESOR | AD17: JEFE DE OFICINA | AE17: 115 | AF17: 6 | AG17: =AE17&"-"&AF17 -> 115-6 | AH17: OFICINA DE TECNOLOGÍA DE LA INFORMACIÓN, SISTEMAS Y COMUNICACIONES | AI17: =AG17=I17 -> TRUE
A18: 17 | B18: 79299847 | C18: MONTOYA MALDONADO JESÚS MARÍA | D18: 3 | E18: PROFESIONAL | F18: PROFESIONAL ESPECIALIZADO | G18: 222 | H18: 27 | I18: =G18&"-"&H18 -> 222-27 | J18: DIRECCIÓN CORPORATIVA | K18: CARRERA ADMINISTRATIVA | L18: =C18=P18 -> TRUE | M18: =J18=AH18 -> TRUE | O18: 79299847 | P18: MONTOYA MALDONADO JESÚS MARÍA | Q18: CARRERA ADMINISTRATIVA | R18: CARRERA ADMINISTRATIVA | S18: 42585 | T18: 33724 | U18: HOMBRE | V18: 60 | AB18: OCUPADO | AC18: PROFESIONAL | AD18: PROFESIONAL ESPECIALIZADO | AE18: 222 | AF18: 27 | AG18: =AE18&"-"&AF18 -> 222-27 | AH18: DIRECCIÓN CORPORATIVA | AI18: =AG18=I18 -> TRUE
A19: 18 | C19: VACANTE DEFINITIVA | D19: 3 | E19: PROFESIONAL | F19: PROFESIONAL ESPECIALIZADO | G19: 222 | H19: 27 | I19: =G19&"-"&H19 -> 222-27 | J19: DIRECCIÓN CORPORATIVA | L19: =C19=P19 -> TRUE | M19: =J19=AH19 -> TRUE | P19: VACANTE DEFINITIVA | R19: VACANTE DEFINITIVA | X19: VACANTE DEFINITIVA | AB19: VACANTE DEFINITIVA | AC19: PROFESIONAL | AD19: PROFESIONAL ESPECIALIZADO | AE19: 222 | AF19: 27 | AG19: =AE19&"-"&AF19 -> 222-27 | AH19: DIRECCIÓN CORPORATIVA | AI19: =AG19=I19 -> TRUE
A20: 19 | B20: 52236487 | C20: MORENO GUERRERO DEYSI YANIRA | D20: 3 | E20: PROFESIONAL | F20: PROFESIONAL ESPECIALIZADO | G20: 222 | H20: 27 | I20: =G20&"-"&H20 -> 222-27 | J20: DIRECCIÓN DISTRITAL DE ASUNTOS DISCIPLINARIOS | K20: CARRERA ADMINISTRATIVA | L20: =C20=P20 -> TRUE | M20: =J20=AH20 -> TRUE | O20: 52236487 | P20: MORENO GUERRERO DEYSI YANIRA | Q20: CARRERA ADMINISTRATIVA | R20: CARRERA ADMINISTRATIVA | S20: 42585 | T20: 38093 | U20: MUJER | V20: 44 | AB20: OCUPADO | AC20: PROFESIONAL | AD20: PROFESIONAL ESPECIALIZADO | AE20: 222 | AF20: 27 | AG20: =AE20&"-"&AF20 -> 222-27 | AH20: DIRECCIÓN DISTRITAL DE ASUNTOS DISCIPLINARIOS | AI20: =AG20=I20 -> TRUE
A21: 20 | C21: VACANTE DEFINITIVA | D21: 3 | E21: PROFESIONAL | F21: PROFESIONAL ESPECIALIZADO | G21: 222 | H21: 27 | I21: =G21&"-"&H21 -> 222-27 | J21: SUBSECRETARÍA JURÍDICA | L21: =C21=P21 -> TRUE | M21: =J21=AH21 -> TRUE | P21: VACANTE DEFINITIVA | R21: VACANTE DEFINITIVA | X21: VACANTE DEFINITIVA | AB21: VACANTE DEFINITIVA | AC21: PROFESIONAL | AD21: PROFESIONAL ESPECIALIZADO | AE21: 222 | AF21: 27 | AG21: =AE21&"-"&AF21 -> 222-27 | AH21: SUBSECRETARÍA JURÍDICA | AI21: =AG21=I21 -> TRUE
A22: 21 | C22: VACANTE DEFINITIVA | D22: 3 | E22: PROFESIONAL | F22: PROFESIONAL ESPECIALIZADO | G22: 222 | H22: 27 | I22: =G22&"-"&H22 -> 222-27 | J22: SUBSECRETARÍA JURÍDICA | L22: =C22=P22 -> TRUE | M22: =J22=AH22 -> TRUE | P22: VACANTE DEFINITIVA | R22: VACANTE DEFINITIVA | X22: VACANTE DEFINITIVA | AB22: VACANTE DEFINITIVA | AC22: PROFESIONAL | AD22: PROFESIONAL ESPECIALIZADO | AE22: 222 | AF22: 27 | AG22: =AE22&"-"&AF22 -> 222-27 | AH22: SUBSECRETARÍA JURÍDICA | AI22: =AG22=I22 -> TRUE
A23: 22 | C23: VACANTE DEFINITIVA | D23: 3 | E23: PROFESIONAL | F23: PROFESIONAL ESPECIALIZADO | G23: 222 | H23: 27 | I23: =G23&"-"&H23 -> 222-27 | J23: SUBSECRETARÍA JURÍDICA | L23: =C23=P23 -> TRUE | M23: =J23=AH23 -> TRUE | P23: VACANTE DEFINITIVA | R23: VACANTE DEFINITIVA | X23: VACANTE DEFINITIVA | AB23: VACANTE DEFINITIVA | AC23: PROFESIONAL | AD23: PROFESIONAL ESPECIALIZADO | AE23: 222 | AF23: 27 | AG23: =AE23&"-"&AF23 -> 222-27 | AH23: SUBSECRETARÍA JURÍDICA | AI23: =AG23=I23 -> TRUE
A24: 23 | B24: 51798311 | C24: AMAYA SALAZAR MARTHA YOLANDA | D24: 3 | E24: PROFESIONAL | F24: PROFESIONAL ESPECIALIZADO | G24: 222 | H24: 27 | I24: =G24&"-"&H24 -> 222-27 | J24: DIRECCIÓN DISTRITAL DE DEFENSA JUDICIAL Y PREVENCIÓN DEL DAÑO ANTIJURÍDICO | K24: CARRERA ADMINISTRATIVA | L24: =C24=P24 -> TRUE | M24: =J24=AH24 -> TRUE | O24: 51798311 | P24: AMAYA SALAZAR MARTHA YOLANDA | Q24: CARRERA ADMINISTRATIVA | R24: CARRERA ADMINISTRATIVA | S24: 42585 | T24: 34457 | U24: MUJER | V24: 57 | AB24: OCUPADO | AC24: PROFESIONAL | AD24: PROFESIONAL ESPECIALIZADO | AE24: 222 | AF24: 27 | AG24: =AE24&"-"&AF24 -> 222-27 | AH24: DIRECCIÓN DISTRITAL DE DEFENSA JUDICIAL Y PREVENCIÓN DEL DAÑO ANTIJURÍDICO | AI24: =AG24=I24 -> TRUE
A25: 24 | B25: 79153811 | C25: CADENA ROJAS ERNESTO | D25: 3 | E25: PROFESIONAL | F25: PROFESIONAL ESPECIALIZADO | G25: 222 | H25: 27 | I25: =G25&"-"&H25 -> 222-27 | J25: DIRECCIÓN DISTRITAL DE DEFENSA JUDICIAL Y PREVENCIÓN DEL DAÑO ANTIJURÍDICO | K25: CARRERA ADMINISTRATIVA | L25: =C25=P25 -> TRUE | M25: =J25=AH25 -> TRUE | O25: 79153811 | P25: CADENA ROJAS ERNESTO | Q25: CARRERA ADMINISTRATIVA | R25: CARRERA ADMINISTRATIVA | S25: 42585 | T25: 34256 | U25: HOMBRE | V25: 60 | AB25: OCUPADO | AC25: PROFESIONAL | AD25: PROFESIONAL ESPECIALIZADO | AE25: 222 | AF25: 27 | AG25: =AE25&"-"&AF25 -> 222-27 | AH25: DIRECCIÓN DISTRITAL DE DEFENSA JUDICIAL Y PREVENCIÓN DEL DAÑO ANTIJURÍDICO | AI25: =AG25=I25 -> TRUE
A26: 25 | B26: 51569861 | C26: DIAGO CASASBUENAS GLORIA MAGDALENA | D26: 3 | E26: PROFESIONAL | F26: PROFESIONAL ESPECIALIZADO | G26: 222 | H26: 27 | I26: =G26&"-"&H26 -> 222-27 | J26: DIRECCIÓN DISTRITAL DE DEFENSA JUDICIAL Y PREVENCIÓN DEL DAÑO ANTIJURÍDICO | K26: CARRERA ADMINISTRATIVA | L26: =C26=P26 -> TRUE | M26: =J26=AH26 -> TRUE | O26: 51569861 | P26: DIAGO CASASBUENAS GLORIA MAGDALENA | Q26: CARRERA ADMINISTRATIVA | R26: CARRERA ADMINISTRATIVA | S26: 42585 | T26: 34684 | U26: MUJER | V26: 63 | AB26: OCUPADO | AC26: PROFESIONAL | AD26: PROFESIONAL ESPECIALIZADO | AE26: 222 | AF26: 27 | AG26: =AE26&"-"&AF26 -> 222-27 | AH26: DIRECCIÓN DISTRITAL DE DEFENSA JUDICIAL Y PREVENCIÓN DEL DAÑO ANTIJURÍDICO | AI26: =AG26=I26 -> TRUE
A27: 26 | C27: VACANTE DEFINITIVA | D27: 3 | E27: PROFESIONAL | F27: PROFESIONAL ESPECIALIZADO | G27: 222 | H27: 27 | I27: =G27&"-"&H27 -> 222-27 | J27: DIRECCIÓN DISTRITAL DE DEFENSA JUDICIAL Y PREVENCIÓN DEL DAÑO ANTIJURÍDICO | L27: =C27=P27 -> TRUE | M27: =J27=AH27 -> TRUE | P27: VACANTE DEFINITIVA | R27: VACANTE DEFINITIVA | X27: VACANTE DEFINITIVA | AB27: VACANTE DEFINITIVA | AC27: PROFESIONAL | AD27: PROFESIONAL ESPECIALIZADO | AE27: 222 | AF27: 27 | AG27: =AE27&"-"&AF27 -> 222-27 | AH27: DIRECCIÓN DISTRITAL DE DEFENSA JUDICIAL Y PREVENCIÓN DEL DAÑO ANTIJURÍDICO | AI27: =AG27=I27 -> TRUE
A28: 27 | C28: VACANTE DEFINITIVA | D28: 3 | E28: PROFESIONAL | F28: PROFESIONAL ESPECIALIZADO | G28: 222 | H28: 27 | I28: =G28&"-"&H28 -> 222-27 | J28: DIRECCIÓN DISTRITAL DE DEFENSA JUDICIAL Y PREVENCIÓN DEL DAÑO ANTIJURÍDICO | L28: =C28=P28 -> TRUE | M28: =J28=AH28 -> TRUE | P28: VACANTE DEFINITIVA | R28: VACANTE DEFINITIVA | X28: VACANTE DEFINITIVA | AB28: VACANTE DEFINITIVA | AC28: PROFESIONAL | AD28: PROFESIONAL ESPECIALIZADO | AE28: 222 | AF28: 27 | AG28: =AE28&"-"&AF28 -> 222-27 | AH28: DIRECCIÓN DISTRITAL DE DEFENSA JUDICIAL Y PREVENCIÓN DEL DAÑO ANTIJURÍDICO | AI28: =AG28=I28 -> TRUE
A29: 28 | C29: VACANTE DEFINITIVA | D29: 3 | E29: PROFESIONAL | F29: PROFESIONAL ESPECIALIZADO | G29: 222 | H29: 27 | I29: =G29&"-"&H29 -> 222-27 | J29: DIRECCIÓN DISTRITAL DE DEFENSA JUDICIAL Y PREVENCIÓN DEL DAÑO ANTIJURÍDICO | L29: =C29=P29 -> TRUE | M29: =J29=AH29 -> TRUE | P29: VACANTE DEFINITIVA | R29: VACANTE DEFINITIVA | X29: VACANTE DEFINITIVA | AB29: VACANTE DEFINITIVA | AC29: PROFESIONAL | AD29: PROFESIONAL ESPECIALIZADO | AE29: 222 | AF29: 27 | AG29: =AE29&"-"&AF29 -> 222-27 | AH29: DIRECCIÓN DISTRITAL DE DEFENSA JUDICIAL Y PREVENCIÓN DEL DAÑO ANTIJURÍDICO | AI29: =AG29=I29 -> TRUE
A30: 29 | C30: VACANTE DEFINITIVA | D30: 3 | E30: PROFESIONAL | F30: PROFESIONAL ESPECIALIZADO | G30: 222 | H30: 27 | I30: =G30&"-"&H30 -> 222-27 | J30: DIRECCIÓN DISTRITAL DE DEFENSA JUDICIAL Y PREVENCIÓN DEL DAÑO ANTIJURÍDICO | L30: =C30=P30 -> TRUE | M30: =J30=AH30 -> TRUE | P30: VACANTE DEFINITIVA | R30: VACANTE DEFINITIVA | X30: VACANTE DEFINITIVA | AB30: VACANTE DEFINITIVA | AC30: PROFESIONAL | AD30: PROFESIONAL ESPECIALIZADO | AE30: 222 | AF30: 27 | AG30: =AE30&"-"&AF30 -> 222-27 | AH30: DIRECCIÓN DISTRITAL DE DEFENSA JUDICIAL Y PREVENCIÓN DEL DAÑO ANTIJURÍDICO | AI30: =AG30=I30 -> TRUE
A31: 30 | C31: VACANTE DEFINITIVA | D31: 3 | E31: PROFESIONAL | F31: PROFESIONAL ESPECIALIZADO | G31: 222 | H31: 27 | I31: =G31&"-"&H31 -> 222-27 | J31: DIRECCIÓN DISTRITAL DE DEFENSA JUDICIAL Y PREVENCIÓN DEL DAÑO ANTIJURÍDICO | L31: =C31=P31 -> TRUE | M31: =J31=AH31 -> TRUE | P31: VACANTE DEFINITIVA | R31: VACANTE DEFINITIVA | X31: VACANTE DEFINITIVA | AB31: VACANTE DEFINITIVA | AC31: PROFESIONAL | AD31: PROFESIONAL ESPECIALIZADO | AE31: 222 | AF31: 27 | AG31: =AE31&"-"&AF31 -> 222-27 | AH31: DIRECCIÓN DISTRITAL DE DEFENSA JUDICIAL Y PREVENCIÓN DEL DAÑO ANTIJURÍDICO | AI31: =AG31=I31 -> TRUE
A32: 31 | C32: VACANTE DEFINITIVA | D32: 3 | E32: PROFESIONAL | F32: PROFESIONAL ESPECIALIZADO | G32: 222 | H32: 27 | I32: =G32&"-"&H32 -> 222-27 | J32: DIRECCIÓN DISTRITAL DE DEFENSA JUDICIAL Y PREVENCIÓN DEL DAÑO ANTIJURÍDICO | L32: =C32=P32 -> TRUE | M32: =J32=AH32 -> TRUE | P32: VACANTE DEFINITIVA | R32: VACANTE DEFINITIVA | X32: VACANTE DEFINITIVA | AB32: VACANTE DEFINITIVA | AC32: PROFESIONAL | AD32: PROFESIONAL ESPECIALIZADO | AE32: 222 | AF32: 27 | AG32: =AE32&"-"&AF32 -> 222-27 | AH32: DIRECCIÓN DISTRITAL DE DEFENSA JUDICIAL Y PREVENCIÓN DEL DAÑO ANTIJURÍDICO | AI32: =AG32=I32 -> TRUE
A33: 32 | B33: 52363895 | C33: HERNANDEZ LIBREROS ELVIRA LILIANA | D33: 3 | E33: PROFESIONAL | F33: PROFESIONAL ESPECIALIZADO | G33: 222 | H33: 27 | I33: =G33&"-"&H33 -> 222-27 | J33: DIRECCIÓN DISTRITAL DE DOCTRINA JURÍDICA | K33: CARRERA ADMINISTRATIVA | L33: =C33=P33 -> TRUE | M33: =J33=AH33 -> TRUE | O33: 52363895 | P33: HERNANDEZ LIBREROS ELVIRA LILIANA | Q33: CARRERA ADMINISTRATIVA | R33: CARRERA ADMINISTRATIVA | S33: 42585 | T33: 37994 | U33: MUJER | V33: 46 | AB33: OCUPADO | AC33: PROFESIONAL | AD33: PROFESIONAL ESPECIALIZADO | AE33: 222 | AF33: 27 | AG33: =AE33&"-"&AF33 -> 222-27 | AH33: DIRECCIÓN DISTRITAL DE DOCTRINA JURÍDICA | AI33: =AG33=I33 -> TRUE
A34: 33 | B34: 52009661 | C34: TIBAMOSCA VILLAMARÍN SANDRA YANETH | D34: 3 | E34: PROFESIONAL | F34: PROFESIONAL ESPECIALIZADO | G34: 222 | H34: 27 | I34: =G34&"-"&H34 -> 222-27 | J34: DIRECCIÓN DISTRITAL DE DOCTRINA JURÍDICA | K34: CARRERA ADMINISTRATIVA | L34: =C34=P34 -> TRUE | M34: =J34=AH34 -> TRUE | O34: 52009661 | P34: TIBAMOSCA VILLAMARÍN SANDRA YANETH | Q34: CARRERA ADMINISTRATIVA | R34: EN COMISIÓN EN EMPLEO DE L.N.R. O DE PERIODO | S34: 42585 | T34: 35387 | U34: MUJER | V34: 50 | W34: COMISIÒN | AA34: CM | AB34: OCUPADO | AC34: PROFESIONAL | AD34: PROFESIONAL ESPECIALIZADO | AE34: 222 | AF34: 27 | AG34: =AE34&"-"&AF34 -> 222-27 | AH34: DIRECCIÓN DISTRITAL DE DOCTRINA JURÍDICA | AI34: =AG34=I34 -> TRUE
A35: 34 | C35: VACANTE DEFINITIVA | D35: 3 | E35: PROFESIONAL | F35: PROFESIONAL ESPECIALIZADO | G35: 222 | H35: 27 | I35: =G35&"-"&H35 -> 222-27 | J35: DIRECCIÓN DISTRITAL DE DOCTRINA JURÍDICA | L35: =C35=P35 -> TRUE | M35: =J35=AH35 -> TRUE | P35: VACANTE DEFINITIVA | R35: VACANTE DEFINITIVA | X35: VACANTE DEFINITIVA | AB35: VACANTE DEFINITIVA | AC35: PROFESIONAL | AD35: PROFESIONAL ESPECIALIZADO | AE35: 222 | AF35: 27 | AG35: =AE35&"-"&AF35 -> 222-27 | AH35: DIRECCIÓN DISTRITAL DE DOCTRINA JURÍDICA | AI35: =AG35=I35 -> TRUE
A36: 35 | B36: 24179106 | C36: ROJAS SUÁREZ ZULMA | D36: 3 | E36: PROFESIONAL | F36: PROFESIONAL ESPECIALIZADO | G36: 222 | H36: 27 | I36: =G36&"-"&H36 -> 222-27 | J36: DIRECCIÓN DISTRITAL DE POLÍTICA E INFORMÁTICA JURÍDICA | K36: CARRERA ADMINISTRATIVA | L36: =C36=P36 -> TRUE | M36: =J36=AH36 -> TRUE | O36: 24179106 | P36: ROJAS SUÁREZ ZULMA | Q36: CARRERA ADMINISTRATIVA | R36: CARRERA ADMINISTRATIVA | S36: 42585 | T36: 38316 | U36: MUJER | V36: 45 | AB36: OCUPADO | AC36: PROFESIONAL | AD36: PROFESIONAL ESPECIALIZADO | AE36: 222 | AF36: 27 | AG36: =AE36&"-"&AF36 -> 222-27 | AH36: DIRECCIÓN DISTRITAL DE POLÍTICA E INFORMÁTICA JURÍDICA | AI36: =AG36=I36 -> TRUE
A37: 36 | C37: VACANTE DEFINITIVA | D37: 3 | E37: PROFESIONAL | F37: PROFESIONAL ESPECIALIZADO | G37: 222 | H37: 27 | I37: =G37&"-"&H37 -> 222-27 | J37: DIRECCIÓN DISTRITAL DE POLÍTICA E INFORMÁTICA JURÍDICA | L37: =C37=P37 -> TRUE | M37: =J37=AH37 -> TRUE | P37: VACANTE DEFINITIVA | R37: VACANTE DEFINITIVA | X37: VACANTE DEFINITIVA | AB37: VACANTE DEFINITIVA | AC37: PROFESIONAL | AD37: PROFESIONAL ESPECIALIZADO | AE37: 222 | AF37: 27 | AG37: =AE37&"-"&AF37 -> 222-27 | AH37: DIRECCIÓN DISTRITAL DE POLÍTICA E INFORMÁTICA JURÍDICA | AI37: =AG37=I37 -> TRUE
A38: 37 | B38: 19347862 | C38: HERNANDEZ ALBARRACÍN JORGE ELIÉCER | D38: 3 | E38: PROFESIONAL | F38: PROFESIONAL ESPECIALIZADO | G38: 222 | H38: 27 | I38: =G38&"-"&H38 -> 222-27 | J38: DIRECCIÓN DISTRITAL DE INSPECCIÓN VIGILANCIA Y CONTROL DE LAS ENTIDADES SIN ÁNIMO DE LUCRO | K38: CARRERA ADMINISTRATIVA | L38: =C38=P38 -> TRUE | M38: =J38=AH38 -> TRUE | O38: 19347862 | P38: HERNANDEZ ALBARRACÍN JORGE ELIÉCER | Q38: CARRERA ADMINISTRATIVA | R38: CARRERA ADMINISTRATIVA | S38: 42585 | T38: 34464 | U38: HOMBRE | V38: 65 | AB38: OCUPADO | AC38: PROFESIONAL | AD38: PROFESIONAL ESPECIALIZADO | AE38: 222 | AF38: 27 | AG38: =AE38&"-"&AF38 -> 222-27 | AH38: DIRECCIÓN DISTRITAL DE INSPECCIÓN VIGILANCIA Y CONTROL DE LAS ENTIDADES SIN ÁNIMO DE LUCRO | AI38: =AG38=I38 -> TRUE
A39: 38 | C39: VACANTE DEFINITIVA | D39: 3 | E39: PROFESIONAL | F39: PROFESIONAL ESPECIALIZADO | G39: 222 | H39: 27 | I39: =G39&"-"&H39 -> 222-27 | J39: DIRECCIÓN DISTRITAL DE INSPECCIÓN VIGILANCIA Y CONTROL DE LAS ENTIDADES SIN ÁNIMO DE LUCRO | L39: =C39=P39 -> TRUE | M39: =J39=AH39 -> TRUE | P39: VACANTE DEFINITIVA | R39: VACANTE DEFINITIVA | X39: VACANTE DEFINITIVA | AB39: VACANTE DEFINITIVA | AC39: PROFESIONAL | AD39: PROFESIONAL ESPECIALIZADO | AE39: 222 | AF39: 27 | AG39: =AE39&"-"&AF39 -> 222-27 | AH39: DIRECCIÓN DISTRITAL DE INSPECCIÓN VIGILANCIA Y CONTROL DE LAS ENTIDADES SIN ÁNIMO DE LUCRO | AI39: =AG39=I39 -> TRUE
A40: 39 | C40: VACANTE DEFINITIVA | D40: 3 | E40: PROFESIONAL | F40: PROFESIONAL ESPECIALIZADO | G40: 222 | H40: 27 | I40: =G40&"-"&H40 -> 222-27 | J40: DIRECCIÓN DISTRITAL DE INSPECCIÓN VIGILANCIA Y CONTROL DE LAS ENTIDADES SIN ÁNIMO DE LUCRO | L40: =C40=P40 -> TRUE | M40: =J40=AH40 -> TRUE | P40: VACANTE DEFINITIVA | R40: VACANTE DEFINITIVA | X40: VACANTE DEFINITIVA | AB40: VACANTE DEFINITIVA | AC40: PROFESIONAL | AD40: PROFESIONAL ESPECIALIZADO | AE40: 222 | AF40: 27 | AG40: =AE40&"-"&AF40 -> 222-27 | AH40: DIRECCIÓN DISTRITAL DE INSPECCIÓN VIGILANCIA Y CONTROL DE LAS ENTIDADES SIN ÁNIMO DE LUCRO | AI40: =AG40=I40 -> TRUE
A41: 40 | C41: VACANTE DEFINITIVA | D41: 3 | E41: PROFESIONAL | F41: PROFESIONAL ESPECIALIZADO | G41: 222 | H41: 27 | I41: =G41&"-"&H41 -> 222-27 | J41: DIRECCIÓN DISTRITAL DE INSPECCIÓN VIGILANCIA Y CONTROL DE LAS ENTIDADES SIN ÁNIMO DE LUCRO | L41: =C41=P41 -> TRUE | M41: =J41=AH41 -> TRUE | P41: VACANTE DEFINITIVA | R41: VACANTE DEFINITIVA | X41: VACANTE DEFINITIVA | AB41: VACANTE DEFINITIVA | AC41: PROFESIONAL | AD41: PROFESIONAL ESPECIALIZADO | AE41: 222 | AF41: 27 | AG41: =AE41&"-"&AF41 -> 222-27 | AH41: DIRECCIÓN DISTRITAL DE INSPECCIÓN VIGILANCIA Y CONTROL DE LAS ENTIDADES SIN ÁNIMO DE LUCRO | AI41: =AG41=I41 -> TRUE
A42: 41 | B42: 28891891 | C42: MESA VASQUEZ GLORIA ASTRID | D42: 3 | E42: PROFESIONAL | F42: PROFESIONAL ESPECIALIZADO | G42: 222 | H42: 26 | I42: =G42&"-"&H42 -> 222-26 | J42: DIRECCIÓN DISTRITAL DE DEFENSA JUDICIAL Y PREVENCIÓN DEL DAÑO ANTIJURÍDICO | K42: CARRERA ADMINISTRATIVA | L42: =C42=P42 -> TRUE | M42: =J42=AH42 -> TRUE | O42: 28891891 | P42: MESA VASQUEZ GLORIA ASTRID | Q42: CARRERA ADMINISTRATIVA | R42: CARRERA ADMINISTRATIVA | S42: 42585 | T42: 33171 | U42: MUJER | V42: 64 | AB42: OCUPADO | AC42: PROFESIONAL | AD42: PROFESIONAL ESPECIALIZADO | AE42: 222 | AF42: 26 | AG42: =AE42&"-"&AF42 -> 222-26 | AH42: DIRECCIÓN DISTRITAL DE DEFENSA JUDICIAL Y PREVENCIÓN DEL DAÑO ANTIJURÍDICO | AI42: =AG42=I42 -> TRUE
A43: 42 | B43: 6761621 | C43: PARRA LEGUIZAMON JORGE ERNESTO | D43: 3 | E43: PROFESIONAL | F43: PROFESIONAL ESPECIALIZADO | G43: 222 | H43: 26 | I43: =G43&"-"&H43 -> 222-26 | J43: DIRECCIÓN DISTRITAL DE INSPECCIÓN VIGILANCIA Y CONTROL DE LAS ENTIDADES SIN ÁNIMO DE LUCRO | K43: CARRERA ADMINISTRATIVA | L43: =C43=P43 -> TRUE | M43: =J43=AH43 -> TRUE | O43: 6761621 | P43: PARRA LEGUIZAMON JORGE ERNESTO | Q43: CARRERA ADMINISTRATIVA | R43: CARRERA ADMINISTRATIVA | S43: 42585 | T43: 33730 | U43: HOMBRE | V43: 63 | AB43: OCUPADO | AC43: PROFESIONAL | AD43: PROFESIONAL ESPECIALIZADO | AE43: 222 | AF43: 26 | AG43: =AE43&"-"&AF43 -> 222-26 | AH43: DIRECCIÓN DISTRITAL DE INSPECCIÓN VIGILANCIA Y CONTROL DE LAS ENTIDADES SIN ÁNIMO DE LUCRO | AI43: =AG43=I43 -> TRUE
A44: 43 | C44: VACANTE DEFINITIVA | D44: 3 | E44: PROFESIONAL | F44: PROFESIONAL ESPECIALIZADO | G44: 222 | H44: 25 | I44: =G44&"-"&H44 -> 222-25 | J44: DIRECCIÓN DISTRITAL DE INSPECCIÓN VIGILANCIA Y CONTROL DE LAS ENTIDADES SIN ÁNIMO DE LUCRO | L44: =C44=P44 -> TRUE | M44: =J44=AH44 -> TRUE | P44: VACANTE DEFINITIVA | R44: VACANTE DEFINITIVA | X44: VACANTE DEFINITIVA | AB44: VACANTE DEFINITIVA | AC44: PROFESIONAL | AD44: PROFESIONAL ESPECIALIZADO | AE44: 222 | AF44: 25 | AG44: =AE44&"-"&AF44 -> 222-25 | AH44: DIRECCIÓN DISTRITAL DE INSPECCIÓN VIGILANCIA Y CONTROL DE LAS ENTIDADES SIN ÁNIMO DE LUCRO | AI44: =AG44=I44 -> TRUE
A45: 44 | C45: VACANTE DEFINITIVA | D45: 3 | E45: PROFESIONAL | F45: PROFESIONAL ESPECIALIZADO | G45: 222 | H45: 24 | I45: =G45&"-"&H45 -> 222-24 | J45: OFICINA DE TECNOLOGÍA DE LA INFORMACIÓN, SISTEMAS Y COMUNICACIONES | L45: =C45=P45 -> TRUE | M45: =J45=AH45 -> TRUE | P45: VACANTE DEFINITIVA | R45: VACANTE DEFINITIVA | X45: VACANTE DEFINITIVA | AB45: VACANTE DEFINITIVA | AC45: PROFESIONAL | AD45: PROFESIONAL ESPECIALIZADO | AE45: 222 | AF45: 24 | AG45: =AE45&"-"&AF45 -> 222-24 | AH45: OFICINA DE TECNOLOGÍA DE LA INFORMACIÓN, SISTEMAS Y COMUNICACIONES | AI45: =AG45=I45 -> TRUE
A46: 45 | B46: 79349710 | C46: OVALLE CUERVO EDGAR ENRIQUE | D46: 3 | E46: PROFESIONAL | F46: PROFESIONAL ESPECIALIZADO | G46: 222 | H46: 24 | I46: =G46&"-"&H46 -> 222-24 | J46: OFICINA DE TECNOLOGÍA DE LA INFORMACIÓN, SISTEMAS Y COMUNICACIONES | K46: CARRERA ADMINISTRATIVA | L46: =C46=P46 -> TRUE | M46: =J46=AH46 -> TRUE | O46: 79349710 | P46: OVALLE CUERVO EDGAR ENRIQUE | Q46: CARRERA ADMINISTRATIVA | R46: CARRERA ADMINISTRATIVA | S46: 42585 | T46: 35786 | U46: HOMBRE | V46: 57 | AB46: OCUPADO | AC46: PROFESIONAL | AD46: PROFESIONAL ESPECIALIZADO | AE46: 222 | AF46: 24 | AG46: =AE46&"-"&AF46 -> 222-24 | AH46: OFICINA DE TECNOLOGÍA DE LA INFORMACIÓN, SISTEMAS Y COMUNICACIONES | AI46: =AG46=I46 -> TRUE
A47: 46 | B47: 28963444 | C47: SALCEDO TAMAYO GLORIA ESTHER | D47: 3 | E47: PROFESIONAL | F47: PROFESIONAL ESPECIALIZADO | G47: 222 | H47: 24 | I47: =G47&"-"&H47 -> 222-24 | J47: DIRECCIÓN CORPORATIVA | K47: CARRERA ADMINISTRATIVA | L47: =C47=P47 -> TRUE | M47: =J47=AH47 -> TRUE | O47: 28963444 | P47: SALCEDO TAMAYO GLORIA ESTHER | Q47: CARRERA ADMINISTRATIVA | R47: CARRERA ADMINISTRATIVA | S47: 42585 | T47: 34257 | U47: MUJER | V47: 58 | AB47: OCUPADO | AC47: PROFESIONAL | AD47: PROFESIONAL ESPECIALIZADO | AE47: 222 | AF47: 24 | AG47: =AE47&"-"&AF47 -> 222-24 | AH47: DIRECCIÓN CORPORATIVA | AI47: =AG47=I47 -> TRUE
A48: 47 | B48: 42497241 | C48: APONTE PENSO SILVIA MODESTA | D48: 3 | E48: PROFESIONAL | F48: PROFESIONAL ESPECIALIZADO | G48: 222 | H48: 24 | I48: =G48&"-"&H48 -> 222-24 | J48: DIRECCIÓN DISTRITAL DE DOCTRINA JURÍDICA | K48: CARRERA ADMINISTRATIVA | L48: =C48=P48 -> TRUE | M48: =J48=AH48 -> TRUE | O48: 42497241 | P48: APONTE PENSO SILVIA MODESTA | Q48: CARRERA ADMINISTRATIVA | R48: CARRERA ADMINISTRATIVA | S48: 42585 | T48: 34687 | U48: MUJER | V48: 63 | AB48: OCUPADO | AC48: PROFESIONAL | AD48: PROFESIONAL ESPECIALIZADO | AE48: 222 | AF48: 24 | AG48: =AE48&"-"&AF48 -> 222-24 | AH48: DIRECCIÓN DISTRITAL DE DOCTRINA JURÍDICA | AI48: =AG48=I48 -> TRUE
A49: 48 | C49: VACANTE DEFINITIVA | D49: 3 | E49: PROFESIONAL | F49: PROFESIONAL ESPECIALIZADO | G49: 222 | H49: 24 | I49: =G49&"-"&H49 -> 222-24 | J49: DIRECCIÓN DISTRITAL DE DOCTRINA JURÍDICA | L49: =C49=P49 -> TRUE | M49: =J49=AH49 -> TRUE | P49: VACANTE DEFINITIVA | R49: VACANTE DEFINITIVA | X49: VACANTE DEFINITIVA | AB49: VACANTE DEFINITIVA | AC49: PROFESIONAL | AD49: PROFESIONAL ESPECIALIZADO | AE49: 222 | AF49: 24 | AG49: =AE49&"-"&AF49 -> 222-24 | AH49: DIRECCIÓN DISTRITAL DE DOCTRINA JURÍDICA | AI49: =AG49=I49 -> TRUE
A50: 49 | C50: VACANTE DEFINITIVA | D50: 3 | E50: PROFESIONAL | F50: PROFESIONAL ESPECIALIZADO | G50: 222 | H50: 24 | I50: =G50&"-"&H50 -> 222-24 | J50: DIRECCIÓN DISTRITAL DE DOCTRINA JURÍDICA | L50: =C50=P50 -> TRUE | M50: =J50=AH50 -> TRUE | P50: VACANTE DEFINITIVA | R50: VACANTE DEFINITIVA | X50: VACANTE DEFINITIVA | AB50: VACANTE DEFINITIVA | AC50: PROFESIONAL | AD50: PROFESIONAL ESPECIALIZADO | AE50: 222 | AF50: 24 | AG50: =AE50&"-"&AF50 -> 222-24 | AH50: DIRECCIÓN DISTRITAL DE DOCTRINA JURÍDICA | AI50: =AG50=I50 -> TRUE
A51: 50 | C51: VACANTE DEFINITIVA | D51: 3 | E51: PROFESIONAL | F51: PROFESIONAL ESPECIALIZADO | G51: 222 | H51: 24 | I51: =G51&"-"&H51 -> 222-24 | J51: DIRECCIÓN DISTRITAL DE DOCTRINA JURÍDICA | L51: =C51=P51 -> TRUE | M51: =J51=AH51 -> TRUE | P51: VACANTE DEFINITIVA | R51: VACANTE DEFINITIVA | X51: VACANTE DEFINITIVA | AB51: VACANTE DEFINITIVA | AC51: PROFESIONAL | AD51: PROFESIONAL ESPECIALIZADO | AE51: 222 | AF51: 24 | AG51: =AE51&"-"&AF51 -> 222-24 | AH51: DIRECCIÓN DISTRITAL DE DOCTRINA JURÍDICA | AI51: =AG51=I51 -> TRUE
A52: 51 | C52: VACANTE DEFINITIVA | D52: 3 | E52: PROFESIONAL | F52: PROFESIONAL ESPECIALIZADO | G52: 222 | H52: 24 | I52: =G52&"-"&H52 -> 222-24 | J52: DIRECCIÓN DISTRITAL DE INSPECCIÓN VIGILANCIA Y CONTROL DE LAS ENTIDADES SIN ÁNIMO DE LUCRO | L52: =C52=P52 -> TRUE | M52: =J52=AH52 -> TRUE | P52: VACANTE DEFINITIVA | R52: VACANTE DEFINITIVA | X52: VACANTE DEFINITIVA | AB52: VACANTE DEFINITIVA | AC52: PROFESIONAL | AD52: PROFESIONAL ESPECIALIZADO | AE52: 222 | AF52: 24 | AG52: =AE52&"-"&AF52 -> 222-24 | AH52: DIRECCIÓN DISTRITAL DE INSPECCIÓN VIGILANCIA Y CONTROL DE LAS ENTIDADES SIN ÁNIMO DE LUCRO | AI52: =AG52=I52 -> TRUE
A53: 52 | B53: 35312719 | C53: GIRALDO MONTOYA MARTHA ALICIA | D53: 3 | E53: PROFESIONAL | F53: PROFESIONAL ESPECIALIZADO | G53: 222 | H53: 24 | I53: =G53&"-"&H53 -> 222-24 | J53: DIRECCIÓN DISTRITAL DE INSPECCIÓN VIGILANCIA Y CONTROL DE LAS ENTIDADES SIN ÁNIMO DE LUCRO | K53: CARRERA ADMINISTRATIVA | L53: =C53=P53 -> TRUE | M53: =J53=AH53 -> TRUE | O53: 35312719 | P53: GIRALDO MONTOYA MARTHA ALICIA | Q53: CARRERA ADMINISTRATIVA | R53: CARRERA ADMINISTRATIVA | S53: 42585 | T53: 34250 | U53: MUJER | V53: 65 | AB53: OCUPADO | AC53: PROFESIONAL | AD53: PROFESIONAL ESPECIALIZADO | AE53: 222 | AF53: 24 | AG53: =AE53&"-"&AF53 -> 222-24 | AH53: DIRECCIÓN DISTRITAL DE INSPECCIÓN VIGILANCIA Y CONTROL DE LAS ENTIDADES SIN ÁNIMO DE LUCRO | AI53: =AG53=I53 -> TRUE
A54: 53 | C54: VACANTE DEFINITIVA | D54: 3 | E54: PROFESIONAL | F54: PROFESIONAL ESPECIALIZADO | G54: 222 | H54: 22 | I54: =G54&"-"&H54 -> 222-22 | J54: DIRECCIÓN DISTRITAL DE POLÍTICA E INFORMÁTICA JURÍDICA | L54: =C54=P54 -> TRUE | M54: =J54=AH54 -> TRUE | P54: VACANTE DEFINITIVA | R54: VACANTE DEFINITIVA | X54: VACANTE DEFINITIVA | AB54: VACANTE DEFINITIVA | AC54: PROFESIONAL | AD54: PROFESIONAL ESPECIALIZADO | AE54: 222 | AF54: 22 | AG54: =AE54&"-"&AF54 -> 222-22 | AH54: DIRECCIÓN DISTRITAL DE POLÍTICA E INFORMÁTICA JURÍDICA | AI54: =AG54=I54 -> TRUE
A55: 54 | B55: 79569642 | C55: SALAZAR URRUTIA NELSON JULIAN | D55: 3 | E55: PROFESIONAL | F55: PROFESIONAL ESPECIALIZADO | G55: 222 | H55: 21 | I55: =G55&"-"&H55 -> 222-21 | J55: OFICINA ASESORA DE PLANEACIÓN | K55: CARRERA ADMINISTRATIVA | L55: =C55=P55 -> TRUE | M55: =J55=AH55 -> TRUE | O55: 79569642 | P55: SALAZAR URRUTIA NELSON JULIAN | Q55: CARRERA ADMINISTRATIVA | R55: CARRERA ADMINISTRATIVA | S55: 42585 | T55: 36271 | U55: HOMBRE | V55: 50 | AB55: OCUPADO | AC55: PROFESIONAL | AD55: PROFESIONAL ESPECIALIZADO | AE55: 222 | AF55: 21 | AG55: =AE55&"-"&AF55 -> 222-21 | AH55: OFICINA ASESORA DE PLANEACIÓN | AI55: =AG55=I55 -> TRUE
A56: 55 | B56: 51748267 | C56: CASTELLANOS RODRÍGUEZ MARTHA LIGIA | D56: 3 | E56: PROFESIONAL | F56: PROFESIONAL ESPECIALIZADO | G56: 222 | H56: 21 | I56: =G56&"-"&H56 -> 222-21 | J56: DIRECCIÓN CORPORATIVA | K56: PROVISIONAL | L56: =C56=P56 -> TRUE | M56: =J56=AH56 -> TRUE | O56: 51748267 | P56: CASTELLANOS RODRÍGUEZ MARTHA LIGIA | Q56: PROVISIONALIDAD | R56: EN PROVISIONALIDAD | S56: 42585 | T56: 40426 | U56: MUJER | V56: 59 | X56: VACANTE DEFINITIVA | AB56: OCUPADO | AC56: PROFESIONAL | AD56: PROFESIONAL ESPECIALIZADO | AE56: 222 | AF56: 21 | AG56: =AE56&"-"&AF56 -> 222-21 | AH56: DIRECCIÓN CORPORATIVA | AI56: =AG56=I56 -> TRUE
A57: 56 | B57: 51649014 | C57: GUTIERREZ HERNANDEZ DORA BELEN | D57: 3 | E57: PROFESIONAL | F57: PROFESIONAL ESPECIALIZADO | G57: 222 | H57: 21 | I57: =G57&"-"&H57 -> 222-21 | J57: DIRECCIÓN CORPORATIVA | K57: CARRERA ADMINISTRATIVA | L57: =C57=P57 -> TRUE | M57: =J57=AH57 -> TRUE | O57: 51649014 | P57: GUTIERREZ HERNANDEZ DORA BELEN | Q57: CARRERA ADMINISTRATIVA | R57: CARRERA ADMINISTRATIVA | S57: 42585 | T57: 34870 | U57: MUJER | V57: 60 | AB57: OCUPADO | AC57: PROFESIONAL | AD57: PROFESIONAL ESPECIALIZADO | AE57: 222 | AF57: 21 | AG57: =AE57&"-"&AF57 -> 222-21 | AH57: DIRECCIÓN CORPORATIVA | AI57: =AG57=I57 -> TRUE
A58: 57 | B58: 52352995 | C58: SALAS SANCHEZ VANESSA | D58: 3 | E58: PROFESIONAL | F58: PROFESIONAL ESPECIALIZADO | G58: 222 | H58: 21 | I58: =G58&"-"&H58 -> 222-21 | J58: DIRECCIÓN CORPORATIVA | K58: PROVISIONAL | L58: =C58=P58 -> TRUE | M58: =J58=AH58 -> TRUE | O58: 52352995 | P58: SALAS SANCHEZ VANESSA | Q58: PROVISIONALIDAD | R58: EN PROVISIONALIDAD | S58: 42585 | T58: 42051 | U58: MUJER | V58: 43 | X58: VACANTE DEFINITIVA | AB58: OCUPADO | AC58: PROFESIONAL | AD58: PROFESIONAL ESPECIALIZADO | AE58: 222 | AF58: 21 | AG58: =AE58&"-"&AF58 -> 222-21 | AH58: DIRECCIÓN CORPORATIVA | AI58: =AG58=I58 -> TRUE
A59: 58 | C59: VACANTE DEFINITIVA | D59: 3 | E59: PROFESIONAL | F59: PROFESIONAL ESPECIALIZADO | G59: 222 | H59: 21 | I59: =G59&"-"&H59 -> 222-21 | J59: DIRECCIÓN CORPORATIVA | L59: =C59=P59 -> TRUE | M59: =J59=AH59 -> TRUE | P59: VACANTE DEFINITIVA | R59: VACANTE DEFINITIVA | X59: VACANTE DEFINITIVA | AB59: VACANTE DEFINITIVA | AC59: PROFESIONAL | AD59: PROFESIONAL ESPECIALIZADO | AE59: 222 | AF59: 21 | AG59: =AE59&"-"&AF59 -> 222-21 | AH59: DIRECCIÓN CORPORATIVA | AI59: =AG59=I59 -> TRUE
A60: 59 | B60: 3085860 | C60: CASTIBLANCO URQUIJO LUIS ALFONSO | D60: 3 | E60: PROFESIONAL | F60: PROFESIONAL ESPECIALIZADO | G60: 222 | H60: 21 | I60: =G60&"-"&H60 -> 222-21 | J60: DIRECCIÓN DISTRITAL DE DEFENSA JUDICIAL Y PREVENCIÓN DEL DAÑO ANTIJURÍDICO | K60: CARRERA ADMINISTRATIVA | L60: =C60=P60 -> TRUE | M60: =J60=AH60 -> TRUE | O60: 3085860 | P60: CASTIBLANCO URQUIJO LUIS ALFONSO | Q60: CARRERA ADMINISTRATIVA | R60: CARRERA ADMINISTRATIVA | S60: 42585 | T60: 38443 | U60: HOMBRE | V60: 54 | AB60: OCUPADO | AC60: PROFESIONAL | AD60: PROFESIONAL ESPECIALIZADO | AE60: 222 | AF60: 21 | AG60: =AE60&"-"&AF60 -> 222-21 | AH60: DIRECCIÓN DISTRITAL DE DEFENSA JUDICIAL Y PREVENCIÓN DEL DAÑO ANTIJURÍDICO | AI60: =AG60=I60 -> TRUE
A61: 60 | C61: VACANTE DEFINITIVA | D61: 3 | E61: PROFESIONAL | F61: PROFESIONAL ESPECIALIZADO | G61: 222 | H61: 21 | I61: =G61&"-"&H61 -> 222-21 | J61: DIRECCIÓN DISTRITAL DE DOCTRINA JURÍDICA | L61: =C61=P61 -> TRUE | M61: =J61=AH61 -> TRUE | P61: VACANTE DEFINITIVA | R61: VACANTE DEFINITIVA | X61: VACANTE DEFINITIVA | AB61: VACANTE DEFINITIVA | AC61: PROFESIONAL | AD61: PROFESIONAL ESPECIALIZADO | AE61: 222 | AF61: 21 | AG61: =AE61&"-"&AF61 -> 222-21 | AH61: DIRECCIÓN DISTRITAL DE DOCTRINA JURÍDICA | AI61: =AG61=I61 -> TRUE
A62: 61 | C62: VACANTE DEFINITIVA | D62: 3 | E62: PROFESIONAL | F62: PROFESIONAL ESPECIALIZADO | G62: 222 | H62: 21 | I62: =G62&"-"&H62 -> 222-21 | J62: DIRECCIÓN DISTRITAL DE INSPECCIÓN VIGILANCIA Y CONTROL DE LAS ENTIDADES SIN ÁNIMO DE LUCRO | L62: =C62=P62 -> TRUE | M62: =J62=AH62 -> TRUE | P62: VACANTE DEFINITIVA | R62: VACANTE DEFINITIVA | X62: VACANTE DEFINITIVA | AB62: VACANTE DEFINITIVA | AC62: PROFESIONAL | AD62: PROFESIONAL ESPECIALIZADO | AE62: 222 | AF62: 21 | AG62: =AE62&"-"&AF62 -> 222-21 | AH62: DIRECCIÓN DISTRITAL DE INSPECCIÓN VIGILANCIA Y CONTROL DE LAS ENTIDADES SIN ÁNIMO DE LUCRO | AI62: =AG62=I62 -> TRUE
A63: 62 | C63: VACANTE DEFINITIVA | D63: 3 | E63: PROFESIONAL | F63: PROFESIONAL ESPECIALIZADO | G63: 222 | H63: 21 | I63: =G63&"-"&H63 -> 222-21 | J63: DIRECCIÓN DISTRITAL DE INSPECCIÓN VIGILANCIA Y CONTROL DE LAS ENTIDADES SIN ÁNIMO DE LUCRO | L63: =C63=P63 -> TRUE | M63: =J63=AH63 -> TRUE | P63: VACANTE DEFINITIVA | R63: VACANTE DEFINITIVA | X63: VACANTE DEFINITIVA | AB63: VACANTE DEFINITIVA | AC63: PROFESIONAL | AD63: PROFESIONAL ESPECIALIZADO | AE63: 222 | AF63: 21 | AG63: =AE63&"-"&AF63 -> 222-21 | AH63: DIRECCIÓN DISTRITAL DE INSPECCIÓN VIGILANCIA Y CONTROL DE LAS ENTIDADES SIN ÁNIMO DE LUCRO | AI63: =AG63=I63 -> TRUE
A64: 63 | B64: 79450267 | C64: GONZÁLEZ MOLINA HENRY ALBERTO | D64: 3 | E64: PROFESIONAL | F64: PROFESIONAL ESPECIALIZADO | G64: 222 | H64: 20 | I64: =G64&"-"&H64 -> 222-20 | J64: DIRECCIÓN DISTRITAL DE DEFENSA JUDICIAL Y PREVENCIÓN DEL DAÑO ANTIJURÍDICO | K64: CARRERA ADMINISTRATIVA | L64: =C64=P64 -> TRUE | M64: =J64=AH64 -> TRUE | O64: 79450267 | P64: GONZÁLEZ MOLINA HENRY ALBERTO | Q64: CARRERA ADMINISTRATIVA | R64: CARRERA ADMINISTRATIVA | S64: 42585 | T64: 35062 | U64: HOMBRE | V64: 55 | AB64: OCUPADO | AC64: PROFESIONAL | AD64: PROFESIONAL ESPECIALIZADO | AE64: 222 | AF64: 20 | AG64: =AE64&"-"&AF64 -> 222-20 | AH64: DIRECCIÓN DISTRITAL DE DEFENSA JUDICIAL Y PREVENCIÓN DEL DAÑO ANTIJURÍDICO | AI64: =AG64=I64 -> TRUE
A65: 64 | C65: VACANTE DEFINITIVA | D65: 3 | E65: PROFESIONAL | F65: PROFESIONAL ESPECIALIZADO | G65: 222 | H65: 20 | I65: =G65&"-"&H65 -> 222-20 | J65: DIRECCIÓN DISTRITAL DE DEFENSA JUDICIAL Y PREVENCIÓN DEL DAÑO ANTIJURÍDICO | L65: =C65=P65 -> TRUE | M65: =J65=AH65 -> TRUE | P65: VACANTE DEFINITIVA | R65: VACANTE DEFINITIVA | X65: VACANTE DEFINITIVA | AB65: VACANTE DEFINITIVA | AC65: PROFESIONAL | AD65: PROFESIONAL ESPECIALIZADO | AE65: 222 | AF65: 20 | AG65: =AE65&"-"&AF65 -> 222-20 | AH65: DIRECCIÓN DISTRITAL DE DEFENSA JUDICIAL Y PREVENCIÓN DEL DAÑO ANTIJURÍDICO | AI65: =AG65=I65 -> TRUE
A66: 65 | C66: VACANTE DEFINITIVA | D66: 3 | E66: PROFESIONAL | F66: PROFESIONAL ESPECIALIZADO | G66: 222 | H66: 19 | I66: =G66&"-"&H66 -> 222-19 | J66: DIRECCIÓN DISTRITAL DE ASUNTOS DISCIPLINARIOS | L66: =C66=P66 -> TRUE | M66: =J66=AH66 -> TRUE | P66: VACANTE DEFINITIVA | R66: VACANTE DEFINITIVA | X66: VACANTE DEFINITIVA | AB66: VACANTE DEFINITIVA | AC66: PROFESIONAL | AD66: PROFESIONAL ESPECIALIZADO | AE66: 222 | AF66: 19 | AG66: =AE66&"-"&AF66 -> 222-19 | AH66: DIRECCIÓN DISTRITAL DE ASUNTOS DISCIPLINARIOS | AI66: =AG66=I66 -> TRUE
A67: 66 | C67: VACANTE DEFINITIVA | D67: 3 | E67: PROFESIONAL | F67: PROFESIONAL ESPECIALIZADO | G67: 222 | H67: 19 | I67: =G67&"-"&H67 -> 222-19 | J67: DIRECCIÓN DISTRITAL DE ASUNTOS DISCIPLINARIOS | L67: =C67=P67 -> TRUE | M67: =J67=AH67 -> TRUE | P67: VACANTE DEFINITIVA | R67: VACANTE DEFINITIVA | X67: VACANTE DEFINITIVA | AB67: VACANTE DEFINITIVA | AC67: PROFESIONAL | AD67: PROFESIONAL ESPECIALIZADO | AE67: 222 | AF67: 19 | AG67: =AE67&"-"&AF67 -> 222-19 | AH67: DIRECCIÓN DISTRITAL DE ASUNTOS DISCIPLINARIOS | AI67: =AG67=I67 -> TRUE
A68: 67 | C68: VACANTE DEFINITIVA | D68: 3 | E68: PROFESIONAL | F68: PROFESIONAL ESPECIALIZADO | G68: 222 | H68: 19 | I68: =G68&"-"&H68 -> 222-19 | J68: DIRECCIÓN DISTRITAL DE DOCTRINA JURÍDICA | L68: =C68=P68 -> TRUE | M68: =J68=AH68 -> TRUE | P68: VACANTE DEFINITIVA | R68: VACANTE DEFINITIVA | X68: VACANTE DEFINITIVA | AB68: VACANTE DEFINITIVA | AC68: PROFESIONAL | AD68: PROFESIONAL ESPECIALIZADO | AE68: 222 | AF68: 19 | AG68: =AE68&"-"&AF68 -> 222-19 | AH68: DIRECCIÓN DISTRITAL DE DOCTRINA JURÍDICA | AI68: =AG68=I68 -> TRUE
A69: 68 | B69: 51772038 | C69: CONTRERAS CASTRO DIANA ESTHER | D69: 3 | E69: PROFESIONAL | F69: PROFESIONAL ESPECIALIZADO | G69: 222 | H69: 19 | I69: =G69&"-"&H69 -> 222-19 | J69: DIRECCIÓN DISTRITAL DE INSPECCIÓN VIGILANCIA Y CONTROL DE LAS ENTIDADES SIN ÁNIMO DE LUCRO | K69: CARRERA ADMINISTRATIVA | L69: =C69=P69 -> TRUE | M69: =J69=AH69 -> TRUE | O69: 51772038 | P69: CONTRERAS CASTRO DIANA ESTHER | Q69: CARRERA ADMINISTRATIVA | R69: CARRERA ADMINISTRATIVA | S69: 42585 | T69: 34555 | U69: MUJER | V69: 57 | AB69: OCUPADO | AC69: PROFESIONAL | AD69: PROFESIONAL ESPECIALIZADO | AE69: 222 | AF69: 19 | AG69: =AE69&"-"&AF69 -> 222-19 | AH69: DIRECCIÓN DISTRITAL DE INSPECCIÓN VIGILANCIA Y CONTROL DE LAS ENTIDADES SIN ÁNIMO DE LUCRO | AI69: =AG69=I69 -> TRUE
A70: 69 | C70: VACANTE DEFINITIVA | D70: 3 | E70: PROFESIONAL | F70: PROFESIONAL UNIVERSITARIO | G70: 219 | H70: 18 | I70: =G70&"-"&H70 -> 219-18 | J70: DESPACHO | L70: =C70=P70 -> TRUE | M70: =J70=AH70 -> TRUE | P70: VACANTE DEFINITIVA | R70: VACANTE DEFINITIVA | X70: VACANTE DEFINITIVA | AB70: VACANTE DEFINITIVA | AC70: PROFESIONAL | AD70: PROFESIONAL UNIVERSITARIO | AE70: 219 | AF70: 18 | AG70: =AE70&"-"&AF70 -> 219-18 | AH70: DESPACHO | AI70: =AG70=I70 -> TRUE
A71: 70 | C71: VACANTE DEFINITIVA | D71: 3 | E71: PROFESIONAL | F71: PROFESIONAL UNIVERSITARIO | G71: 219 | H71: 18 | I71: =G71&"-"&H71 -> 219-18 | J71: OFICINA ASESORA DE PLANEACIÓN | L71: =C71=P71 -> TRUE | M71: =J71=AH71 -> TRUE | P71: VACANTE DEFINITIVA | R71: VACANTE DEFINITIVA | X71: VACANTE DEFINITIVA | AB71: VACANTE DEFINITIVA | AC71: PROFESIONAL | AD71: PROFESIONAL UNIVERSITARIO | AE71: 219 | AF71: 18 | AG71: =AE71&"-"&AF71 -> 219-18 | AH71: OFICINA ASESORA DE PLANEACIÓN | AI71: =AG71=I71 -> TRUE
A72: 71 | B72: 80022321 | C72: HERNÁNDEZ MURCIA SAMUEL ARTURO | D72: 3 | E72: PROFESIONAL | F72: PROFESIONAL UNIVERSITARIO | G72: 219 | H72: 18 | I72: =G72&"-"&H72 -> 219-18 | J72: DIRECCIÓN CORPORATIVA | K72: PROVISIONAL | L72: =C72=P72 -> TRUE | M72: =J72=AH72 -> TRUE | O72: 80022321 | P72: HERNÁNDEZ MURCIA SAMUEL ARTURO | Q72: PROVISIONALIDAD | R72: EN PROVISIONALIDAD | S72: 42585 | T72: 40408 | U72: HOMBRE | V72: 43 | X72: VACANTE DEFINITIVA | AB72: OCUPADO | AC72: PROFESIONAL | AD72: PROFESIONAL UNIVERSITARIO | AE72: 219 | AF72: 18 | AG72: =AE72&"-"&AF72 -> 219-18 | AH72: DIRECCIÓN CORPORATIVA | AI72: =AG72=I72 -> TRUE
A73: 72 | B73: 51657823 | C73: MENDOZA HILDA CONSUELO | D73: 3 | E73: PROFESIONAL | F73: PROFESIONAL UNIVERSITARIO | G73: 219 | H73: 18 | I73: =G73&"-"&H73 -> 219-18 | J73: DIRECCIÓN CORPORATIVA | K73: CARRERA ADMINISTRATIVA | L73: =C73=P73 -> TRUE | M73: =J73=AH73 -> TRUE | O73: 51657823 | P73: MENDOZA HILDA CONSUELO | Q73: CARRERA ADMINISTRATIVA | R73: CARRERA ADMINISTRATIVA | S73: 42585 | T73: 33696 | U73: MUJER | V73: 61 | AB73: OCUPADO | AC73: PROFESIONAL | AD73: PROFESIONAL UNIVERSITARIO | AE73: 219 | AF73: 18 | AG73: =AE73&"-"&AF73 -> 219-18 | AH73: DIRECCIÓN CORPORATIVA | AI73: =AG73=I73 -> TRUE
A74: 73 | C74: VACANTE DEFINITIVA | D74: 3 | E74: PROFESIONAL | F74: PROFESIONAL UNIVERSITARIO | G74: 219 | H74: 18 | I74: =G74&"-"&H74 -> 219-18 | J74: DIRECCIÓN CORPORATIVA | L74: =C74=P74 -> TRUE | M74: =J74=AH74 -> TRUE | P74: VACANTE DEFINITIVA | R74: VACANTE DEFINITIVA | X74: VACANTE DEFINITIVA | AB74: VACANTE DEFINITIVA | AC74: PROFESIONAL | AD74: PROFESIONAL UNIVERSITARIO | AE74: 219 | AF74: 18 | AG74: =AE74&"-"&AF74 -> 219-18 | AH74: DIRECCIÓN CORPORATIVA | AI74: =AG74=I74 -> TRUE
A75: 74 | C75: VACANTE DEFINITIVA | D75: 3 | E75: PROFESIONAL | F75: PROFESIONAL UNIVERSITARIO | G75: 219 | H75: 18 | I75: =G75&"-"&H75 -> 219-18 | J75: DIRECCIÓN CORPORATIVA | L75: =C75=P75 -> TRUE | M75: =J75=AH75 -> TRUE | P75: VACANTE DEFINITIVA | R75: VACANTE DEFINITIVA | X75: VACANTE DEFINITIVA | AB75: VACANTE DEFINITIVA | AC75: PROFESIONAL | AD75: PROFESIONAL UNIVERSITARIO | AE75: 219 | AF75: 18 | AG75: =AE75&"-"&AF75 -> 219-18 | AH75: DIRECCIÓN CORPORATIVA | AI75: =AG75=I75 -> TRUE
A76: 75 | C76: VACANTE DEFINITIVA | D76: 3 | E76: PROFESIONAL | F76: PROFESIONAL UNIVERSITARIO | G76: 219 | H76: 18 | I76: =G76&"-"&H76 -> 219-18 | J76: DIRECCIÓN CORPORATIVA | L76: =C76=P76 -> TRUE | M76: =J76=AH76 -> TRUE | P76: VACANTE DEFINITIVA | R76: VACANTE DEFINITIVA | X76: VACANTE DEFINITIVA | AB76: VACANTE DEFINITIVA | AC76: PROFESIONAL | AD76: PROFESIONAL UNIVERSITARIO | AE76: 219 | AF76: 18 | AG76: =AE76&"-"&AF76 -> 219-18 | AH76: DIRECCIÓN CORPORATIVA | AI76: =AG76=I76 -> TRUE
A77: 76 | B77: 38263037 | C77: GOMEZ CARMONA WALDINA | D77: 3 | E77: PROFESIONAL | F77: PROFESIONAL UNIVERSITARIO | G77: 219 | H77: 18 | I77: =G77&"-"&H77 -> 219-18 | J77: DIRECCIÓN DISTRITAL DE DEFENSA JUDICIAL Y PREVENCIÓN DEL DAÑO ANTIJURÍDICO | K77: CARRERA ADMINISTRATIVA | L77: =C77=P77 -> TRUE | M77: =J77=AH77 -> TRUE | O77: 38263037 | P77: GOMEZ CARMONA WALDINA | Q77: CARRERA ADMINISTRATIVA | R77: CARRERA ADMINISTRATIVA | S77: 42585 | T77: 35327 | U77: MUJER | V77: 58 | AB77: OCUPADO | AC77: PROFESIONAL | AD77: PROFESIONAL UNIVERSITARIO | AE77: 219 | AF77: 18 | AG77: =AE77&"-"&AF77 -> 219-18 | AH77: DIRECCIÓN DISTRITAL DE DEFENSA JUDICIAL Y PREVENCIÓN DEL DAÑO ANTIJURÍDICO | AI77: =AG77=I77 -> TRUE
A78: 77 | B78: 7630834 | C78: RUIZ VEGA HÉCTOR RAFAEL | D78: 3 | E78: PROFESIONAL | F78: PROFESIONAL UNIVERSITARIO | G78: 219 | H78: 18 | I78: =G78&"-"&H78 -> 219-18 | J78: DIRECCIÓN DISTRITAL DE DEFENSA JUDICIAL Y PREVENCIÓN DEL DAÑO ANTIJURÍDICO | K78: PROVISIONAL | L78: =C78=P78 -> TRUE | M78: =J78=AH78 -> TRUE | O78: 7630834 | P78: RUIZ VEGA HÉCTOR RAFAEL | Q78: PROVISIONALIDAD | R78: EN PROVISIONALIDAD | S78: 42585 | T78: 41106 | U78: HOMBRE | V78: 42 | X78: VACANTE DEFINITIVA | AB78: OCUPADO | AC78: PROFESIONAL | AD78: PROFESIONAL UNIVERSITARIO | AE78: 219 | AF78: 18 | AG78: =AE78&"-"&AF78 -> 219-18 | AH78: DIRECCIÓN DISTRITAL DE DEFENSA JUDICIAL Y PREVENCIÓN DEL DAÑO ANTIJURÍDICO | AI78: =AG78=I78 -> TRUE
A79: 78 | C79: VACANTE DEFINITIVA | D79: 3 | E79: PROFESIONAL | F79: PROFESIONAL UNIVERSITARIO | G79: 219 | H79: 18 | I79: =G79&"-"&H79 -> 219-18 | J79: DIRECCIÓN DISTRITAL DE DEFENSA JUDICIAL Y PREVENCIÓN DEL DAÑO ANTIJURÍDICO | L79: =C79=P79 -> TRUE | M79: =J79=AH79 -> TRUE | P79: VACANTE DEFINITIVA | R79: VACANTE DEFINITIVA | X79: VACANTE DEFINITIVA | AB79: VACANTE DEFINITIVA | AC79: PROFESIONAL | AD79: PROFESIONAL UNIVERSITARIO | AE79: 219 | AF79: 18 | AG79: =AE79&"-"&AF79 -> 219-18 | AH79: DIRECCIÓN DISTRITAL DE DEFENSA JUDICIAL Y PREVENCIÓN DEL DAÑO ANTIJURÍDICO | AI79: =AG79=I79 -> TRUE
A80: 79 | C80: VACANTE DEFINITIVA | D80: 3 | E80: PROFESIONAL | F80: PROFESIONAL UNIVERSITARIO | G80: 219 | H80: 18 | I80: =G80&"-"&H80 -> 219-18 | J80: DIRECCIÓN DISTRITAL DE DEFENSA JUDICIAL Y PREVENCIÓN DEL DAÑO ANTIJURÍDICO | L80: =C80=P80 -> TRUE | M80: =J80=AH80 -> TRUE | P80: VACANTE DEFINITIVA | R80: VACANTE DEFINITIVA | X80: VACANTE DEFINITIVA | AB80: VACANTE DEFINITIVA | AC80: PROFESIONAL | AD80: PROFESIONAL UNIVERSITARIO | AE80: 219 | AF80: 18 | AG80: =AE80&"-"&AF80 -> 219-18 | AH80: DIRECCIÓN DISTRITAL DE DEFENSA JUDICIAL Y PREVENCIÓN DEL DAÑO ANTIJURÍDICO | AI80: =AG80=I80 -> TRUE
A81: 80 | C81: VACANTE DEFINITIVA | D81: 3 | E81: PROFESIONAL | F81: PROFESIONAL UNIVERSITARIO | G81: 219 | H81: 18 | I81: =G81&"-"&H81 -> 219-18 | J81: DIRECCIÓN DISTRITAL DE DEFENSA JUDICIAL Y PREVENCIÓN DEL DAÑO ANTIJURÍDICO | L81: =C81=P81 -> TRUE | M81: =J81=AH81 -> TRUE | P81: VACANTE DEFINITIVA | R81: VACANTE DEFINITIVA | X81: VACANTE DEFINITIVA | AB81: VACANTE DEFINITIVA | AC81: PROFESIONAL | AD81: PROFESIONAL UNIVERSITARIO | AE81: 219 | AF81: 18 | AG81: =AE81&"-"&AF81 -> 219-18 | AH81: DIRECCIÓN DISTRITAL DE DEFENSA JUDICIAL Y PREVENCIÓN DEL DAÑO ANTIJURÍDICO | AI81: =AG81=I81 -> TRUE
A82: 81 | C82: VACANTE DEFINITIVA | D82: 3 | E82: PROFESIONAL | F82: PROFESIONAL UNIVERSITARIO | G82: 219 | H82: 18 | I82: =G82&"-"&H82 -> 219-18 | J82: DIRECCIÓN DISTRITAL DE DEFENSA JUDICIAL Y PREVENCIÓN DEL DAÑO ANTIJURÍDICO | L82: =C82=P82 -> TRUE | M82: =J82=AH82 -> TRUE | P82: VACANTE DEFINITIVA | R82: VACANTE DEFINITIVA | X82: VACANTE DEFINITIVA | AB82: VACANTE DEFINITIVA | AC82: PROFESIONAL | AD82: PROFESIONAL UNIVERSITARIO | AE82: 219 | AF82: 18 | AG82: =AE82&"-"&AF82 -> 219-18 | AH82: DIRECCIÓN DISTRITAL DE DEFENSA JUDICIAL Y PREVENCIÓN DEL DAÑO ANTIJURÍDICO | AI82: =AG82=I82 -> TRUE
A83: 82 | B83: 79567977 | C83: PACHÓN PIÑEROS FERNANDO | D83: 3 | E83: PROFESIONAL | F83: PROFESIONAL UNIVERSITARIO | G83: 219 | H83: 18 | I83: =G83&"-"&H83 -> 219-18 | J83: DIRECCIÓN DISTRITAL DE DOCTRINA JURÍDICA | K83: CARRERA ADMINISTRATIVA | L83: =C83=P83 -> TRUE | M83: =J83=AH83 -> TRUE | O83: 79567977 | P83: PACHÓN PIÑEROS FERNANDO | Q83: CARRERA ADMINISTRATIVA | R83: CARRERA ADMINISTRATIVA | S83: 42585 | T83: 40260 | U83: HOMBRE | V83: 49 | AB83: OCUPADO | AC83: PROFESIONAL | AD83: PROFESIONAL UNIVERSITARIO | AE83: 219 | AF83: 18 | AG83: =AE83&"-"&AF83 -> 219-18 | AH83: DIRECCIÓN DISTRITAL DE DOCTRINA JURÍDICA | AI83: =AG83=I83 -> TRUE
A84: 83 | C84: VACANTE DEFINITIVA | D84: 3 | E84: PROFESIONAL | F84: PROFESIONAL UNIVERSITARIO | G84: 219 | H84: 18 | I84: =G84&"-"&H84 -> 219-18 | J84: DIRECCIÓN DISTRITAL DE DOCTRINA JURÍDICA | L84: =C84=P84 -> TRUE | M84: =J84=AH84 -> TRUE | P84: VACANTE DEFINITIVA | R84: VACANTE DEFINITIVA | X84: VACANTE DEFINITIVA | AB84: VACANTE DEFINITIVA | AC84: PROFESIONAL | AD84: PROFESIONAL UNIVERSITARIO | AE84: 219 | AF84: 18 | AG84: =AE84&"-"&AF84 -> 219-18 | AH84: DIRECCIÓN DISTRITAL DE DOCTRINA JURÍDICA | AI84: =AG84=I84 -> TRUE
A85: 84 | B85: 93371977 | C85: SANDOVAL RODRÍGUEZ DUVÁN | D85: 3 | E85: PROFESIONAL | F85: PROFESIONAL UNIVERSITARIO | G85: 219 | H85: 18 | I85: =G85&"-"&H85 -> 219-18 | J85: DIRECCIÓN DISTRITAL DE DOCTRINA JURÍDICA | K85: CARRERA ADMINISTRATIVA | L85: =C85=P85 -> TRUE | M85: =J85=AH85 -> TRUE | O85: 93371977 | P85: SANDOVAL RODRÍGUEZ DUVÁN | Q85: CARRERA ADMINISTRATIVA | R85: CARRERA ADMINISTRATIVA | S85: 42585 | T85: 40267 | U85: HOMBRE | V85: 54 | AB85: OCUPADO | AC85: PROFESIONAL | AD85: PROFESIONAL UNIVERSITARIO | AE85: 219 | AF85: 18 | AG85: =AE85&"-"&AF85 -> 219-18 | AH85: DIRECCIÓN DISTRITAL DE DOCTRINA JURÍDICA | AI85: =AG85=I85 -> TRUE
A86: 85 | B86: 79802044 | C86: BERNATE NAVARRO ALVARO CAMILO | D86: 3 | E86: PROFESIONAL | F86: PROFESIONAL UNIVERSITARIO | G86: 219 | H86: 18 | I86: =G86&"-"&H86 -> 219-18 | J86: DIRECCIÓN DISTRITAL DE POLÍTICA E INFORMÁTICA JURÍDICA | K86: CARRERA ADMINISTRATIVA | L86: =C86=P86 -> TRUE | M86: =J86=AH86 -> TRUE | O86: 79802044 | P86: BERNATE NAVARRO ALVARO CAMILO | Q86: CARRERA ADMINISTRATIVA | R86: CARRERA ADMINISTRATIVA | S86: 42585 | T86: 38294 | U86: HOMBRE | V86: 46 | AB86: OCUPADO | AC86: PROFESIONAL | AD86: PROFESIONAL UNIVERSITARIO | AE86: 219 | AF86: 18 | AG86: =AE86&"-"&AF86 -> 219-18 | AH86: DIRECCIÓN DISTRITAL DE POLÍTICA E INFORMÁTICA JURÍDICA | AI86: =AG86=I86 -> TRUE
A87: 86 | C87: VACANTE DEFINITIVA | D87: 3 | E87: PROFESIONAL | F87: PROFESIONAL UNIVERSITARIO | G87: 219 | H87: 18 | I87: =G87&"-"&H87 -> 219-18 | J87: DIRECCIÓN DISTRITAL DE POLÍTICA E INFORMÁTICA JURÍDICA | L87: =C87=P87 -> TRUE | M87: =J87=AH87 -> TRUE | P87: VACANTE DEFINITIVA | R87: VACANTE DEFINITIVA | X87: VACANTE DEFINITIVA | AB87: VACANTE DEFINITIVA | AC87: PROFESIONAL | AD87: PROFESIONAL UNIVERSITARIO | AE87: 219 | AF87: 18 | AG87: =AE87&"-"&AF87 -> 219-18 | AH87: DIRECCIÓN DISTRITAL DE POLÍTICA E INFORMÁTICA JURÍDICA | AI87: =AG87=I87 -> TRUE
A88: 87 | B88: 6758776 | C88: MUÑOZ CUERVO HERNAN BENJAMIN | D88: 3 | E88: PROFESIONAL | F88: PROFESIONAL UNIVERSITARIO | G88: 219 | H88: 18 | I88: =G88&"-"&H88 -> 219-18 | J88: DIRECCIÓN DISTRITAL DE INSPECCIÓN VIGILANCIA Y CONTROL DE LAS ENTIDADES SIN ÁNIMO DE LUCRO | K88: CARRERA ADMINISTRATIVA | L88: =C88=P88 -> TRUE | M88: =J88=AH88 -> TRUE | O88: 6758776 | P88: MUÑOZ CUERVO HERNAN BENJAMIN | Q88: CARRERA ADMINISTRATIVA | R88: CARRERA ADMINISTRATIVA | S88: 42585 | T88: 31944 | U88: HOMBRE | V88: 69 | AB88: OCUPADO | AC88: PROFESIONAL | AD88: PROFESIONAL UNIVERSITARIO | AE88: 219 | AF88: 18 | AG88: =AE88&"-"&AF88 -> 219-18 | AH88: DIRECCIÓN DISTRITAL DE INSPECCIÓN VIGILANCIA Y CONTROL DE LAS ENTIDADES SIN ÁNIMO DE LUCRO | AI88: =AG88=I88 -> TRUE
A89: 88 | B89: 52103754 | C89: ORTIZ NUBIA STELLA | D89: 3 | E89: PROFESIONAL | F89: PROFESIONAL UNIVERSITARIO | G89: 219 | H89: 18 | I89: =G89&"-"&H89 -> 219-18 | J89: DIRECCIÓN DISTRITAL DE INSPECCIÓN VIGILANCIA Y CONTROL DE LAS ENTIDADES SIN ÁNIMO DE LUCRO | K89: PROVISIONAL | L89: =C89=P89 -> TRUE | M89: =J89=AH89 -> TRUE | O89: 52103754 | P89: ORTIZ NUBIA STELLA | Q89: PROVISIONALIDAD | R89: EN PROVISIONALIDAD | S89: 42585 | T89: 38294 | U89: MUJER | V89: 50 | X89: VACANTE DEFINITIVA | AB89: OCUPADO | AC89: PROFESIONAL | AD89: PROFESIONAL UNIVERSITARIO | AE89: 219 | AF89: 18 | AG89: =AE89&"-"&AF89 -> 219-18 | AH89: DIRECCIÓN DISTRITAL DE INSPECCIÓN VIGILANCIA Y CONTROL DE LAS ENTIDADES SIN ÁNIMO DE LUCRO | AI89: =AG89=I89 -> TRUE
A90: 89 | B90: 19299567 | C90: CAGUA NIAMPIRA LUIS ALBERTO | D90: 3 | E90: PROFESIONAL | F90: PROFESIONAL UNIVERSITARIO | G90: 219 | H90: 18 | I90: =G90&"-"&H90 -> 219-18 | J90: DIRECCIÓN DISTRITAL DE INSPECCIÓN VIGILANCIA Y CONTROL DE LAS ENTIDADES SIN ÁNIMO DE LUCRO | K90: CARRERA ADMINISTRATIVA | L90: =C90=P90 -> TRUE | M90: =J90=AH90 -> TRUE | O90: 19299567 | P90: CAGUA NIAMPIRA LUIS ALBERTO | Q90: CARRERA ADMINISTRATIVA | R90: CARRERA ADMINISTRATIVA | S90: 42585 | T90: 34775 | U90: HOMBRE | V90: 67 | AB90: OCUPADO | AC90: PROFESIONAL | AD90: PROFESIONAL UNIVERSITARIO | AE90: 219 | AF90: 18 | AG90: =AE90&"-"&AF90 -> 219-18 | AH90: DIRECCIÓN DISTRITAL DE INSPECCIÓN VIGILANCIA Y CONTROL DE LAS ENTIDADES SIN ÁNIMO DE LUCRO | AI90: =AG90=I90 -> TRUE
A91: 90 | B91: 51641343 | C91: GARZON RONCANCIO LUZ MARY | D91: 3 | E91: PROFESIONAL | F91: PROFESIONAL UNIVERSITARIO | G91: 219 | H91: 18 | I91: =G91&"-"&H91 -> 219-18 | J91: DIRECCIÓN DISTRITAL DE INSPECCIÓN VIGILANCIA Y CONTROL DE LAS ENTIDADES SIN ÁNIMO DE LUCRO | K91: PROVISIONAL | L91: =C91=P91 -> TRUE | M91: =J91=AH91 -> TRUE | O91: 51641343 | P91: GARZON RONCANCIO LUZ MARY | Q91: PROVISIONALIDAD | R91: EN PROVISIONALIDAD | S91: 42585 | T91: 38443 | U91: MUJER | V91: 60 | X91: VACANTE DEFINITIVA | AB91: OCUPADO | AC91: PROFESIONAL | AD91: PROFESIONAL UNIVERSITARIO | AE91: 219 | AF91: 18 | AG91: =AE91&"-"&AF91 -> 219-18 | AH91: DIRECCIÓN DISTRITAL DE INSPECCIÓN VIGILANCIA Y CONTROL DE LAS ENTIDADES SIN ÁNIMO DE LUCRO | AI91: =AG91=I91 -> TRUE
A92: 91 | C92: VACANTE DEFINITIVA | D92: 3 | E92: PROFESIONAL | F92: PROFESIONAL UNIVERSITARIO | G92: 219 | H92: 18 | I92: =G92&"-"&H92 -> 219-18 | J92: DIRECCIÓN DISTRITAL DE INSPECCIÓN VIGILANCIA Y CONTROL DE LAS ENTIDADES SIN ÁNIMO DE LUCRO | L92: =C92=P92 -> TRUE | M92: =J92=AH92 -> TRUE | P92: VACANTE DEFINITIVA | R92: VACANTE DEFINITIVA | X92: VACANTE DEFINITIVA | AB92: VACANTE DEFINITIVA | AC92: PROFESIONAL | AD92: PROFESIONAL UNIVERSITARIO | AE92: 219 | AF92: 18 | AG92: =AE92&"-"&AF92 -> 219-18 | AH92: DIRECCIÓN DISTRITAL DE INSPECCIÓN VIGILANCIA Y CONTROL DE LAS ENTIDADES SIN ÁNIMO DE LUCRO | AI92: =AG92=I92 -> TRUE
A93: 92 | C93: VACANTE DEFINITIVA | D93: 3 | E93: PROFESIONAL | F93: PROFESIONAL UNIVERSITARIO | G93: 219 | H93: 18 | I93: =G93&"-"&H93 -> 219-18 | J93: DIRECCIÓN DISTRITAL DE INSPECCIÓN VIGILANCIA Y CONTROL DE LAS ENTIDADES SIN ÁNIMO DE LUCRO | L93: =C93=P93 -> TRUE | M93: =J93=AH93 -> TRUE | P93: VACANTE DEFINITIVA | R93: VACANTE DEFINITIVA | X93: VACANTE DEFINITIVA | AB93: VACANTE DEFINITIVA | AC93: PROFESIONAL | AD93: PROFESIONAL UNIVERSITARIO | AE93: 219 | AF93: 18 | AG93: =AE93&"-"&AF93 -> 219-18 | AH93: DIRECCIÓN DISTRITAL DE INSPECCIÓN VIGILANCIA Y CONTROL DE LAS ENTIDADES SIN ÁNIMO DE LUCRO | AI93: =AG93=I93 -> TRUE
A94: 93 | C94: VACANTE DEFINITIVA | D94: 3 | E94: PROFESIONAL | F94: PROFESIONAL UNIVERSITARIO | G94: 219 | H94: 18 | I94: =G94&"-"&H94 -> 219-18 | J94: DIRECCIÓN DISTRITAL DE INSPECCIÓN VIGILANCIA Y CONTROL DE LAS ENTIDADES SIN ÁNIMO DE LUCRO | L94: =C94=P94 -> TRUE | M94: =J94=AH94 -> TRUE | P94: VACANTE DEFINITIVA | R94: VACANTE DEFINITIVA | X94: VACANTE DEFINITIVA | AB94: VACANTE DEFINITIVA | AC94: PROFESIONAL | AD94: PROFESIONAL UNIVERSITARIO | AE94: 219 | AF94: 18 | AG94: =AE94&"-"&AF94 -> 219-18 | AH94: DIRECCIÓN DISTRITAL DE INSPECCIÓN VIGILANCIA Y CONTROL DE LAS ENTIDADES SIN ÁNIMO DE LUCRO | AI94: =AG94=I94 -> TRUE
A95: 94 | C95: VACANTE DEFINITIVA | D95: 3 | E95: PROFESIONAL | F95: PROFESIONAL UNIVERSITARIO | G95: 219 | H95: 15 | I95: =G95&"-"&H95 -> 219-15 | J95: DIRECCIÓN DISTRITAL DE ASUNTOS DISCIPLINARIOS | L95: =C95=P95 -> TRUE | M95: =J95=AH95 -> TRUE | P95: VACANTE DEFINITIVA | R95: VACANTE DEFINITIVA | X95: VACANTE DEFINITIVA | AB95: VACANTE DEFINITIVA | AC95: PROFESIONAL | AD95: PROFESIONAL UNIVERSITARIO | AE95: 219 | AF95: 15 | AG95: =AE95&"-"&AF95 -> 219-15 | AH95: DIRECCIÓN DISTRITAL DE ASUNTOS DISCIPLINARIOS | AI95: =AG95=I95 -> TRUE
A96: 95 | B96: 80060729 | C96: BELALCAZAR ERASSO EDISON ANDRES | D96: 3 | E96: PROFESIONAL | F96: PROFESIONAL UNIVERSITARIO | G96: 219 | H96: 15 | I96: =G96&"-"&H96 -> 219-15 | J96: DIRECCIÓN DISTRITAL DE INSPECCIÓN VIGILANCIA Y CONTROL DE LAS ENTIDADES SIN ÁNIMO DE LUCRO | K96: CARRERA ADMINISTRATIVA | L96: =C96=P96 -> TRUE | M96: =J96=AH96 -> TRUE | O96: 80060729 | P96: BELALCAZAR ERASSO EDISON ANDRES | Q96: CARRERA ADMINISTRATIVA | R96: CARRERA ADMINISTRATIVA | S96: 42585 | T96: 38443 | U96: HOMBRE | V96: 43 | AB96: OCUPADO | AC96: PROFESIONAL | AD96: PROFESIONAL UNIVERSITARIO | AE96: 219 | AF96: 15 | AG96: =AE96&"-"&AF96 -> 219-15 | AH96: DIRECCIÓN DISTRITAL DE INSPECCIÓN VIGILANCIA Y CONTROL DE LAS ENTIDADES SIN ÁNIMO DE LUCRO | AI96: =AG96=I96 -> TRUE
A97: 96 | C97: VACANTE DEFINITIVA | D97: 3 | E97: PROFESIONAL | F97: PROFESIONAL UNIVERSITARIO | G97: 219 | H97: 15 | I97: =G97&"-"&H97 -> 219-15 | J97: DIRECCIÓN DISTRITAL DE INSPECCIÓN VIGILANCIA Y CONTROL DE LAS ENTIDADES SIN ÁNIMO DE LUCRO | L97: =C97=P97 -> TRUE | M97: =J97=AH97 -> TRUE | P97: VACANTE DEFINITIVA | R97: VACANTE DEFINITIVA | X97: VACANTE DEFINITIVA | AB97: VACANTE DEFINITIVA | AC97: PROFESIONAL | AD97: PROFESIONAL UNIVERSITARIO | AE97: 219 | AF97: 15 | AG97: =AE97&"-"&AF97 -> 219-15 | AH97: DIRECCIÓN DISTRITAL DE INSPECCIÓN VIGILANCIA Y CONTROL DE LAS ENTIDADES SIN ÁNIMO DE LUCRO | AI97: =AG97=I97 -> TRUE
A98: 97 | C98: VACANTE DEFINITIVA | D98: 3 | E98: PROFESIONAL | F98: PROFESIONAL UNIVERSITARIO | G98: 219 | H98: 15 | I98: =G98&"-"&H98 -> 219-15 | J98: DIRECCIÓN DISTRITAL DE INSPECCIÓN VIGILANCIA Y CONTROL DE LAS ENTIDADES SIN ÁNIMO DE LUCRO | L98: =C98=P98 -> TRUE | M98: =J98=AH98 -> TRUE | P98: VACANTE DEFINITIVA | R98: VACANTE DEFINITIVA | X98: VACANTE DEFINITIVA | AB98: VACANTE DEFINITIVA | AC98: PROFESIONAL | AD98: PROFESIONAL UNIVERSITARIO | AE98: 219 | AF98: 15 | AG98: =AE98&"-"&AF98 -> 219-15 | AH98: DIRECCIÓN DISTRITAL DE INSPECCIÓN VIGILANCIA Y CONTROL DE LAS ENTIDADES SIN ÁNIMO DE LUCRO | AI98: =AG98=I98 -> TRUE
A99: 98 | C99: VACANTE DEFINITIVA | D99: 3 | E99: PROFESIONAL | F99: PROFESIONAL UNIVERSITARIO | G99: 219 | H99: 15 | I99: =G99&"-"&H99 -> 219-15 | J99: DIRECCIÓN DISTRITAL DE INSPECCIÓN VIGILANCIA Y CONTROL DE LAS ENTIDADES SIN ÁNIMO DE LUCRO | L99: =C99=P99 -> TRUE | M99: =J99=AH99 -> TRUE | P99: VACANTE DEFINITIVA | R99: VACANTE DEFINITIVA | X99: VACANTE DEFINITIVA | AB99: VACANTE DEFINITIVA | AC99: PROFESIONAL | AD99: PROFESIONAL UNIVERSITARIO | AE99: 219 | AF99: 15 | AG99: =AE99&"-"&AF99 -> 219-15 | AH99: DIRECCIÓN DISTRITAL DE INSPECCIÓN VIGILANCIA Y CONTROL DE LAS ENTIDADES SIN ÁNIMO DE LUCRO | AI99: =AG99=I99 -> TRUE
A100: 99 | C100: VACANTE DEFINITIVA | D100: 3 | E100: PROFESIONAL | F100: PROFESIONAL UNIVERSITARIO | G100: 219 | H100: 13 | I100: =G100&"-"&H100 -> 219-13 | J100: OFICINA DE CONTROL INTERNO | L100: =C100=P100 -> TRUE | M100: =J100=AH100 -> TRUE | P100: VACANTE DEFINITIVA | R100: VACANTE DEFINITIVA | X100: VACANTE DEFINITIVA | AB100: VACANTE DEFINITIVA | AC100: PROFESIONAL | AD100: PROFESIONAL UNIVERSITARIO | AE100: 219 | AF100: 13 | AG100: =AE100&"-"&AF100 -> 219-13 | AH100: OFICINA DE CONTROL INTERNO | AI100: =AG100=I100 -> TRUE
...

Sheet PLANTA INICIAL (2)
B1: CC | C1: NOMBRE | D1: N | E1: NIVEL | F1: NOMENCLATURA_ADMIN | G1: CÓDIGO | H1: GRADO | J1: DEPENDENCIA | K1: NOMBRAMIENTO | N1: ID PERNO | AK1: DEPENDENCIA DEL CARGO
A2: 15 | C2: VACANTE DEFINITIVA | D2: 2 | E2: ASESOR | F2: JEFE DE OFICINA | G2: 115 | H2: 6 | I2: =G2&"-"&H2 -> 115-6 | J2: OFICINA ASESORA DE PLANEACIÓN | L2: =C2=P2 -> TRUE | M2: =J2=AH2 -> TRUE | N2: 11 | P2: VACANTE DEFINITIVA | R2: VACANTE DEFINITIVA | X2: VACANTE DEFINITIVA | AB2: VACANTE DEFINITIVA | AC2: ASESOR | AD2: JEFE DE OFICINA | AE2: 115 | AF2: 6 | AG2: =AE2&"-"&AF2 -> 115-6 | AH2: OFICINA ASESORA DE PLANEACIÓN | AI2: =AG2=I2 -> TRUE | AK2: OFICINA ASESORA DE PLANEACIÓN | AL2: =J2=AK2 -> TRUE
A3: 16 | C3: VACANTE DEFINITIVA | D3: 2 | E3: ASESOR | F3: JEFE DE OFICINA | G3: 115 | H3: 6 | I3: =G3&"-"&H3 -> 115-6 | J3: OFICINA DE LAS TECNOLOGÍAS DE LA INFORMACIÓN Y LAS COMUNICACIONES | L3: =C3=P3 -> FALSE | M3: =J3=AH3 -> FALSE | N3: 171 | O3: 19498970 | P3: OJEDA MONCAYO DIEGO EMILIO | Q3: LIBRE NOMBRAMIENTO Y REMOCIÓN | R3: NOMBRAMIENTO ORDINARIO | S3: 42622 | T3: 42622 | U3: HOMBRE | V3: 59 | X3: VACANTE DEFINITIVA | AB3: OCUPADO | AC3: ASESOR | AD3: JEFE DE OFICINA | AE3: 115 | AF3: 6 | AG3: =AE3&"-"&AF3 -> 115-6 | AH3: OFICINA DE TECNOLOGÍA DE LA INFORMACIÓN, SISTEMAS Y COMUNICACIONES | AI3: =AG3=I3 -> TRUE | AK3: OFICINA DE LAS TECNOLOGÍAS DE LA INFORMACIÓN Y LAS COMUNICACIONES | AL3: =J3=AK3 -> TRUE
A4: 10 | B4: 1085262099 | C4: BURBANO SÁNCHEZ MARÍA ANGÉLICA | D4: 2 | E4: ASESOR | F4: ASESOR | G4: 105 | H4: 5 | I4: =G4&"-"&H4 -> 105-5 | J4: DESPACHO SECRETARÍA JURÍDICA | K4: LIBRE NOMBRAMIENTO | L4: =C4=P4 -> FALSE | M4: =J4=AH4 -> FALSE | N4: 12 | O4: 79317479 | P4: CORDOBA DELGADO JOSE IGNACIO | Q4: LIBRE NOMBRAMIENTO Y REMOCIÓN | R4: NOMBRAMIENTO ORDINARIO | S4: 42632 | T4: 42632 | U4: HOMBRE | V4: 60 | X4: VACANTE DEFINITIVA | AB4: OCUPADO | AC4: ASESOR | AD4: ASESOR | AE4: 105 | AF4: 5 | AG4: =AE4&"-"&AF4 -> 105-5 | AH4: DESPACHO | AI4: =AG4=I4 -> TRUE | AK4: DESPACHO SECRETARÍA JURÍDICA | AL4: =J4=AK4 -> TRUE
A5: 11 | B5: 80040965 | C5: CUELLAR TRUJILLO PEDRO ANDRÉS | D5: 2 | E5: ASESOR | F5: ASESOR | G5: 105 | H5: 5 | I5: =G5&"-"&H5 -> 105-5 | J5: DESPACHO SECRETARÍA JURÍDICA | K5: LIBRE NOMBRAMIENTO | L5: =C5=P5 -> TRUE | M5: =J5=AH5 -> FALSE | N5: 13 | O5: 80040965 | P5: CUELLAR TRUJILLO PEDRO ANDRÉS | Q5: LIBRE NOMBRAMIENTO Y REMOCIÓN | R5: NOMBRAMIENTO ORDINARIO | S5: 42585 | T5: 42401 | U5: HOMBRE | V5: 39 | AB5: OCUPADO | AC5: ASESOR | AD5: ASESOR | AE5: 105 | AF5: 5 | AG5: =AE5&"-"&AF5 -> 105-5 | AH5: DESPACHO | AI5: =AG5=I5 -> TRUE | AK5: DESPACHO SECRETARÍA JURÍDICA | AL5: =J5=AK5 -> TRUE
A6: 12 | B6: 72291125 | C6: ESPINOSA OTERO ANDRES MAURICIO | D6: 2 | E6: ASESOR | F6: ASESOR | G6: 105 | H6: 5 | I6: =G6&"-"&H6 -> 105-5 | J6: DESPACHO SECRETARÍA JURÍDICA | K6: LIBRE NOMBRAMIENTO | L6: =C6=P6 -> TRUE | M6: =J6=AH6 -> FALSE | N6: 14 | O6: 72291125 | P6: ESPINOSA OTERO ANDRES MAURICIO | Q6: LIBRE NOMBRAMIENTO Y REMOCIÓN | R6: NOMBRAMIENTO ORDINARIO | S6: 42585 | T6: 42468 | U6: HOMBRE | V6: 38 | AB6: OCUPADO | AC6: ASESOR | AD6: ASESOR | AE6: 105 | AF6: 5 | AG6: =AE6&"-"&AF6 -> 105-5 | AH6: DESPACHO | AI6: =AG6=I6 -> TRUE | AK6: DESPACHO SECRETARÍA JURÍDICA | AL6: =J6=AK6 -> TRUE
A7: 13 | B7: 52233911 | C7: RODRÍGUEZ BARRERA NOHORA PATRICIA | D7: 2 | E7: ASESOR | F7: ASESOR | G7: 105 | H7: 5 | I7: =G7&"-"&H7 -> 105-5 | J7: DESPACHO SECRETARÍA JURÍDICA | K7: LIBRE NOMBRAMIENTO | L7: =C7=P7 -> TRUE | M7: =J7=AH7 -> FALSE | N7: 15 | O7: 52233911 | P7: RODRÍGUEZ BARRERA NOHORA PATRICIA | Q7: LIBRE NOMBRAMIENTO Y REMOCIÓN | R7: NOMBRAMIENTO ORDINARIO | S7: 42585 | T7: 35900 | U7: MUJER | V7: 44 | AB7: OCUPADO | AC7: ASESOR | AD7: ASESOR | AE7: 105 | AF7: 5 | AG7: =AE7&"-"&AF7 -> 105-5 | AH7: DESPACHO | AI7: =AG7=I7 -> TRUE | AK7: DESPACHO SECRETARÍA JURÍDICA | AL7: =J7=AK7 -> TRUE
A8: 14 | B8: 52394165 | C8: TOBÓN DÍAZ ALEJANDRA | D8: 2 | E8: ASESOR | F8: ASESOR | G8: 105 | H8: 5 | I8: =G8&"-"&H8 -> 105-5 | J8: DESPACHO SECRETARÍA JURÍDICA | K8: LIBRE NOMBRAMIENTO | L8: =C8=P8 -> FALSE | M8: =J8=AH8 -> FALSE | N8: 16 | P8: VACANTE TEMPORAL | R8: VACANTE TEMPORAL | X8: TOBÓN DÍAZ ALEJANDRA | Y8: E02 | Z8: VT | AB8: OCUPADO | AC8: ASESOR | AD8: ASESOR | AE8: 105 | AF8: 5 | AG8: =AE8&"-"&AF8 -> 105-5 | AH8: DESPACHO | AI8: =AG8=I8 -> TRUE | AK8: DESPACHO SECRETARÍA JURÍDICA | AL8: =J8=AK8 -> TRUE
A9: 136 | B9: 19209798 | C9: JIMENEZ RIVERA GUSTAVO ADOLFO | D9: 5 | E9: ASISTENCIAL | F9: AUXILIAR ADMINISTRATIVO | G9: 407 | H9: 27 | I9: =G9&"-"&H9 -> 407-27 | J9: DIRECCIÓN DE GESTIÓN CORPORATIVA | K9: CARRERA ADMINISTRATIVA | L9: =C9=P9 -> TRUE | M9: =J9=AH9 -> FALSE | N9: 137 | O9: 19209798 | P9: JIMENEZ RIVERA GUSTAVO ADOLFO | Q9: CARRERA ADMINISTRATIVA | R9: CARRERA ADMINISTRATIVA | S9: 42585 | T9: 35815 | U9: HOMBRE | V9: 69 | AB9: OCUPADO | AC9: ASISTENCIAL | AD9: AUXILIAR ADMINISTRATIVO | AE9: 407 | AF9: 27 | AG9: 407-27 | AH9: DIRECCIÓN CORPORATIVA | AI9: =AG9=I9 -> TRUE | AK9: DIRECCIÓN DE GESTIÓN CORPORATIVA | AL9: =J9=AK9 -> TRUE
A10: 137 | C10: VACANTE DEFINITIVA | D10: 5 | E10: ASISTENCIAL | F10: AUXILIAR ADMINISTRATIVO | G10: 407 | H10: 26 | I10: =G10&"-"&H10 -> 407-26 | J10: DIRECCIÓN DISTRITAL DE INSPECCIÓN, VIGILANCIA Y CONTROL | L10: =C10=P10 -> TRUE | M10: =J10=AH10 -> FALSE | N10: 165 | P10: VACANTE DEFINITIVA | R10: VACANTE DEFINITIVA | X10: VACANTE DEFINITIVA | AB10: VACANTE DEFINITIVA | AC10: ASISTENCIAL | AD10: AUXILIAR ADMINISTRATIVO | AE10: 407 | AF10: 26 | AG10: 407-26 | AH10: DIRECCIÓN DISTRITAL DE INSPECCIÓN VIGILANCIA Y CONTROL DE LAS ENTIDADES SIN ÁNIMO DE LUCRO | AI10: =AG10=I10 -> TRUE | AK10: DIRECCIÓN DISTRITAL DE GESTION JUDICIAL | AL10: =J10=AK10 -> FALSE
A11: 138 | C11: VACANTE DEFINITIVA | D11: 5 | E11: ASISTENCIAL | F11: AUXILIAR ADMINISTRATIVO | G11: 407 | H11: 24 | I11: =G11&"-"&H11 -> 407-24 | J11: DIRECCIÓN DE GESTIÓN CORPORATIVA | L11: =C11=P11 -> TRUE | M11: =J11=AH11 -> FALSE | N11: 138 | P11: VACANTE DEFINITIVA | R11: VACANTE DEFINITIVA | X11: VACANTE DEFINITIVA | AB11: VACANTE DEFINITIVA | AC11: ASISTENCIAL | AD11: AUXILIAR ADMINISTRATIVO | AE11: 407 | AF11: 24 | AG11: 407-24 | AH11: DIRECCIÓN CORPORATIVA | AI11: =AG11=I11 -> TRUE | AK11: DIRECCIÓN DISTRITAL DE ASUNTOS DISCIPLINARIOS | AL11: =J11=AK11 -> FALSE
A12: 139 | B12: 79431243 | C12: OSPINA ZAPATA WALTER | D12: 5 | E12: ASISTENCIAL | F12: AUXILIAR ADMINISTRATIVO | G12: 407 | H12: 20 | I12: =G12&"-"&H12 -> 407-20 | J12: DIRECCIÓN DE GESTIÓN CORPORATIVA | K12: CARRERA ADMINISTRATIVA | L12: =C12=P12 -> TRUE | M12: =J12=AH12 -> FALSE | N12: 166 | O12: 79431243 | P12: OSPINA ZAPATA WALTER | Q12: CARRERA ADMINISTRATIVA | R12: CARRERA ADMINISTRATIVA | S12: 42585 | T12: 38443 | U12: HOMBRE | V12: 55 | AB12: OCUPADO | AC12: ASISTENCIAL | AD12: AUXILIAR ADMINISTRATIVO | AE12: 407 | AF12: 20 | AG12: 407-20 | AH12: DIRECCIÓN CORPORATIVA | AI12: =AG12=I12 -> TRUE | AK12: OFICINA DE LAS TECNOLOGÍAS DE LA INFORMACIÓN Y LAS COMUNICACIONES | AL12: =J12=AK12 -> FALSE
A13: 140 | B13: 51628413 | C13: SALAMANCA CUEVAS LUZ MAVEL | D13: 5 | E13: ASISTENCIAL | F13: AUXILIAR ADMINISTRATIVO | G13: 407 | H13: 20 | I13: =G13&"-"&H13 -> 407-20 | J13: SUBSECRETARÍA JURÍDICA DISTRITAL | K13: CARRERA ADMINISTRATIVA | L13: =C13=P13 -> TRUE | M13: =J13=AH13 -> FALSE | N13: 139 | O13: 51628413 | P13: SALAMANCA CUEVAS LUZ MAVEL | Q13: CARRERA ADMINISTRATIVA | R13: CARRERA ADMINISTRATIVA | S13: 42585 | T13: 30587 | U13: MUJER | V13: 61 | AB13: OCUPADO | AC13: ASISTENCIAL | AD13: AUXILIAR ADMINISTRATIVO | AE13: 407 | AF13: 20 | AG13: 407-20 | AH13: SUBSECRETARÍA JURÍDICA | AI13: =AG13=I13 -> TRUE | AK13: DIRECCIÓN DE GESTIÓN CORPORATIVA | AL13: =J13=AK13 -> FALSE
A14: 141 | B14: 79138328 | C14: CORTES SALGADO ALEX | D14: 5 | E14: ASISTENCIAL | F14: AUXILIAR ADMINISTRATIVO | G14: 407 | H14: 20 | I14: =G14&"-"&H14 -> 407-20 | J14: DIRECCIÓN DISTRITAL DE GESTION JUDICIAL | K14: CARRERA ADMINISTRATIVA | L14: =C14=P14 -> TRUE | M14: =J14=AH14 -> FALSE | N14: 167 | O14: 79138328 | P14: CORTES SALGADO ALEX | Q14: CARRERA ADMINISTRATIVA | R14: CARRERA ADMINISTRATIVA | S14: 42585 | T14: 34711 | U14: HOMBRE | V14: 50 | AB14: OCUPADO | AC14: ASISTENCIAL | AD14: AUXILIAR ADMINISTRATIVO | AE14: 407 | AF14: 20 | AG14: 407-20 | AH14: DIRECCIÓN DISTRITAL DE DEFENSA JUDICIAL Y PREVENCIÓN DEL DAÑO ANTIJURÍDICO | AI14: =AG14=I14 -> TRUE | AK14: DIRECCIÓN DISTRITAL DE ASUNTOS DISCIPLINARIOS | AL14: =J14=AK14 -> FALSE
A15: 142 | B15: 35337860 | C15: NAVA SERRANO MERY ANEIDA | D15: 5 | E15: ASISTENCIAL | F15: AUXILIAR ADMINISTRATIVO | G15: 407 | H15: 17 | I15: =G15&"-"&H15 -> 407-17 | J15: DIRECCIÓN DE GESTIÓN CORPORATIVA | K15: PROVISIONAL | L15: =C15=P15 -> FALSE | M15: =J15=AH15 -> FALSE | N15: 140 | P15: VACANTE DEFINITIVA | R15: VACANTE DEFINITIVA | X15: VACANTE DEFINITIVA | AB15: VACANTE DEFINITIVA | AC15: ASISTENCIAL | AD15: AUXILIAR ADMINISTRATIVO | AE15: 407 | AF15: 17 | AG15: 407-17 | AH15: DIRECCIÓN CORPORATIVA | AI15: =AG15=I15 -> TRUE | AK15: DIRECCIÓN DE GESTIÓN CORPORATIVA | AL15: =J15=AK15 -> TRUE
A16: 143 | B16: 80775238 | C16: TORRES GRANADOS LUIS GABRIEL | D16: 5 | E16: ASISTENCIAL | F16: AUXILIAR ADMINISTRATIVO | G16: 407 | H16: 16 | I16: =G16&"-"&H16 -> 407-16 | J16: DIRECCIÓN DE GESTIÓN CORPORATIVA | K16: PROVISIONAL | L16: =C16=P16 -> TRUE | M16: =J16=AH16 -> FALSE | N16: 141 | O16: 80775238 | P16: TORRES GRANADOS LUIS GABRIEL | Q16: PROVISIONALIDAD | R16: EN PROVISIONALIDAD | S16: 42585 | T16: 39892 | U16: HOMBRE | V16: 36 | X16: VACANTE DEFINITIVA | AB16: OCUPADO | AC16: ASISTENCIAL | AD16: AUXILIAR ADMINISTRATIVO | AE16: 407 | AF16: 16 | AG16: 407-16 | AH16: DIRECCIÓN CORPORATIVA | AI16: =AG16=I16 -> TRUE | AK16: DESPACHO SECRETARÍA JURÍDICA | AL16: =J16=AK16 -> FALSE
A17: 144 | C17: VACANTE DEFINITIVA | D17: 5 | E17: ASISTENCIAL | F17: AUXILIAR ADMINISTRATIVO | G17: 407 | H17: 16 | I17: =G17&"-"&H17 -> 407-16 | J17: DESPACHO SECRETARÍA JURÍDICA | L17: =C17=P17 -> TRUE | M17: =J17=AH17 -> FALSE | N17: 142 | P17: VACANTE DEFINITIVA | R17: VACANTE DEFINITIVA | X17: VACANTE DEFINITIVA | AB17: VACANTE DEFINITIVA | AC17: ASISTENCIAL | AD17: AUXILIAR ADMINISTRATIVO | AE17: 407 | AF17: 16 | AG17: 407-16 | AH17: DESPACHO | AI17: =AG17=I17 -> TRUE | AK17: DIRECCIÓN DISTRITAL DE GESTION JUDICIAL | AL17: =J17=AK17 -> FALSE
A18: 145 | B18: 19443235 | C18: GARZON LUIS ENRIQUE | D18: 5 | E18: ASISTENCIAL | F18: AUXILIAR ADMINISTRATIVO | G18: 407 | H18: 15 | I18: =G18&"-"&H18 -> 407-15 | J18: DIRECCIÓN DISTRITAL DE GESTION JUDICIAL | K18: CARRERA ADMINISTRATIVA | L18: =C18=P18 -> TRUE | M18: =J18=AH18 -> FALSE | N18: 168 | O18: 19443235 | P18: GARZON LUIS ENRIQUE | Q18: CARRERA ADMINISTRATIVA | R18: CARRERA ADMINISTRATIVA | S18: 42585 | T18: 33462 | U18: HOMBRE | V18: 62 | AB18: OCUPADO | AC18: ASISTENCIAL | AD18: AUXILIAR ADMINISTRATIVO | AE18: 407 | AF18: 15 | AG18: 407-15 | AH18: DIRECCIÓN DISTRITAL DE DEFENSA JUDICIAL Y PREVENCIÓN DEL DAÑO ANTIJURÍDICO | AI18: =AG18=I18 -> TRUE | AK18: DIRECCIÓN DISTRITAL DE INSPECCIÓN, VIGILANCIA Y CONTROL | AL18: =J18=AK18 -> FALSE
A19: 146 | B19: 41713009 | C19: QUIROGA DE GAMBOA MARTHA LUZ | D19: 5 | E19: ASISTENCIAL | F19: AUXILIAR ADMINISTRATIVO | G19: 407 | H19: 15 | I19: =G19&"-"&H19 -> 407-15 | J19: DIRECCIÓN DISTRITAL DE GESTION JUDICIAL | K19: CARRERA ADMINISTRATIVA | L19: =C19=P19 -> TRUE | M19: =J19=AH19 -> FALSE | N19: 159 | O19: 41713009 | P19: QUIROGA DE GAMBOA MARTHA LUZ | Q19: CARRERA ADMINISTRATIVA | R19: CARRERA ADMINISTRATIVA | S19: 42585 | T19: 34169 | U19: MUJER | V19: 67 | AB19: OCUPADO | AC19: ASISTENCIAL | AD19: AUXILIAR ADMINISTRATIVO | AE19: 407 | AF19: 15 | AG19: 407-15 | AH19: DIRECCIÓN DISTRITAL DE DEFENSA JUDICIAL Y PREVENCIÓN DEL DAÑO ANTIJURÍDICO | AI19: =AG19=I19 -> TRUE | AK19: DIRECCIÓN DISTRITAL DE GESTION JUDICIAL | AL19: =J19=AK19 -> TRUE
A20: 147 | B20: 41774744 | C20: ORTIZ RODRIGUEZ JUDITH | D20: 5 | E20: ASISTENCIAL | F20: AUXILIAR ADMINISTRATIVO | G20: 407 | H20: 15 | I20: =G20&"-"&H20 -> 407-15 | J20: DIRECCIÓN DISTRITAL DE GESTION JUDICIAL | K20: CARRERA ADMINISTRATIVA | L20: =C20=P20 -> TRUE | M20: =J20=AH20 -> FALSE | N20: 143 | O20: 41774744 | P20: ORTIZ RODRIGUEZ JUDITH | Q20: CARRERA ADMINISTRATIVA | R20: CARRERA ADMINISTRATIVA | S20: 42585 | T20: 36102 | U20: MUJER | V20: 65 | AB20: OCUPADO | AC20: ASISTENCIAL | AD20: AUXILIAR ADMINISTRATIVO | AE20: 407 | AF20: 15 | AG20: 407-15 | AH20: DIRECCIÓN DISTRITAL DE DEFENSA JUDICIAL Y PREVENCIÓN DEL DAÑO ANTIJURÍDICO | AI20: =AG20=I20 -> TRUE | AK20: DIRECCIÓN DE GESTIÓN CORPORATIVA | AL20: =J20=AK20 -> FALSE
A21: 148 | B21: 52235989 | C21: ARDILA VERGARA MILDRED PAOLA | D21: 5 | E21: ASISTENCIAL | F21: AUXILIAR ADMINISTRATIVO | G21: 407 | H21: 15 | I21: =G21&"-"&H21 -> 407-15 | J21: DIRECCIÓN DISTRITAL DE INSPECCIÓN, VIGILANCIA Y CONTROL | K21: CARRERA ADMINISTRATIVA | L21: =C21=P21 -> TRUE | M21: =J21=AH21 -> FALSE | N21: 144 | O21: 52235989 | P21: ARDILA VERGARA MILDRED PAOLA | Q21: CARRERA ADMINISTRATIVA | R21: CARRERA ADMINISTRATIVA | S21: 42585 | T21: 38446 | U21: MUJER | V21: 43 | AB21: OCUPADO | AC21: ASISTENCIAL | AD21: AUXILIAR ADMINISTRATIVO | AE21: 407 | AF21: 15 | AG21: 407-15 | AH21: DIRECCIÓN DISTRITAL DE INSPECCIÓN VIGILANCIA Y CONTROL DE LAS ENTIDADES SIN ÁNIMO DE LUCRO | AI21: =AG21=I21 -> TRUE | AK21: DIRECCIÓN DE GESTIÓN CORPORATIVA | AL21: =J21=AK21 -> FALSE
A22: 149 | B22: 51732443 | C22: TORRES ROJAS ACENETH | D22: 5 | E22: ASISTENCIAL | F22: AUXILIAR ADMINISTRATIVO | G22: 407 | H22: 15 | I22: =G22&"-"&H22 -> 407-15 | J22: DIRECCIÓN DISTRITAL DE INSPECCIÓN, VIGILANCIA Y CONTROL | K22: CARRERA ADMINISTRATIVA | L22: =C22=P22 -> TRUE | M22: =J22=AH22 -> FALSE | N22: 145 | O22: 51732443 | P22: TORRES ROJAS ACENETH | Q22: CARRERA ADMINISTRATIVA | R22: CARRERA ADMINISTRATIVA | S22: 42585 | T22: 40672 | U22: MUJER | V22: 58 | AB22: OCUPADO | AC22: ASISTENCIAL | AD22: AUXILIAR ADMINISTRATIVO | AE22: 407 | AF22: 15 | AG22: 407-15 | AH22: DIRECCIÓN DISTRITAL DE INSPECCIÓN VIGILANCIA Y CONTROL DE LAS ENTIDADES SIN ÁNIMO DE LUCRO | AI22: =AG22=I22 -> TRUE | AK22: DIRECCIÓN DE GESTIÓN CORPORATIVA | AL22: =J22=AK22 -> FALSE
A23: 150 | B23: 79262614 | C23: LÓPEZ ACUÑA OSCAR ERNESTO | D23: 5 | E23: ASISTENCIAL | F23: AUXILIAR ADMINISTRATIVO | G23: 407 | H23: 14 | I23: =G23&"-"&H23 -> 407-14 | J23: DIRECCIÓN DE GESTIÓN CORPORATIVA | K23: CARRERA ADMINISTRATIVA | L23: =C23=P23 -> TRUE | M23: =J23=AH23 -> FALSE | N23: 146 | O23: 79262614 | P23: LÓPEZ ACUÑA OSCAR ERNESTO | Q23: CARRERA ADMINISTRATIVA | R23: CARRERA ADMINISTRATIVA | S23: 42585 | T23: 35906 | U23: HOMBRE | V23: 59 | AB23: OCUPADO | AC23: ASISTENCIAL | AD23: AUXILIAR ADMINISTRATIVO | AE23: 407 | AF23: 14 | AG23: 407-14 | AH23: DIRECCIÓN CORPORATIVA | AI23: =AG23=I23 -> TRUE | AK23: DIRECCIÓN DISTRITAL DE GESTION JUDICIAL | AL23: =J23=AK23 -> FALSE
A24: 151 | B24: 51882380 | C24: FORERO FORERO CARMEN ALICIA | D24: 5 | E24: ASISTENCIAL | F24: AUXILIAR ADMINISTRATIVO | G24: 407 | H24: 13 | I24: =G24&"-"&H24 -> 407-13 | J24: DIRECCIÓN DE GESTIÓN CORPORATIVA | K24: CARRERA ADMINISTRATIVA | L24: =C24=P24 -> TRUE | M24: =J24=AH24 -> FALSE | N24: 147 | O24: 51882380 | P24: FORERO FORERO CARMEN ALICIA | Q24: CARRERA ADMINISTRATIVA | R24: CARRERA ADMINISTRATIVA | S24: 42585 | T24: 33672 | U24: MUJER | V24: 56 | AB24: OCUPADO | AC24: ASISTENCIAL | AD24: AUXILIAR ADMINISTRATIVO | AE24: 407 | AF24: 13 | AG24: 407-13 | AH24: DIRECCIÓN CORPORATIVA | AI24: =AG24=I24 -> TRUE | AK24: DIRECCIÓN DISTRITAL DE DOCTRINA Y ASUNTOS NORMATIVOS | AL24: =J24=AK24 -> FALSE
A25: 152 | B25: 79468462 | C25: GARCIA GARAVITO EDGAR ANDRES | D25: 5 | E25: ASISTENCIAL | F25: AUXILIAR ADMINISTRATIVO | G25: 407 | H25: 11 | I25: =G25&"-"&H25 -> 407-11 | J25: DIRECCIÓN DE GESTIÓN CORPORATIVA | K25: CARRERA ADMINISTRATIVA | L25: =C25=P25 -> TRUE | M25: =J25=AH25 -> FALSE | N25: 148 | O25: 79468462 | P25: GARCIA GARAVITO EDGAR ANDRES | Q25: CARRERA ADMINISTRATIVA | R25: CARRERA ADMINISTRATIVA | S25: 42585 | T25: 35506 | U25: HOMBRE | V25: 53 | AB25: OCUPADO | AC25: ASISTENCIAL | AD25: AUXILIAR ADMINISTRATIVO | AE25: 407 | AF25: 11 | AG25: 407-11 | AH25: DIRECCIÓN CORPORATIVA | AI25: =AG25=I25 -> TRUE | AK25: DIRECCIÓN DE GESTIÓN CORPORATIVA | AL25: =J25=AK25 -> TRUE
A26: 153 | B26: 41780136 | C26: URREGO DE GARCIA LUZ STELLA | D26: 5 | E26: ASISTENCIAL | F26: AUXILIAR ADMINISTRATIVO | G26: 407 | H26: 11 | I26: =G26&"-"&H26 -> 407-11 | J26: DIRECCIÓN DE GESTIÓN CORPORATIVA | K26: CARRERA ADMINISTRATIVA | L26: =C26=P26 -> TRUE | M26: =J26=AH26 -> FALSE | N26: 149 | O26: 41780136 | P26: URREGO DE GARCIA LUZ STELLA | Q26: CARRERA ADMINISTRATIVA | R26: CARRERA ADMINISTRATIVA | S26: 42585 | T26: 34872 | U26: MUJER | V26: 62 | AB26: OCUPADO | AC26: ASISTENCIAL | AD26: AUXILIAR ADMINISTRATIVO | AE26: 407 | AF26: 11 | AG26: 407-11 | AH26: DIRECCIÓN CORPORATIVA | AI26: =AG26=I26 -> TRUE | AK26: DIRECCIÓN DE GESTIÓN CORPORATIVA | AL26: =J26=AK26 -> TRUE
A27: 154 | B27: 51623332 | C27: MONTEJO GARZÓN YOLANDA | D27: 5 | E27: ASISTENCIAL | F27: AUXILIAR ADMINISTRATIVO | G27: 407 | H27: 9 | I27: =G27&"-"&H27 -> 407-9 | J27: DIRECCIÓN DISTRITAL DE ASUNTOS DISCIPLINARIOS | K27: CARRERA ADMINISTRATIVA | L27: =C27=P27 -> TRUE | M27: =J27=AH27 -> TRUE | N27: 150 | O27: 51623332 | P27: MONTEJO GARZÓN YOLANDA | Q27: CARRERA ADMINISTRATIVA | R27: CARRERA ADMINISTRATIVA | S27: 42585 | T27: 33717 | U27: MUJER | V27: 61 | AB27: OCUPADO | AC27: ASISTENCIAL | AD27: AUXILIAR ADMINISTRATIVO | AE27: 407 | AF27: 9 | AG27: 407-9 | AH27: DIRECCIÓN DISTRITAL DE ASUNTOS DISCIPLINARIOS | AI27: =AG27=I27 -> TRUE | AK27: DIRECCIÓN DISTRITAL DE INSPECCIÓN, VIGILANCIA Y CONTROL | AL27: =J27=AK27 -> FALSE
A28: 155 | B28: 79048737 | C28: PULIDO SALAMANCA PABLO DANIEL | D28: 5 | E28: ASISTENCIAL | F28: CONDUCTOR | G28: 480 | H28: 13 | I28: =G28&"-"&H28 -> 480-13 | J28: DIRECCIÓN DE GESTIÓN CORPORATIVA | K28: CARRERA ADMINISTRATIVA | L28: =C28=P28 -> TRUE | M28: =J28=AH28 -> FALSE | N28: 151 | O28: 79048737 | P28: PULIDO SALAMANCA PABLO DANIEL | Q28: CARRERA ADMINISTRATIVA | R28: CARRERA ADMINISTRATIVA | S28: 42585 | T28: 35926 | U28: HOMBRE | V28: 57 | AB28: OCUPADO | AC28: ASISTENCIAL | AD28: CONDUCTOR | AE28: 480 | AF28: 13 | AG28: 480-13 | AH28: DIRECCIÓN CORPORATIVA | AI28: =AG28=I28 -> TRUE | AK28: DIRECCIÓN DE GESTIÓN CORPORATIVA | AL28: =J28=AK28 -> TRUE
A29: 156 | C29: VACANTE DEFINITIVA | D29: 5 | E29: ASISTENCIAL | F29: CONDUCTOR | G29: 480 | H29: 13 | I29: =G29&"-"&H29 -> 480-13 | J29: DIRECCIÓN DE GESTIÓN CORPORATIVA | L29: =C29=P29 -> FALSE | M29: =J29=AH29 -> FALSE | N29: 152 | O29: 79271403 | P29: LARROTA SUTA PEDRO LUIS | Q29: PROVISIONALIDAD | R29: EN PROVISIONALIDAD | S29: 42608 | T29: 42608 | U29: HOMBRE | V29: 59 | X29: VACANTE DEFINITIVA | AB29: OCUPADO | AC29: ASISTENCIAL | AD29: CONDUCTOR | AE29: 480 | AF29: 13 | AG29: 480-13 | AH29: DIRECCIÓN CORPORATIVA | AI29: =AG29=I29 -> TRUE | AK29: SUBSECRETARÍA JURÍDICA DISTRITAL | AL29: =J29=AK29 -> FALSE
A30: 157 | C30: VACANTE DEFINITIVA | D30: 5 | E30: ASISTENCIAL | F30: CONDUCTOR | G30: 480 | H30: 13 | I30: =G30&"-"&H30 -> 480-13 | J30: DIRECCIÓN DE GESTIÓN CORPORATIVA | L30: =C30=P30 -> FALSE | M30: =J30=AH30 -> FALSE | N30: 156 | O30: 79740255 | P30: HERNAN ADOLFO CASTAÑEDA FIALLO | Q30: PROVISIONALIDAD | R30: EN PROVISIONALIDAD | S30: 42608 | T30: 42608 | U30: HOMBRE | V30: 46 | X30: VACANTE DEFINITIVA | AB30: OCUPADO | AC30: ASISTENCIAL | AD30: CONDUCTOR | AE30: 480 | AF30: 13 | AG30: 480-13 | AH30: DIRECCIÓN CORPORATIVA | AI30: =AG30=I30 -> TRUE | AK30: DIRECCIÓN DE GESTIÓN CORPORATIVA | AL30: =J30=AK30 -> TRUE
A31: 158 | B31: 52557124 | C31: SILVA GARCIA DORIS | D31: 5 | E31: ASISTENCIAL | F31: SECRETARIO | G31: 440 | H31: 19 | I31: =G31&"-"&H31 -> 440-19 | J31: DIRECCIÓN DISTRITAL DE GESTION JUDICIAL | K31: CARRERA ADMINISTRATIVA | L31: =C31=P31 -> TRUE | M31: =J31=AH31 -> FALSE | N31: 158 | O31: 52557124 | P31: SILVA GARCIA DORIS | Q31: CARRERA ADMINISTRATIVA | R31: CARRERA ADMINISTRATIVA | S31: 42585 | T31: 36307 | U31: MUJER | V31: 50 | AB31: OCUPADO | AC31: ASISTENCIAL | AD31: SECRETARIO | AE31: 440 | AF31: 19 | AG31: 440-19 | AH31: DIRECCIÓN DISTRITAL DE DEFENSA JUDICIAL Y PREVENCIÓN DEL DAÑO ANTIJURÍDICO | AI31: =AG31=I31 -> TRUE | AK31: DIRECCIÓN DE GESTIÓN CORPORATIVA | AL31: =J31=AK31 -> FALSE
A32: 159 | B32: 52033959 | C32: HERNÁNDEZ NAVARRO MARIBEL | D32: 5 | E32: ASISTENCIAL | F32: SECRETARIO | G32: 440 | H32: 11 | I32: =G32&"-"&H32 -> 440-11 | J32: DIRECCIÓN DISTRITAL DE DOCTRINA Y ASUNTOS NORMATIVOS | K32: PROVISIONAL | L32: =C32=P32 -> TRUE | M32: =J32=AH32 -> FALSE | N32: 157 | O32: 52033959 | P32: HERNÁNDEZ NAVARRO MARIBEL | Q32: PROVISIONALIDAD | R32: EN PROVISIONALIDAD | S32: 42585 | T32: 41201 | U32: MUJER | V32: 50 | X32: VACANTE DEFINITIVA | AB32: OCUPADO | AC32: ASISTENCIAL | AD32: SECRETARIO | AE32: 440 | AF32: 11 | AG32: 440-11 | AH32: DIRECCIÓN DISTRITAL DE DOCTRINA JURÍDICA | AI32: =AG32=I32 -> TRUE | AK32: DIRECCIÓN DE GESTIÓN CORPORATIVA | AL32: =J32=AK32 -> FALSE
A33: 160 | B33: 39773518 | C33: VANEGAS LARGO MARIA CRISTINA | D33: 5 | E33: ASISTENCIAL | F33: SECRETARIO | G33: 440 | H33: 9 | I33: =G33&"-"&H33 -> 440-9 | J33: OFICINA DE CONTROL INTERNO | K33: CARRERA ADMINISTRATIVA | L33: =C33=P33 -> TRUE | M33: =J33=AH33 -> TRUE | N33: 153 | O33: 39773518 | P33: VANEGAS LARGO MARIA CRISTINA | Q33: CARRERA ADMINISTRATIVA | R33: CARRERA ADMINISTRATIVA | S33: 42585 | T33: 33703 | U33: MUJER | V33: 56 | AB33: OCUPADO | AC33: ASISTENCIAL | AD33: SECRETARIO | AE33: 440 | AF33: 9 | AG33: 440-9 | AH33: OFICINA DE CONTROL INTERNO | AI33: =AG33=I33 -> TRUE | AK33: DIRECCIÓN DE GESTIÓN CORPORATIVA | AL33: =J33=AK33 -> FALSE
A34: 161 | B34: 1032434263 | C34: SIERRA LENIS LAURA STHEPANY | D34: 5 | E34: ASISTENCIAL | F34: SECRETARIO | G34: 440 | H34: 9 | I34: =G34&"-"&H34 -> 440-9 | J34: OFICINA ASESORA DE PLANEACIÓN | K34: PROVISIONAL | L34: =C34=P34 -> TRUE | M34: =J34=AH34 -> TRUE | N34: 154 | O34: 1032434263 | P34: SIERRA LENIS LAURA STHEPANY | Q34: PROVISIONALIDAD | R34: EN PROVISIONALIDAD | S34: 42585 | T34: 42131 | U34: MUJER | V34: 33 | X34: VACANTE DEFINITIVA | AB34: OCUPADO | AC34: ASISTENCIAL | AD34: SECRETARIO | AE34: 440 | AF34: 9 | AG34: 440-9 | AH34: OFICINA ASESORA DE PLANEACIÓN | AI34: =AG34=I34 -> TRUE | AK34: DIRECCIÓN DE GESTIÓN CORPORATIVA | AL34: =J34=AK34 -> FALSE
A35: 162 | B35: 80247325 | C35: AVILA GOMEZ NESTOR DANIEL | D35: 5 | E35: ASISTENCIAL | F35: SECRETARIO | G35: 440 | H35: 9 | I35: =G35&"-"&H35 -> 440-9 | J35: DIRECCIÓN DE GESTIÓN CORPORATIVA | K35: PROVISIONAL | L35: =C35=P35 -> TRUE | M35: =J35=AH35 -> FALSE | N35: 160 | O35: 80247325 | P35: AVILA GOMEZ NESTOR DANIEL | Q35: PROVISIONALIDAD | R35: EN PROVISIONALIDAD | S35: 42585 | T35: 42128 | U35: HOMBRE | V35: 38 | X35: VACANTE DEFINITIVA | AB35: OCUPADO | AC35: ASISTENCIAL | AD35: SECRETARIO | AE35: 440 | AF35: 9 | AG35: 440-9 | AH35: DIRECCIÓN CORPORATIVA | AI35: =AG35=I35 -> TRUE | AK35: OFICINA ASESORA DE PLANEACIÓN | AL35: =J35=AK35 -> FALSE
A36: 163 | B36: 51784842 | C36: MARTINEZ HERNANDEZ MARIA MERY | D36: 5 | E36: ASISTENCIAL | F36: SECRETARIO | G36: 440 | H36: 9 | I36: =G36&"-"&H36 -> 440-9 | J36: DIRECCIÓN DISTRITAL DE POLÍTICA JURÍDICA | K36: CARRERA ADMINISTRATIVA | L36: =C36=P36 -> TRUE | M36: =J36=AH36 -> FALSE | N36: 161 | O36: 51784842 | P36: MARTINEZ HERNANDEZ MARIA MERY | Q36: CARRERA ADMINISTRATIVA | R36: CARRERA ADMINISTRATIVA | S36: 42585 | T36: 33702 | U36: MUJER | V36: 58 | AB36: OCUPADO | AC36: ASISTENCIAL | AD36: SECRETARIO | AE36: 440 | AF36: 9 | AG36: 440-9 | AH36: DIRECCIÓN DISTRITAL DE POLÍTICA E INFORMÁTICA JURÍDICA | AI36: =AG36=I36 -> TRUE | AK36: OFICINA DE CONTROL INTERNO | AL36: =J36=AK36 -> FALSE
A37: 164 | B37: 52146196 | C37: RODGERS QUIROGA KATHERYN YOLANDA | D37: 5 | E37: ASISTENCIAL | F37: SECRETARIO EJECUTIVO | G37: 425 | H37: 27 | I37: =G37&"-"&H37 -> 425-27 | J37: DIRECCIÓN DISTRITAL DE GESTION JUDICIAL | K37: CARRERA ADMINISTRATIVA | L37: =C37=P37 -> TRUE | M37: =J37=AH37 -> FALSE | N37: 162 | O37: 52146196 | P37: RODGERS QUIROGA KATHERYN YOLANDA | Q37: CARRERA ADMINISTRATIVA | R37: CARRERA ADMINISTRATIVA | S37: 42585 | T37: 38443 | U37: MUJER | V37: 49 | AB37: OCUPADO | AC37: ASISTENCIAL | AD37: SECRETARIO EJECUTIVO | AE37: 425 | AF37: 27 | AG37: 425-27 | AH37: DIRECCIÓN DISTRITAL DE DEFENSA JUDICIAL Y PREVENCIÓN DEL DAÑO ANTIJURÍDICO | AI37: =AG37=I37 -> TRUE | AK37: DIRECCIÓN DE GESTIÓN CORPORATIVA | AL37: =J37=AK37 -> FALSE
A38: 165 | C38: VACANTE DEFINITIVA | D38: 5 | E38: ASISTENCIAL | F38: SECRETARIO EJECUTIVO | G38: 425 | H38: 24 | I38: =G38&"-"&H38 -> 425-24 | J38: OFICINA DE LAS TECNOLOGÍAS DE LA INFORMACIÓN Y LAS COMUNICACIONES | L38: =C38=P38 -> TRUE | M38: =J38=AH38 -> FALSE | N38: 163 | P38: VACANTE DEFINITIVA | R38: VACANTE DEFINITIVA | X38: VACANTE DEFINITIVA | AB38: VACANTE DEFINITIVA | AC38: ASISTENCIAL | AD38: SECRETARIO EJECUTIVO | AE38: 425 | AF38: 24 | AG38: 425-24 | AH38: OFICINA DE TECNOLOGÍA DE LA INFORMACIÓN, SISTEMAS Y COMUNICACIONES | AI38: =AG38=I38 -> TRUE | AK38: DIRECCIÓN DISTRITAL DE DOCTRINA Y ASUNTOS NORMATIVOS | AL38: =J38=AK38 -> FALSE
A39: 166 | B39: 51731780 | C39: RABIA SIERRA AYDA CONSTANZA | D39: 5 | E39: ASISTENCIAL | F39: SECRETARIO EJECUTIVO | G39: 425 | H39: 21 | I39: =G39&"-"&H39 -> 425-21 | J39: DIRECCIÓN DISTRITAL DE ASUNTOS DISCIPLINARIOS | K39: CARRERA ADMINISTRATIVA | L39: =C39=P39 -> TRUE | M39: =J39=AH39 -> TRUE | N39: 155 | O39: 51731780 | P39: RABIA SIERRA AYDA CONSTANZA | Q39: CARRERA ADMINISTRATIVA | R39: CARRERA ADMINISTRATIVA | S39: 42585 | T39: 38443 | U39: MUJER | V39: 58 | AB39: OCUPADO | AC39: ASISTENCIAL | AD39: SECRETARIO EJECUTIVO | AE39: 425 | AF39: 21 | AG39: 425-21 | AH39: DIRECCIÓN DISTRITAL DE ASUNTOS DISCIPLINARIOS | AI39: =AG39=I39 -> TRUE | AK39: DIRECCIÓN DISTRITAL DE INSPECCIÓN, VIGILANCIA Y CONTROL | AL39: =J39=AK39 -> FALSE
A40: 167 | B40: 20737393 | C40: MONTILLA SERRANO FABIOLA | D40: 5 | E40: ASISTENCIAL | F40: SECRETARIO EJECUTIVO | G40: 425 | H40: 20 | I40: =G40&"-"&H40 -> 425-20 | J40: DIRECCIÓN DISTRITAL DE GESTION JUDICIAL | K40: CARRERA ADMINISTRATIVA | L40: =C40=P40 -> TRUE | M40: =J40=AH40 -> FALSE | N40: 164 | O40: 20737393 | P40: MONTILLA SERRANO FABIOLA | Q40: CARRERA ADMINISTRATIVA | R40: CARRERA ADMINISTRATIVA | S40: 42585 | T40: 32237 | U40: MUJER | V40: 59 | AB40: OCUPADO | AC40: ASISTENCIAL | AD40: SECRETARIO EJECUTIVO | AE40: 425 | AF40: 20 | AG40: 425-20 | AH40: DIRECCIÓN DISTRITAL DE DEFENSA JUDICIAL Y PREVENCIÓN DEL DAÑO ANTIJURÍDICO | AI40: =AG40=I40 -> TRUE | AK40: DIRECCIÓN DE GESTIÓN CORPORATIVA | AL40: =J40=AK40 -> FALSE
A41: 168 | B41: 39718778 | C41: REVELO QUINTERO SONIA DEL ROSARIO | D41: 5 | E41: ASISTENCIAL | F41: SERVICIOS GENERALES | G41: 470 | H41: 7 | I41: =G41&"-"&H41 -> 470-7 | J41: DIRECCIÓN DE GESTIÓN CORPORATIVA | K41: CARRERA ADMINISTRATIVA | L41: =C41=P41 -> TRUE | M41: =J41=AH41 -> FALSE | N41: 169 | O41: 39718778 | P41: REVELO QUINTERO SONIA DEL ROSARIO | Q41: CARRERA ADMINISTRATIVA | R41: CARRERA ADMINISTRATIVA | S41: 42585 | T41: 34810 | U41: MUJER | V41: 56 | AB41: OCUPADO | AC41: ASISTENCIAL | AD41: SERVICIOS GENERALES | AE41: 470 | AF41: 7 | AG41: 470-7 | AH41: DIRECCIÓN CORPORATIVA | AI41: =AG41=I41 -> TRUE | AK41: DIRECCIÓN DE GESTIÓN CORPORATIVA | AL41: =J41=AK41 -> TRUE
A42: 169 | B42: 41732503 | C42: VELASQUEZ CABRERA GABRIELINA | D42: 5 | E42: ASISTENCIAL | F42: SERVICIOS GENERALES | G42: 470 | H42: 7 | I42: =G42&"-"&H42 -> 470-7 | J42: DIRECCIÓN DE GESTIÓN CORPORATIVA | K42: CARRERA ADMINISTRATIVA | L42: =C42=P42 -> TRUE | M42: =J42=AH42 -> FALSE | N42: 27 | O42: 41732503 | P42: VELASQUEZ CABRERA GABRIELINA | Q42: CARRERA ADMINISTRATIVA | R42: CARRERA ADMINISTRATIVA | S42: 42585 | T42: 34731 | U42: MUJER | V42: 63 | AB42: OCUPADO | AC42: ASISTENCIAL | AD42: SERVICIOS GENERALES | AE42: 470 | AF42: 7 | AG42: 470-7 | AH42: DIRECCIÓN CORPORATIVA | AI42: =AG42=I42 -> TRUE | AK42: DIRECCIÓN DE GESTIÓN CORPORATIVA | AL42: =J42=AK42 -> TRUE
A43: 170 | B43: 52124597 | C43: MONTAÑA MORA BETTY ESPERANZA | D43: 5 | E43: ASISTENCIAL | F43: SERVICIOS GENERALES | G43: 470 | H43: 3 | I43: =G43&"-"&H43 -> 470-3 | J43: DIRECCIÓN DE GESTIÓN CORPORATIVA | K43: CARRERA ADMINISTRATIVA | L43: =C43=P43 -> TRUE | M43: =J43=AH43 -> FALSE | N43: 170 | O43: 52124597 | P43: MONTAÑA MORA BETTY ESPERANZA | Q43: CARRERA ADMINISTRATIVA | R43: CARRERA ADMINISTRATIVA | S43: 42585 | T43: 35403 | U43: MUJER | V43: 47 | AB43: OCUPADO | AC43: ASISTENCIAL | AD43: SERVICIOS GENERALES | AE43: 470 | AF43: 3 | AG43: 470-3 | AH43: DIRECCIÓN CORPORATIVA | AI43: =AG43=I43 -> TRUE | AK43: DIRECCIÓN DE GESTIÓN CORPORATIVA | AL43: =J43=AK43 -> TRUE
A44: 8 | B44: 51740995 | C44: HERNANDEZ CORZO DALILA ASTRID | D44: 1 | E44: DIRECTIVO | F44: SECRETARIA JURIDICA | G44: 20 | H44: 9 | I44: =G44&"-"&H44 -> 20-9 | J44: DESPACHO SECRETARÍA JURÍDICA | K44: LIBRE NOMBRAMIENTO | L44: =C44=P44 -> TRUE | M44: =J44=AH44 -> FALSE | N44: 1 | O44: 51740995 | P44: HERNANDEZ CORZO DALILA ASTRID | Q44: LIBRE NOMBRAMIENTO Y REMOCIÓN | R44: NOMBRAMIENTO ORDINARIO | S44: 42585 | T44: 42394 | U44: MUJER | V44: 57 | AB44: OCUPADO | AC44: DIRECTIVO | AD44: SECRETARIA JURIDICA | AE44: 20 | AF44: 9 | AG44: =AE44&"-"&AF44 -> 20-9 | AH44: DESPACHO | AI44: =AG44=I44 -> TRUE | AK44: DESPACHO SECRETARÍA JURÍDICA | AL44: =J44=AK44 -> TRUE
A45: 9 | B45: 79543049 | C45: BURGOS DURANGO WILLIAM ANTONIO | D45: 1 | E45: DIRECTIVO | F45: SUBSECRETARIO | G45: 45 | H45: 8 | I45: =G45&"-"&H45 -> 45-8 | J45: SUBSECRETARÍA JURÍDICA DISTRITAL | K45: LIBRE NOMBRAMIENTO | L45: =C45=P45 -> TRUE | M45: =J45=AH45 -> FALSE | N45: 2 | O45: 79543049 | P45: BURGOS DURANGO WILLIAM ANTONIO | Q45: LIBRE NOMBRAMIENTO Y REMOCIÓN | R45: NOMBRAMIENTO ORDINARIO | S45: 42585 | T45: 42403 | U45: HOMBRE | V45: 51 | AB45: OCUPADO | AC45: DIRECTIVO | AD45: SUBSECRETARIO | AE45: 45 | AF45: 8 | AG45: =AE45&"-"&AF45 -> 45-8 | AH45: SUBSECRETARÍA JURÍDICA | AI45: =AG45=I45 -> TRUE | AK45: SUBSECRETARÍA JURÍDICA DISTRITAL | AL45: =J45=AK45 -> TRUE
A46: 1 | C46: VACANTE DEFINITIVA | D46: 1 | E46: DIRECTIVO | F46: DIRECTOR TÉCNICO | G46: 9 | H46: 7 | I46: =G46&"-"&H46 -> 9-7 | J46: DIRECCIÓN DE GESTIÓN CORPORATIVA | L46: =C46=P46 -> FALSE | M46: =J46=AH46 -> FALSE | N46: 8 | O46: 39546837 | P46: VÁSQUEZ ROJAS ETHEL | Q46: LIBRE NOMBRAMIENTO Y REMOCIÓN | R46: NOMBRAMIENTO ORDINARIO | S46: 42621 | T46: 42622 | U46: MUJER | V46: 53 | X46: VACANTE DEFINITIVA | AB46: OCUPADO | AC46: DIRECTIVO | AD46: DIRECTOR TÉCNICO | AE46: 9 | AF46: 7 | AG46: =AE46&"-"&AF46 -> 9-7 | AH46: DIRECCIÓN CORPORATIVA | AI46: =AG46=I46 -> TRUE | AK46: DIRECCIÓN DE GESTIÓN CORPORATIVA | AL46: =J46=AK46 -> TRUE
A47: 2 | C47: VACANTE DEFINITIVA | D47: 1 | E47: DIRECTIVO | F47: DIRECTOR TÉCNICO | G47: 9 | H47: 7 | I47: =G47&"-"&H47 -> 9-7 | J47: DIRECCIÓN DISTRITAL DE ASUNTOS DISCIPLINARIOS | K47: LIBRE NOMBRAMIENTO | L47: =C47=P47 -> FALSE | M47: =J47=AH47 -> TRUE | N47: 5 | O47: 52394165 | P47: TOBÓN DÍAZ ALEJANDRA | Q47: LIBRE NOMBRAMIENTO Y REMOCIÓN | R47: EN ENCARGO | S47: 42585 | T47: 42404 | U47: MUJER | V47: 43 | W47: ENCARGO | X47: VACANTE DEFINITIVA | Y47: E02 | Z47: 1 | AB47: OCUPADO | AC47: DIRECTIVO | AD47: DIRECTOR TÉCNICO | AE47: 9 | AF47: 7 | AG47: =AE47&"-"&AF47 -> 9-7 | AH47: DIRECCIÓN DISTRITAL DE ASUNTOS DISCIPLINARIOS | AI47: =AG47=I47 -> TRUE | AK47: DIRECCIÓN DISTRITAL DE ASUNTOS DISCIPLINARIOS | AL47: =J47=AK47 -> TRUE
A48: 3 | B48: 28915546 | C48: RODRIGUEZ QUIMBAYO LUZ ELENA | D48: 1 | E48: DIRECTIVO | F48: DIRECTOR TÉCNICO | G48: 9 | H48: 7 | I48: =G48&"-"&H48 -> 9-7 | J48: DIRECCIÓN DISTRITAL DE GESTION JUDICIAL | K48: LIBRE NOMBRAMIENTO | L48: =C48=P48 -> TRUE | M48: =J48=AH48 -> FALSE | N48: 7 | O48: 28915546 | P48: RODRIGUEZ QUIMBAYO LUZ ELENA | Q48: LIBRE NOMBRAMIENTO Y REMOCIÓN | R48: NOMBRAMIENTO ORDINARIO | S48: 42585 | T48: 42493 | U48: MUJER | V48: 52 | AB48: OCUPADO | AC48: DIRECTIVO | AD48: DIRECTOR TÉCNICO | AE48: 9 | AF48: 7 | AG48: =AE48&"-"&AF48 -> 9-7 | AH48: DIRECCIÓN DISTRITAL DE DEFENSA JUDICIAL Y PREVENCIÓN DEL DAÑO ANTIJURÍDICO | AI48: =AG48=I48 -> TRUE | AK48: DIRECCIÓN DISTRITAL DE GESTION JUDICIAL | AL48: =J48=AK48 -> TRUE
A49: 4 | C49: VACANTE DEFINITIVA | D49: 1 | E49: DIRECTIVO | F49: DIRECTOR TÉCNICO | G49: 9 | H49: 7 | I49: =G49&"-"&H49 -> 9-7 | J49: DIRECCIÓN DISTRITAL DE DOCTRINA Y ASUNTOS NORMATIVOS | L49: =C49=P49 -> FALSE | M49: =J49=AH49 -> FALSE | N49: 6 | O49: 51743499 | P49: ANA LUCY CASTRO CASTRO | Q49: LIBRE NOMBRAMIENTO Y REMOCIÓN | R49: NOMBRAMIENTO ORDINARIO | S49: 42607 | T49: 42461 | U49: MUJER | V49: 58 | AB49: OCUPADO | AC49: DIRECTIVO | AD49: DIRECTOR TÉCNICO | AE49: 9 | AF49: 7 | AG49: =AE49&"-"&AF49 -> 9-7 | AH49: DIRECCIÓN DISTRITAL DE DOCTRINA JURÍDICA | AI49: =AG49=I49 -> TRUE | AK49: DIRECCIÓN DISTRITAL DE DOCTRINA Y ASUNTOS NORMATIVOS | AL49: =J49=AK49 -> TRUE
A50: 5 | B50: 35521959 | C50: MARTÍNEZ SIERRA GLORIA EDITH | D50: 1 | E50: DIRECTIVO | F50: DIRECTOR TÉCNICO | G50: 9 | H50: 7 | I50: =G50&"-"&H50 -> 9-7 | J50: DIRECCIÓN DISTRITAL DE POLÍTICA JURÍDICA | K50: LIBRE NOMBRAMIENTO | L50: =C50=P50 -> TRUE | M50: =J50=AH50 -> FALSE | N50: 3 | O50: 35521959 | P50: MARTÍNEZ SIERRA GLORIA EDITH | Q50: LIBRE NOMBRAMIENTO Y REMOCIÓN | R50: NOMBRAMIENTO ORDINARIO | S50: 42585 | T50: 42461 | U50: MUJER | V50: 53 | AB50: OCUPADO | AC50: DIRECTIVO | AD50: DIRECTOR TÉCNICO | AE50: 9 | AF50: 7 | AG50: =AE50&"-"&AF50 -> 9-7 | AH50: DIRECCIÓN DISTRITAL DE POLÍTICA E INFORMÁTICA JURÍDICA | AI50: =AG50=I50 -> TRUE | AK50: DIRECCIÓN DISTRITAL DE POLÍTICA JURÍDICA | AL50: =J50=AK50 -> TRUE
A51: 6 | B51: 39742375 | C51: ROBAYO ALFONSO ANDREA | D51: 1 | E51: DIRECTIVO | F51: DIRECTOR TÉCNICO | G51: 9 | H51: 7 | I51: =G51&"-"&H51 -> 9-7 | J51: DIRECCIÓN DISTRITAL DE INSPECCIÓN, VIGILANCIA Y CONTROL | K51: LIBRE NOMBRAMIENTO | L51: =C51=P51 -> TRUE | M51: =J51=AH51 -> FALSE | N51: 4 | O51: 39742375 | P51: ROBAYO ALFONSO ANDREA | Q51: LIBRE NOMBRAMIENTO Y REMOCIÓN | R51: NOMBRAMIENTO ORDINARIO | S51: 42585 | T51: 42523 | U51: MUJER | V51: 45 | AB51: OCUPADO | AC51: DIRECTIVO | AD51: DIRECTOR TÉCNICO | AE51: 9 | AF51: 7 | AG51: =AE51&"-"&AF51 -> 9-7 | AH51: DIRECCIÓN DISTRITAL DE INSPECCIÓN VIGILANCIA Y CONTROL DE LAS ENTIDADES SIN ÁNIMO DE LUCRO | AI51: =AG51=I51 -> TRUE | AK51: DIRECCIÓN DISTRITAL DE INSPECCIÓN, VIGILANCIA Y CONTROL | AL51: =J51=AK51 -> TRUE
A52: 7 | C52: VACANTE DEFINITIVA | D52: 1 | E52: DIRECTIVO | F52: JEFE DE OFICINA | G52: 6 | H52: 6 | I52: =G52&"-"&H52 -> 6-6 | J52: OFICINA DE CONTROL INTERNO | L52: =C52=P52 -> TRUE | M52: =J52=AH52 -> TRUE | N52: 10 | P52: VACANTE DEFINITIVA | R52: VACANTE DEFINITIVA | X52: VACANTE DEFINITIVA | AB52: VACANTE DEFINITIVA | AC52: DIRECTIVO | AD52: JEFE DE OFICINA | AE52: 6 | AF52: 6 | AG52: =AE52&"-"&AF52 -> 6-6 | AH52: OFICINA DE CONTROL INTERNO | AI52: =AG52=I52 -> TRUE | AK52: OFICINA DE CONTROL INTERNO | AL52: =J52=AK52 -> TRUE
A53: 17 | B53: 79299847 | C53: MONTOYA MALDONADO JESÚS MARÍA | D53: 3 | E53: PROFESIONAL | F53: PROFESIONAL ESPECIALIZADO | G53: 222 | H53: 27 | I53: =G53&"-"&H53 -> 222-27 | J53: DIRECCIÓN DE GESTIÓN CORPORATIVA | K53: CARRERA ADMINISTRATIVA | L53: =C53=P53 -> TRUE | M53: =J53=AH53 -> FALSE | N53: 17 | O53: 79299847 | P53: MONTOYA MALDONADO JESÚS MARÍA | Q53: CARRERA ADMINISTRATIVA | R53: CARRERA ADMINISTRATIVA | S53: 42585 | T53: 33724 | U53: HOMBRE | V53: 60 | AB53: OCUPADO | AC53: PROFESIONAL | AD53: PROFESIONAL ESPECIALIZADO | AE53: 222 | AF53: 27 | AG53: =AE53&"-"&AF53 -> 222-27 | AH53: DIRECCIÓN CORPORATIVA | AI53: =AG53=I53 -> TRUE | AK53: DIRECCIÓN DE GESTIÓN CORPORATIVA | AL53: =J53=AK53 -> TRUE
A54: 18 | C54: VACANTE DEFINITIVA | D54: 3 | E54: PROFESIONAL | F54: PROFESIONAL ESPECIALIZADO | G54: 222 | H54: 27 | I54: =G54&"-"&H54 -> 222-27 | J54: DIRECCIÓN DE GESTIÓN CORPORATIVA | L54: =C54=P54 -> TRUE | M54: =J54=AH54 -> FALSE | N54: 18 | P54: VACANTE DEFINITIVA | R54: VACANTE DEFINITIVA | X54: VACANTE DEFINITIVA | AB54: VACANTE DEFINITIVA | AC54: PROFESIONAL | AD54: PROFESIONAL ESPECIALIZADO | AE54: 222 | AF54: 27 | AG54: =AE54&"-"&AF54 -> 222-27 | AH54: DIRECCIÓN CORPORATIVA | AI54: =AG54=I54 -> TRUE | AK54: DIRECCIÓN DE GESTIÓN CORPORATIVA | AL54: =J54=AK54 -> TRUE
A55: 19 | B55: 52236487 | C55: MORENO GUERRERO DEYSI YANIRA | D55: 3 | E55: PROFESIONAL | F55: PROFESIONAL ESPECIALIZADO | G55: 222 | H55: 27 | I55: =G55&"-"&H55 -> 222-27 | J55: DIRECCIÓN DISTRITAL DE ASUNTOS DISCIPLINARIOS | K55: CARRERA ADMINISTRATIVA | L55: =C55=P55 -> TRUE | M55: =J55=AH55 -> TRUE | N55: 28 | O55: 52236487 | P55: MORENO GUERRERO DEYSI YANIRA | Q55: CARRERA ADMINISTRATIVA | R55: CARRERA ADMINISTRATIVA | S55: 42585 | T55: 38093 | U55: MUJER | V55: 44 | AB55: OCUPADO | AC55: PROFESIONAL | AD55: PROFESIONAL ESPECIALIZADO | AE55: 222 | AF55: 27 | AG55: =AE55&"-"&AF55 -> 222-27 | AH55: DIRECCIÓN DISTRITAL DE ASUNTOS DISCIPLINARIOS | AI55: =AG55=I55 -> TRUE | AK55: DIRECCIÓN DISTRITAL DE ASUNTOS DISCIPLINARIOS | AL55: =J55=AK55 -> TRUE
A56: 20 | C56: VACANTE DEFINITIVA | D56: 3 | E56: PROFESIONAL | F56: PROFESIONAL ESPECIALIZADO | G56: 222 | H56: 27 | I56: =G56&"-"&H56 -> 222-27 | J56: SUBSECRETARÍA JURÍDICA DISTRITAL | L56: =C56=P56 -> TRUE | M56: =J56=AH56 -> FALSE | N56: 29 | P56: VACANTE DEFINITIVA | R56: VACANTE DEFINITIVA | X56: VACANTE DEFINITIVA | AB56: VACANTE DEFINITIVA | AC56: PROFESIONAL | AD56: PROFESIONAL ESPECIALIZADO | AE56: 222 | AF56: 27 | AG56: =AE56&"-"&AF56 -> 222-27 | AH56: SUBSECRETARÍA JURÍDICA | AI56: =AG56=I56 -> TRUE | AK56: SUBSECRETARÍA JURÍDICA DISTRITAL | AL56: =J56=AK56 -> TRUE
A57: 21 | C57: VACANTE DEFINITIVA | D57: 3 | E57: PROFESIONAL | F57: PROFESIONAL ESPECIALIZADO | G57: 222 | H57: 27 | I57: =G57&"-"&H57 -> 222-27 | J57: SUBSECRETARÍA JURÍDICA DISTRITAL | L57: =C57=P57 -> TRUE | M57: =J57=AH57 -> FALSE | N57: 30 | P57: VACANTE DEFINITIVA | R57: VACANTE DEFINITIVA | X57: VACANTE DEFINITIVA | AB57: VACANTE DEFINITIVA | AC57: PROFESIONAL | AD57: PROFESIONAL ESPECIALIZADO | AE57: 222 | AF57: 27 | AG57: =AE57&"-"&AF57 -> 222-27 | AH57: SUBSECRETARÍA JURÍDICA | AI57: =AG57=I57 -> TRUE | AK57: SUBSECRETARÍA JURÍDICA DISTRITAL | AL57: =J57=AK57 -> TRUE
A58: 22 | C58: VACANTE DEFINITIVA | D58: 3 | E58: PROFESIONAL | F58: PROFESIONAL ESPECIALIZADO | G58: 222 | H58: 27 | I58: =G58&"-"&H58 -> 222-27 | J58: SUBSECRETARÍA JURÍDICA DISTRITAL | L58: =C58=P58 -> TRUE | M58: =J58=AH58 -> FALSE | N58: 31 | P58: VACANTE DEFINITIVA | R58: VACANTE DEFINITIVA | X58: VACANTE DEFINITIVA | AB58: VACANTE DEFINITIVA | AC58: PROFESIONAL | AD58: PROFESIONAL ESPECIALIZADO | AE58: 222 | AF58: 27 | AG58: =AE58&"-"&AF58 -> 222-27 | AH58: SUBSECRETARÍA JURÍDICA | AI58: =AG58=I58 -> TRUE | AK58: SUBSECRETARÍA JURÍDICA DISTRITAL | AL58: =J58=AK58 -> TRUE
A59: 23 | B59: 51798311 | C59: AMAYA SALAZAR MARTHA YOLANDA | D59: 3 | E59: PROFESIONAL | F59: PROFESIONAL ESPECIALIZADO | G59: 222 | H59: 27 | I59: =G59&"-"&H59 -> 222-27 | J59: DIRECCIÓN DISTRITAL DE GESTION JUDICIAL | K59: CARRERA ADMINISTRATIVA | L59: =C59=P59 -> TRUE | M59: =J59=AH59 -> FALSE | N59: 32 | O59: 51798311 | P59: AMAYA SALAZAR MARTHA YOLANDA | Q59: CARRERA ADMINISTRATIVA | R59: CARRERA ADMINISTRATIVA | S59: 42585 | T59: 34457 | U59: MUJER | V59: 57 | AB59: OCUPADO | AC59: PROFESIONAL | AD59: PROFESIONAL ESPECIALIZADO | AE59: 222 | AF59: 27 | AG59: =AE59&"-"&AF59 -> 222-27 | AH59: DIRECCIÓN DISTRITAL DE DEFENSA JUDICIAL Y PREVENCIÓN DEL DAÑO ANTIJURÍDICO | AI59: =AG59=I59 -> TRUE | AK59: DIRECCIÓN DISTRITAL DE GESTION JUDICIAL | AL59: =J59=AK59 -> TRUE
A60: 24 | B60: 79153811 | C60: CADENA ROJAS ERNESTO | D60: 3 | E60: PROFESIONAL | F60: PROFESIONAL ESPECIALIZADO | G60: 222 | H60: 27 | I60: =G60&"-"&H60 -> 222-27 | J60: DIRECCIÓN DISTRITAL DE GESTION JUDICIAL | K60: CARRERA ADMINISTRATIVA | L60: =C60=P60 -> TRUE | M60: =J60=AH60 -> FALSE | N60: 33 | O60: 79153811 | P60: CADENA ROJAS ERNESTO | Q60: CARRERA ADMINISTRATIVA | R60: CARRERA ADMINISTRATIVA | S60: 42585 | T60: 34256 | U60: HOMBRE | V60: 60 | AB60: OCUPADO | AC60: PROFESIONAL | AD60: PROFESIONAL ESPECIALIZADO | AE60: 222 | AF60: 27 | AG60: =AE60&"-"&AF60 -> 222-27 | AH60: DIRECCIÓN DISTRITAL DE DEFENSA JUDICIAL Y PREVENCIÓN DEL DAÑO ANTIJURÍDICO | AI60: =AG60=I60 -> TRUE | AK60: DIRECCIÓN DISTRITAL DE GESTION JUDICIAL | AL60: =J60=AK60 -> TRUE
A61: 25 | B61: 51569861 | C61: DIAGO CASASBUENAS GLORIA MAGDALENA | D61: 3 | E61: PROFESIONAL | F61: PROFESIONAL ESPECIALIZADO | G61: 222 | H61: 27 | I61: =G61&"-"&H61 -> 222-27 | J61: DIRECCIÓN DISTRITAL DE GESTION JUDICIAL | K61: CARRERA ADMINISTRATIVA | L61: =C61=P61 -> TRUE | M61: =J61=AH61 -> FALSE | N61: 34 | O61: 51569861 | P61: DIAGO CASASBUENAS GLORIA MAGDALENA | Q61: CARRERA ADMINISTRATIVA | R61: CARRERA ADMINISTRATIVA | S61: 42585 | T61: 34684 | U61: MUJER | V61: 63 | AB61: OCUPADO | AC61: PROFESIONAL | AD61: PROFESIONAL ESPECIALIZADO | AE61: 222 | AF61: 27 | AG61: =AE61&"-"&AF61 -> 222-27 | AH61: DIRECCIÓN DISTRITAL DE DEFENSA JUDICIAL Y PREVENCIÓN DEL DAÑO ANTIJURÍDICO | AI61: =AG61=I61 -> TRUE | AK61: DIRECCIÓN DISTRITAL DE GESTION JUDICIAL | AL61: =J61=AK61 -> TRUE
A62: 26 | C62: VACANTE DEFINITIVA | D62: 3 | E62: PROFESIONAL | F62: PROFESIONAL ESPECIALIZADO | G62: 222 | H62: 27 | I62: =G62&"-"&H62 -> 222-27 | J62: DIRECCIÓN DISTRITAL DE GESTION JUDICIAL | L62: =C62=P62 -> TRUE | M62: =J62=AH62 -> FALSE | N62: 39 | P62: VACANTE DEFINITIVA | R62: VACANTE DEFINITIVA | X62: VACANTE DEFINITIVA | AB62: VACANTE DEFINITIVA | AC62: PROFESIONAL | AD62: PROFESIONAL ESPECIALIZADO | AE62: 222 | AF62: 27 | AG62: =AE62&"-"&AF62 -> 222-27 | AH62: DIRECCIÓN DISTRITAL DE DEFENSA JUDICIAL Y PREVENCIÓN DEL DAÑO ANTIJURÍDICO | AI62: =AG62=I62 -> TRUE | AK62: DIRECCIÓN DE GESTIÓN CORPORATIVA | AL62: =J62=AK62 -> FALSE
A63: 27 | C63: VACANTE DEFINITIVA | D63: 3 | E63: PROFESIONAL | F63: PROFESIONAL ESPECIALIZADO | G63: 222 | H63: 27 | I63: =G63&"-"&H63 -> 222-27 | J63: DIRECCIÓN DISTRITAL DE GESTION JUDICIAL | L63: =C63=P63 -> TRUE | M63: =J63=AH63 -> FALSE | N63: 35 | P63: VACANTE DEFINITIVA | R63: VACANTE DEFINITIVA | X63: VACANTE DEFINITIVA | AB63: VACANTE DEFINITIVA | AC63: PROFESIONAL | AD63: PROFESIONAL ESPECIALIZADO | AE63: 222 | AF63: 27 | AG63: =AE63&"-"&AF63 -> 222-27 | AH63: DIRECCIÓN DISTRITAL DE DEFENSA JUDICIAL Y PREVENCIÓN DEL DAÑO ANTIJURÍDICO | AI63: =AG63=I63 -> TRUE | AK63: DIRECCIÓN DISTRITAL DE GESTION JUDICIAL | AL63: =J63=AK63 -> TRUE
A64: 28 | C64: VACANTE DEFINITIVA | D64: 3 | E64: PROFESIONAL | F64: PROFESIONAL ESPECIALIZADO | G64: 222 | H64: 27 | I64: =G64&"-"&H64 -> 222-27 | J64: DIRECCIÓN DISTRITAL DE GESTION JUDICIAL | L64: =C64=P64 -> TRUE | M64: =J64=AH64 -> FALSE | N64: 40 | P64: VACANTE DEFINITIVA | R64: VACANTE DEFINITIVA | X64: VACANTE DEFINITIVA | AB64: VACANTE DEFINITIVA | AC64: PROFESIONAL | AD64: PROFESIONAL ESPECIALIZADO | AE64: 222 | AF64: 27 | AG64: =AE64&"-"&AF64 -> 222-27 | AH64: DIRECCIÓN DISTRITAL DE DEFENSA JUDICIAL Y PREVENCIÓN DEL DAÑO ANTIJURÍDICO | AI64: =AG64=I64 -> TRUE | AK64: DIRECCIÓN DISTRITAL DE GESTION JUDICIAL | AL64: =J64=AK64 -> TRUE
A65: 29 | C65: VACANTE DEFINITIVA | D65: 3 | E65: PROFESIONAL | F65: PROFESIONAL ESPECIALIZADO | G65: 222 | H65: 27 | I65: =G65&"-"&H65 -> 222-27 | J65: DIRECCIÓN DISTRITAL DE GESTION JUDICIAL | L65: =C65=P65 -> TRUE | M65: =J65=AH65 -> FALSE | N65: 37 | P65: VACANTE DEFINITIVA | R65: VACANTE DEFINITIVA | X65: VACANTE DEFINITIVA | AB65: VACANTE DEFINITIVA | AC65: PROFESIONAL | AD65: PROFESIONAL ESPECIALIZADO | AE65: 222 | AF65: 27 | AG65: =AE65&"-"&AF65 -> 222-27 | AH65: DIRECCIÓN DISTRITAL DE DEFENSA JUDICIAL Y PREVENCIÓN DEL DAÑO ANTIJURÍDICO | AI65: =AG65=I65 -> TRUE | AK65: DIRECCIÓN DISTRITAL DE GESTION JUDICIAL | AL65: =J65=AK65 -> TRUE
A66: 30 | C66: VACANTE DEFINITIVA | D66: 3 | E66: PROFESIONAL | F66: PROFESIONAL ESPECIALIZADO | G66: 222 | H66: 27 | I66: =G66&"-"&H66 -> 222-27 | J66: DIRECCIÓN DISTRITAL DE GESTION JUDICIAL | L66: =C66=P66 -> TRUE | M66: =J66=AH66 -> FALSE | N66: 38 | P66: VACANTE DEFINITIVA | R66: VACANTE DEFINITIVA | X66: VACANTE DEFINITIVA | AB66: VACANTE DEFINITIVA | AC66: PROFESIONAL | AD66: PROFESIONAL ESPECIALIZADO | AE66: 222 | AF66: 27 | AG66: =AE66&"-"&AF66 -> 222-27 | AH66: DIRECCIÓN DISTRITAL DE DEFENSA JUDICIAL Y PREVENCIÓN DEL DAÑO ANTIJURÍDICO | AI66: =AG66=I66 -> TRUE | AK66: DIRECCIÓN DISTRITAL DE GESTION JUDICIAL | AL66: =J66=AK66 -> TRUE
A67: 31 | C67: VACANTE DEFINITIVA | D67: 3 | E67: PROFESIONAL | F67: PROFESIONAL ESPECIALIZADO | G67: 222 | H67: 27 | I67: =G67&"-"&H67 -> 222-27 | J67: DIRECCIÓN DISTRITAL DE GESTION JUDICIAL | L67: =C67=P67 -> TRUE | M67: =J67=AH67 -> FALSE | N67: 36 | P67: VACANTE DEFINITIVA | R67: VACANTE DEFINITIVA | X67: VACANTE DEFINITIVA | AB67: VACANTE DEFINITIVA | AC67: PROFESIONAL | AD67: PROFESIONAL ESPECIALIZADO | AE67: 222 | AF67: 27 | AG67: =AE67&"-"&AF67 -> 222-27 | AH67: DIRECCIÓN DISTRITAL DE DEFENSA JUDICIAL Y PREVENCIÓN DEL DAÑO ANTIJURÍDICO | AI67: =AG67=I67 -> TRUE | AK67: DIRECCIÓN DISTRITAL DE GESTION JUDICIAL | AL67: =J67=AK67 -> TRUE
A68: 32 | B68: 52363895 | C68: HERNANDEZ LIBREROS ELVIRA LILIANA | D68: 3 | E68: PROFESIONAL | F68: PROFESIONAL ESPECIALIZADO | G68: 222 | H68: 27 | I68: =G68&"-"&H68 -> 222-27 | J68: DIRECCIÓN DISTRITAL DE DOCTRINA Y ASUNTOS NORMATIVOS | K68: CARRERA ADMINISTRATIVA | L68: =C68=P68 -> TRUE | M68: =J68=AH68 -> FALSE | N68: 41 | O68: 52363895 | P68: HERNANDEZ LIBREROS ELVIRA LILIANA | Q68: CARRERA ADMINISTRATIVA | R68: CARRERA ADMINISTRATIVA | S68: 42585 | T68: 37994 | U68: MUJER | V68: 46 | AB68: OCUPADO | AC68: PROFESIONAL | AD68: PROFESIONAL ESPECIALIZADO | AE68: 222 | AF68: 27 | AG68: =AE68&"-"&AF68 -> 222-27 | AH68: DIRECCIÓN DISTRITAL DE DOCTRINA JURÍDICA | AI68: =AG68=I68 -> TRUE | AK68: DIRECCIÓN DISTRITAL DE POLÍTICA JURÍDICA | AL68: =J68=AK68 -> FALSE
A69: 33 | B69: 52009661 | C69: TIBAMOSCA VILLAMARÍN SANDRA YANETH | D69: 3 | E69: PROFESIONAL | F69: PROFESIONAL ESPECIALIZADO | G69: 222 | H69: 27 | I69: =G69&"-"&H69 -> 222-27 | J69: DIRECCIÓN DISTRITAL DE DOCTRINA Y ASUNTOS NORMATIVOS | K69: CARRERA ADMINISTRATIVA | L69: =C69=P69 -> TRUE | M69: =J69=AH69 -> FALSE | N69: 42 | O69: 52009661 | P69: TIBAMOSCA VILLAMARÍN SANDRA YANETH | Q69: CARRERA ADMINISTRATIVA | R69: EN COMISIÓN EN EMPLEO DE L.N.R. O DE PERIODO | S69: 42585 | T69: 35387 | U69: MUJER | V69: 50 | W69: COMISIÒN | AA69: CM | AB69: OCUPADO | AC69: PROFESIONAL | AD69: PROFESIONAL ESPECIALIZADO | AE69: 222 | AF69: 27 | AG69: =AE69&"-"&AF69 -> 222-27 | AH69: DIRECCIÓN DISTRITAL DE DOCTRINA JURÍDICA | AI69: =AG69=I69 -> TRUE | AK69: DIRECCIÓN DISTRITAL DE DOCTRINA Y ASUNTOS NORMATIVOS | AL69: =J69=AK69 -> TRUE
A70: 34 | C70: VACANTE DEFINITIVA | D70: 3 | E70: PROFESIONAL | F70: PROFESIONAL ESPECIALIZADO | G70: 222 | H70: 27 | I70: =G70&"-"&H70 -> 222-27 | J70: DIRECCIÓN DISTRITAL DE DOCTRINA Y ASUNTOS NORMATIVOS | L70: =C70=P70 -> TRUE | M70: =J70=AH70 -> FALSE | N70: 43 | P70: VACANTE DEFINITIVA | R70: VACANTE DEFINITIVA | X70: VACANTE DEFINITIVA | AB70: VACANTE DEFINITIVA | AC70: PROFESIONAL | AD70: PROFESIONAL ESPECIALIZADO | AE70: 222 | AF70: 27 | AG70: =AE70&"-"&AF70 -> 222-27 | AH70: DIRECCIÓN DISTRITAL DE DOCTRINA JURÍDICA | AI70: =AG70=I70 -> TRUE | AK70: DIRECCIÓN DISTRITAL DE DOCTRINA Y ASUNTOS NORMATIVOS | AL70: =J70=AK70 -> TRUE
A71: 35 | B71: 24179106 | C71: ROJAS SUÁREZ ZULMA | D71: 3 | E71: PROFESIONAL | F71: PROFESIONAL ESPECIALIZADO | G71: 222 | H71: 27 | I71: =G71&"-"&H71 -> 222-27 | J71: DIRECCIÓN DISTRITAL DE POLÍTICA JURÍDICA | K71: CARRERA ADMINISTRATIVA | L71: =C71=P71 -> TRUE | M71: =J71=AH71 -> FALSE | N71: 44 | O71: 24179106 | P71: ROJAS SUÁREZ ZULMA | Q71: CARRERA ADMINISTRATIVA | R71: CARRERA ADMINISTRATIVA | S71: 42585 | T71: 38316 | U71: MUJER | V71: 45 | AB71: OCUPADO | AC71: PROFESIONAL | AD71: PROFESIONAL ESPECIALIZADO | AE71: 222 | AF71: 27 | AG71: =AE71&"-"&AF71 -> 222-27 | AH71: DIRECCIÓN DISTRITAL DE POLÍTICA E INFORMÁTICA JURÍDICA | AI71: =AG71=I71 -> TRUE | AK71: DIRECCIÓN DISTRITAL DE POLÍTICA JURÍDICA | AL71: =J71=AK71 -> TRUE
A72: 36 | C72: VACANTE DEFINITIVA | D72: 3 | E72: PROFESIONAL | F72: PROFESIONAL ESPECIALIZADO | G72: 222 | H72: 27 | I72: =G72&"-"&H72 -> 222-27 | J72: DIRECCIÓN DISTRITAL DE POLÍTICA JURÍDICA | L72: =C72=P72 -> TRUE | M72: =J72=AH72 -> FALSE | N72: 45 | P72: VACANTE DEFINITIVA | R72: VACANTE DEFINITIVA | X72: VACANTE DEFINITIVA | AB72: VACANTE DEFINITIVA | AC72: PROFESIONAL | AD72: PROFESIONAL ESPECIALIZADO | AE72: 222 | AF72: 27 | AG72: =AE72&"-"&AF72 -> 222-27 | AH72: DIRECCIÓN DISTRITAL DE POLÍTICA E INFORMÁTICA JURÍDICA | AI72: =AG72=I72 -> TRUE | AK72: DIRECCIÓN DISTRITAL DE POLÍTICA JURÍDICA | AL72: =J72=AK72 -> TRUE
A73: 37 | B73: 19347862 | C73: HERNANDEZ ALBARRACÍN JORGE ELIÉCER | D73: 3 | E73: PROFESIONAL | F73: PROFESIONAL ESPECIALIZADO | G73: 222 | H73: 27 | I73: =G73&"-"&H73 -> 222-27 | J73: DIRECCIÓN DISTRITAL DE INSPECCIÓN, VIGILANCIA Y CONTROL | K73: CARRERA ADMINISTRATIVA | L73: =C73=P73 -> TRUE | M73: =J73=AH73 -> FALSE | N73: 46 | O73: 19347862 | P73: HERNANDEZ ALBARRACÍN JORGE ELIÉCER | Q73: CARRERA ADMINISTRATIVA | R73: CARRERA ADMINISTRATIVA | S73: 42585 | T73: 34464 | U73: HOMBRE | V73: 65 | AB73: OCUPADO | AC73: PROFESIONAL | AD73: PROFESIONAL ESPECIALIZADO | AE73: 222 | AF73: 27 | AG73: =AE73&"-"&AF73 -> 222-27 | AH73: DIRECCIÓN DISTRITAL DE INSPECCIÓN VIGILANCIA Y CONTROL DE LAS ENTIDADES SIN ÁNIMO DE LUCRO | AI73: =AG73=I73 -> TRUE | AK73: DIRECCIÓN DISTRITAL DE INSPECCIÓN, VIGILANCIA Y CONTROL | AL73: =J73=AK73 -> TRUE
A74: 38 | C74: VACANTE DEFINITIVA | D74: 3 | E74: PROFESIONAL | F74: PROFESIONAL ESPECIALIZADO | G74: 222 | H74: 27 | I74: =G74&"-"&H74 -> 222-27 | J74: DIRECCIÓN DISTRITAL DE INSPECCIÓN, VIGILANCIA Y CONTROL | L74: =C74=P74 -> TRUE | M74: =J74=AH74 -> FALSE | N74: 47 | P74: VACANTE DEFINITIVA | R74: VACANTE DEFINITIVA | X74: VACANTE DEFINITIVA | AB74: VACANTE DEFINITIVA | AC74: PROFESIONAL | AD74: PROFESIONAL ESPECIALIZADO | AE74: 222 | AF74: 27 | AG74: =AE74&"-"&AF74 -> 222-27 | AH74: DIRECCIÓN DISTRITAL DE INSPECCIÓN VIGILANCIA Y CONTROL DE LAS ENTIDADES SIN ÁNIMO DE LUCRO | AI74: =AG74=I74 -> TRUE | AK74: DIRECCIÓN DISTRITAL DE INSPECCIÓN, VIGILANCIA Y CONTROL | AL74: =J74=AK74 -> TRUE
A75: 39 | C75: VACANTE DEFINITIVA | D75: 3 | E75: PROFESIONAL | F75: PROFESIONAL ESPECIALIZADO | G75: 222 | H75: 27 | I75: =G75&"-"&H75 -> 222-27 | J75: DIRECCIÓN DISTRITAL DE INSPECCIÓN, VIGILANCIA Y CONTROL | L75: =C75=P75 -> TRUE | M75: =J75=AH75 -> FALSE | N75: 49 | P75: VACANTE DEFINITIVA | R75: VACANTE DEFINITIVA | X75: VACANTE DEFINITIVA | AB75: VACANTE DEFINITIVA | AC75: PROFESIONAL | AD75: PROFESIONAL ESPECIALIZADO | AE75: 222 | AF75: 27 | AG75: =AE75&"-"&AF75 -> 222-27 | AH75: DIRECCIÓN DISTRITAL DE INSPECCIÓN VIGILANCIA Y CONTROL DE LAS ENTIDADES SIN ÁNIMO DE LUCRO | AI75: =AG75=I75 -> TRUE | AK75: DIRECCIÓN DISTRITAL DE INSPECCIÓN, VIGILANCIA Y CONTROL | AL75: =J75=AK75 -> TRUE
A76: 40 | C76: VACANTE DEFINITIVA | D76: 3 | E76: PROFESIONAL | F76: PROFESIONAL ESPECIALIZADO | G76: 222 | H76: 27 | I76: =G76&"-"&H76 -> 222-27 | J76: DIRECCIÓN DISTRITAL DE INSPECCIÓN, VIGILANCIA Y CONTROL | L76: =C76=P76 -> TRUE | M76: =J76=AH76 -> FALSE | N76: 48 | P76: VACANTE DEFINITIVA | R76: VACANTE DEFINITIVA | X76: VACANTE DEFINITIVA | AB76: VACANTE DEFINITIVA | AC76: PROFESIONAL | AD76: PROFESIONAL ESPECIALIZADO | AE76: 222 | AF76: 27 | AG76: =AE76&"-"&AF76 -> 222-27 | AH76: DIRECCIÓN DISTRITAL DE INSPECCIÓN VIGILANCIA Y CONTROL DE LAS ENTIDADES SIN ÁNIMO DE LUCRO | AI76: =AG76=I76 -> TRUE | AK76: DIRECCIÓN DISTRITAL DE INSPECCIÓN, VIGILANCIA Y CONTROL | AL76: =J76=AK76 -> TRUE
A77: 41 | B77: 28891891 | C77: MESA VASQUEZ GLORIA ASTRID | D77: 3 | E77: PROFESIONAL | F77: PROFESIONAL ESPECIALIZADO | G77: 222 | H77: 26 | I77: =G77&"-"&H77 -> 222-26 | J77: DIRECCIÓN DISTRITAL DE GESTION JUDICIAL | K77: CARRERA ADMINISTRATIVA | L77: =C77=P77 -> TRUE | M77: =J77=AH77 -> FALSE | N77: 50 | O77: 28891891 | P77: MESA VASQUEZ GLORIA ASTRID | Q77: CARRERA ADMINISTRATIVA | R77: CARRERA ADMINISTRATIVA | S77: 42585 | T77: 33171 | U77: MUJER | V77: 64 | AB77: OCUPADO | AC77: PROFESIONAL | AD77: PROFESIONAL ESPECIALIZADO | AE77: 222 | AF77: 26 | AG77: =AE77&"-"&AF77 -> 222-26 | AH77: DIRECCIÓN DISTRITAL DE DEFENSA JUDICIAL Y PREVENCIÓN DEL DAÑO ANTIJURÍDICO | AI77: =AG77=I77 -> TRUE | AK77: DIRECCIÓN DISTRITAL DE GESTION JUDICIAL | AL77: =J77=AK77 -> TRUE
A78: 42 | B78: 6761621 | C78: PARRA LEGUIZAMON JORGE ERNESTO | D78: 3 | E78: PROFESIONAL | F78: PROFESIONAL ESPECIALIZADO | G78: 222 | H78: 26 | I78: =G78&"-"&H78 -> 222-26 | J78: DIRECCIÓN DISTRITAL DE INSPECCIÓN, VIGILANCIA Y CONTROL | K78: CARRERA ADMINISTRATIVA | L78: =C78=P78 -> TRUE | M78: =J78=AH78 -> FALSE | N78: 51 | O78: 6761621 | P78: PARRA LEGUIZAMON JORGE ERNESTO | Q78: CARRERA ADMINISTRATIVA | R78: CARRERA ADMINISTRATIVA | S78: 42585 | T78: 33730 | U78: HOMBRE | V78: 63 | AB78: OCUPADO | AC78: PROFESIONAL | AD78: PROFESIONAL ESPECIALIZADO | AE78: 222 | AF78: 26 | AG78: =AE78&"-"&AF78 -> 222-26 | AH78: DIRECCIÓN DISTRITAL DE INSPECCIÓN VIGILANCIA Y CONTROL DE LAS ENTIDADES SIN ÁNIMO DE LUCRO | AI78: =AG78=I78 -> TRUE | AK78: DIRECCIÓN DE GESTIÓN CORPORATIVA | AL78: =J78=AK78 -> FALSE
A79: 43 | C79: VACANTE DEFINITIVA | D79: 3 | E79: PROFESIONAL | F79: PROFESIONAL ESPECIALIZADO | G79: 222 | H79: 25 | I79: =G79&"-"&H79 -> 222-25 | J79: DIRECCIÓN DISTRITAL DE INSPECCIÓN, VIGILANCIA Y CONTROL | L79: =C79=P79 -> TRUE | M79: =J79=AH79 -> FALSE | N79: 52 | P79: VACANTE DEFINITIVA | R79: VACANTE DEFINITIVA | X79: VACANTE DEFINITIVA | AB79: VACANTE DEFINITIVA | AC79: PROFESIONAL | AD79: PROFESIONAL ESPECIALIZADO | AE79: 222 | AF79: 25 | AG79: =AE79&"-"&AF79 -> 222-25 | AH79: DIRECCIÓN DISTRITAL DE INSPECCIÓN VIGILANCIA Y CONTROL DE LAS ENTIDADES SIN ÁNIMO DE LUCRO | AI79: =AG79=I79 -> TRUE | AK79: DIRECCIÓN DISTRITAL DE INSPECCIÓN, VIGILANCIA Y CONTROL | AL79: =J79=AK79 -> TRUE
A80: 44 | C80: VACANTE DEFINITIVA | D80: 3 | E80: PROFESIONAL | F80: PROFESIONAL ESPECIALIZADO | G80: 222 | H80: 24 | I80: =G80&"-"&H80 -> 222-24 | J80: OFICINA DE LAS TECNOLOGÍAS DE LA INFORMACIÓN Y LAS COMUNICACIONES | L80: =C80=P80 -> TRUE | M80: =J80=AH80 -> FALSE | N80: 54 | P80: VACANTE DEFINITIVA | R80: VACANTE DEFINITIVA | X80: VACANTE DEFINITIVA | AB80: VACANTE DEFINITIVA | AC80: PROFESIONAL | AD80: PROFESIONAL ESPECIALIZADO | AE80: 222 | AF80: 24 | AG80: =AE80&"-"&AF80 -> 222-24 | AH80: OFICINA DE TECNOLOGÍA DE LA INFORMACIÓN, SISTEMAS Y COMUNICACIONES | AI80: =AG80=I80 -> TRUE | AK80: OFICINA DE LAS TECNOLOGÍAS DE LA INFORMACIÓN Y LAS COMUNICACIONES | AL80: =J80=AK80 -> TRUE
A81: 45 | B81: 79349710 | C81: OVALLE CUERVO EDGAR ENRIQUE | D81: 3 | E81: PROFESIONAL | F81: PROFESIONAL ESPECIALIZADO | G81: 222 | H81: 24 | I81: =G81&"-"&H81 -> 222-24 | J81: OFICINA DE LAS TECNOLOGÍAS DE LA INFORMACIÓN Y LAS COMUNICACIONES | K81: CARRERA ADMINISTRATIVA | L81: =C81=P81 -> TRUE | M81: =J81=AH81 -> FALSE | N81: 53 | O81: 79349710 | P81: OVALLE CUERVO EDGAR ENRIQUE | Q81: CARRERA ADMINISTRATIVA | R81: CARRERA ADMINISTRATIVA | S81: 42585 | T81: 35786 | U81: HOMBRE | V81: 57 | AB81: OCUPADO | AC81: PROFESIONAL | AD81: PROFESIONAL ESPECIALIZADO | AE81: 222 | AF81: 24 | AG81: =AE81&"-"&AF81 -> 222-24 | AH81: OFICINA DE TECNOLOGÍA DE LA INFORMACIÓN, SISTEMAS Y COMUNICACIONES | AI81: =AG81=I81 -> TRUE | AK81: OFICINA DE LAS TECNOLOGÍAS DE LA INFORMACIÓN Y LAS COMUNICACIONES | AL81: =J81=AK81 -> TRUE
A82: 46 | B82: 28963444 | C82: SALCEDO TAMAYO GLORIA ESTHER | D82: 3 | E82: PROFESIONAL | F82: PROFESIONAL ESPECIALIZADO | G82: 222 | H82: 24 | I82: =G82&"-"&H82 -> 222-24 | J82: DIRECCIÓN DE GESTIÓN CORPORATIVA | K82: CARRERA ADMINISTRATIVA | L82: =C82=P82 -> TRUE | M82: =J82=AH82 -> FALSE | N82: 21 | O82: 28963444 | P82: SALCEDO TAMAYO GLORIA ESTHER | Q82: CARRERA ADMINISTRATIVA | R82: CARRERA ADMINISTRATIVA | S82: 42585 | T82: 34257 | U82: MUJER | V82: 58 | AB82: OCUPADO | AC82: PROFESIONAL | AD82: PROFESIONAL ESPECIALIZADO | AE82: 222 | AF82: 24 | AG82: =AE82&"-"&AF82 -> 222-24 | AH82: DIRECCIÓN CORPORATIVA | AI82: =AG82=I82 -> TRUE | AK82: DIRECCIÓN DE GESTIÓN CORPORATIVA | AL82: =J82=AK82 -> TRUE
A83: 47 | B83: 42497241 | C83: APONTE PENSO SILVIA MODESTA | D83: 3 | E83: PROFESIONAL | F83: PROFESIONAL ESPECIALIZADO | G83: 222 | H83: 24 | I83: =G83&"-"&H83 -> 222-24 | J83: DIRECCIÓN DISTRITAL DE DOCTRINA Y ASUNTOS NORMATIVOS | K83: CARRERA ADMINISTRATIVA | L83: =C83=P83 -> TRUE | M83: =J83=AH83 -> FALSE | N83: 55 | O83: 42497241 | P83: APONTE PENSO SILVIA MODESTA | Q83: CARRERA ADMINISTRATIVA | R83: CARRERA ADMINISTRATIVA | S83: 42585 | T83: 34687 | U83: MUJER | V83: 63 | AB83: OCUPADO | AC83: PROFESIONAL | AD83: PROFESIONAL ESPECIALIZADO | AE83: 222 | AF83: 24 | AG83: =AE83&"-"&AF83 -> 222-24 | AH83: DIRECCIÓN DISTRITAL DE DOCTRINA JURÍDICA | AI83: =AG83=I83 -> TRUE | AK83: DIRECCIÓN DISTRITAL DE DOCTRINA Y ASUNTOS NORMATIVOS | AL83: =J83=AK83 -> TRUE
A84: 48 | C84: VACANTE DEFINITIVA | D84: 3 | E84: PROFESIONAL | F84: PROFESIONAL ESPECIALIZADO | G84: 222 | H84: 24 | I84: =G84&"-"&H84 -> 222-24 | J84: DIRECCIÓN DISTRITAL DE DOCTRINA Y ASUNTOS NORMATIVOS | L84: =C84=P84 -> TRUE | M84: =J84=AH84 -> FALSE | N84: 57 | P84: VACANTE DEFINITIVA | R84: VACANTE DEFINITIVA | X84: VACANTE DEFINITIVA | AB84: VACANTE DEFINITIVA | AC84: PROFESIONAL | AD84: PROFESIONAL ESPECIALIZADO | AE84: 222 | AF84: 24 | AG84: =AE84&"-"&AF84 -> 222-24 | AH84: DIRECCIÓN DISTRITAL DE DOCTRINA JURÍDICA | AI84: =AG84=I84 -> TRUE | AK84: DIRECCIÓN DISTRITAL DE DOCTRINA Y ASUNTOS NORMATIVOS | AL84: =J84=AK84 -> TRUE
A85: 49 | C85: VACANTE DEFINITIVA | D85: 3 | E85: PROFESIONAL | F85: PROFESIONAL ESPECIALIZADO | G85: 222 | H85: 24 | I85: =G85&"-"&H85 -> 222-24 | J85: DIRECCIÓN DISTRITAL DE DOCTRINA Y ASUNTOS NORMATIVOS | L85: =C85=P85 -> TRUE | M85: =J85=AH85 -> FALSE | N85: 58 | P85: VACANTE DEFINITIVA | R85: VACANTE DEFINITIVA | X85: VACANTE DEFINITIVA | AB85: VACANTE DEFINITIVA | AC85: PROFESIONAL | AD85: PROFESIONAL ESPECIALIZADO | AE85: 222 | AF85: 24 | AG85: =AE85&"-"&AF85 -> 222-24 | AH85: DIRECCIÓN DISTRITAL DE DOCTRINA JURÍDICA | AI85: =AG85=I85 -> TRUE | AK85: DIRECCIÓN DISTRITAL DE DOCTRINA Y ASUNTOS NORMATIVOS | AL85: =J85=AK85 -> TRUE
A86: 50 | C86: VACANTE DEFINITIVA | D86: 3 | E86: PROFESIONAL | F86: PROFESIONAL ESPECIALIZADO | G86: 222 | H86: 24 | I86: =G86&"-"&H86 -> 222-24 | J86: DIRECCIÓN DISTRITAL DE DOCTRINA Y ASUNTOS NORMATIVOS | L86: =C86=P86 -> TRUE | M86: =J86=AH86 -> FALSE | N86: 59 | P86: VACANTE DEFINITIVA | R86: VACANTE DEFINITIVA | X86: VACANTE DEFINITIVA | AB86: VACANTE DEFINITIVA | AC86: PROFESIONAL | AD86: PROFESIONAL ESPECIALIZADO | AE86: 222 | AF86: 24 | AG86: =AE86&"-"&AF86 -> 222-24 | AH86: DIRECCIÓN DISTRITAL DE DOCTRINA JURÍDICA | AI86: =AG86=I86 -> TRUE | AK86: DIRECCIÓN DISTRITAL DE DOCTRINA Y ASUNTOS NORMATIVOS | AL86: =J86=AK86 -> TRUE
A87: 51 | C87: VACANTE DEFINITIVA | D87: 3 | E87: PROFESIONAL | F87: PROFESIONAL ESPECIALIZADO | G87: 222 | H87: 24 | I87: =G87&"-"&H87 -> 222-24 | J87: DIRECCIÓN DISTRITAL DE INSPECCIÓN, VIGILANCIA Y CONTROL | L87: =C87=P87 -> TRUE | M87: =J87=AH87 -> FALSE | N87: 56 | P87: VACANTE DEFINITIVA | R87: VACANTE DEFINITIVA | X87: VACANTE DEFINITIVA | AB87: VACANTE DEFINITIVA | AC87: PROFESIONAL | AD87: PROFESIONAL ESPECIALIZADO | AE87: 222 | AF87: 24 | AG87: =AE87&"-"&AF87 -> 222-24 | AH87: DIRECCIÓN DISTRITAL DE INSPECCIÓN VIGILANCIA Y CONTROL DE LAS ENTIDADES SIN ÁNIMO DE LUCRO | AI87: =AG87=I87 -> TRUE | AK87: OFICINA DE CONTROL INTERNO | AL87: =J87=AK87 -> FALSE
A88: 52 | B88: 35312719 | C88: GIRALDO MONTOYA MARTHA ALICIA | D88: 3 | E88: PROFESIONAL | F88: PROFESIONAL ESPECIALIZADO | G88: 222 | H88: 24 | I88: =G88&"-"&H88 -> 222-24 | J88: DIRECCIÓN DISTRITAL DE INSPECCIÓN, VIGILANCIA Y CONTROL | K88: CARRERA ADMINISTRATIVA | L88: =C88=P88 -> TRUE | M88: =J88=AH88 -> FALSE | N88: 60 | O88: 35312719 | P88: GIRALDO MONTOYA MARTHA ALICIA | Q88: CARRERA ADMINISTRATIVA | R88: CARRERA ADMINISTRATIVA | S88: 42585 | T88: 34250 | U88: MUJER | V88: 65 | AB88: OCUPADO | AC88: PROFESIONAL | AD88: PROFESIONAL ESPECIALIZADO | AE88: 222 | AF88: 24 | AG88: =AE88&"-"&AF88 -> 222-24 | AH88: DIRECCIÓN DISTRITAL DE INSPECCIÓN VIGILANCIA Y CONTROL DE LAS ENTIDADES SIN ÁNIMO DE LUCRO | AI88: =AG88=I88 -> TRUE | AK88: DIRECCIÓN DISTRITAL DE INSPECCIÓN, VIGILANCIA Y CONTROL | AL88: =J88=AK88 -> TRUE
A89: 53 | C89: VACANTE DEFINITIVA | D89: 3 | E89: PROFESIONAL | F89: PROFESIONAL ESPECIALIZADO | G89: 222 | H89: 22 | I89: =G89&"-"&H89 -> 222-22 | J89: DIRECCIÓN DISTRITAL DE POLÍTICA JURÍDICA | L89: =C89=P89 -> TRUE | M89: =J89=AH89 -> FALSE | N89: 61 | P89: VACANTE DEFINITIVA | R89: VACANTE DEFINITIVA | X89: VACANTE DEFINITIVA | AB89: VACANTE DEFINITIVA | AC89: PROFESIONAL | AD89: PROFESIONAL ESPECIALIZADO | AE89: 222 | AF89: 22 | AG89: =AE89&"-"&AF89 -> 222-22 | AH89: DIRECCIÓN DISTRITAL DE POLÍTICA E INFORMÁTICA JURÍDICA | AI89: =AG89=I89 -> TRUE | AK89: DIRECCIÓN DISTRITAL DE POLÍTICA JURÍDICA | AL89: =J89=AK89 -> TRUE
A90: 54 | B90: 79569642 | C90: SALAZAR URRUTIA NELSON JULIAN | D90: 3 | E90: PROFESIONAL | F90: PROFESIONAL ESPECIALIZADO | G90: 222 | H90: 21 | I90: =G90&"-"&H90 -> 222-21 | J90: OFICINA ASESORA DE PLANEACIÓN | K90: CARRERA ADMINISTRATIVA | L90: =C90=P90 -> TRUE | M90: =J90=AH90 -> TRUE | N90: 62 | O90: 79569642 | P90: SALAZAR URRUTIA NELSON JULIAN | Q90: CARRERA ADMINISTRATIVA | R90: CARRERA ADMINISTRATIVA | S90: 42585 | T90: 36271 | U90: HOMBRE | V90: 50 | AB90: OCUPADO | AC90: PROFESIONAL | AD90: PROFESIONAL ESPECIALIZADO | AE90: 222 | AF90: 21 | AG90: =AE90&"-"&AF90 -> 222-21 | AH90: OFICINA ASESORA DE PLANEACIÓN | AI90: =AG90=I90 -> TRUE | AK90: OFICINA ASESORA DE PLANEACIÓN | AL90: =J90=AK90 -> TRUE
A91: 55 | B91: 51748267 | C91: CASTELLANOS RODRÍGUEZ MARTHA LIGIA | D91: 3 | E91: PROFESIONAL | F91: PROFESIONAL ESPECIALIZADO | G91: 222 | H91: 21 | I91: =G91&"-"&H91 -> 222-21 | J91: DIRECCIÓN DE GESTIÓN CORPORATIVA | K91: PROVISIONAL | L91: =C91=P91 -> TRUE | M91: =J91=AH91 -> FALSE | N91: 22 | O91: 51748267 | P91: CASTELLANOS RODRÍGUEZ MARTHA LIGIA | Q91: PROVISIONALIDAD | R91: EN PROVISIONALIDAD | S91: 42585 | T91: 40426 | U91: MUJER | V91: 59 | X91: VACANTE DEFINITIVA | AB91: OCUPADO | AC91: PROFESIONAL | AD91: PROFESIONAL ESPECIALIZADO | AE91: 222 | AF91: 21 | AG91: =AE91&"-"&AF91 -> 222-21 | AH91: DIRECCIÓN CORPORATIVA | AI91: =AG91=I91 -> TRUE | AK91: DIRECCIÓN DE GESTIÓN CORPORATIVA | AL91: =J91=AK91 -> TRUE
A92: 56 | B92: 51649014 | C92: GUTIERREZ HERNANDEZ DORA BELEN | D92: 3 | E92: PROFESIONAL | F92: PROFESIONAL ESPECIALIZADO | G92: 222 | H92: 21 | I92: =G92&"-"&H92 -> 222-21 | J92: DIRECCIÓN DE GESTIÓN CORPORATIVA | K92: CARRERA ADMINISTRATIVA | L92: =C92=P92 -> TRUE | M92: =J92=AH92 -> FALSE | N92: 23 | O92: 51649014 | P92: GUTIERREZ HERNANDEZ DORA BELEN | Q92: CARRERA ADMINISTRATIVA | R92: CARRERA ADMINISTRATIVA | S92: 42585 | T92: 34870 | U92: MUJER | V92: 60 | AB92: OCUPADO | AC92: PROFESIONAL | AD92: PROFESIONAL ESPECIALIZADO | AE92: 222 | AF92: 21 | AG92: =AE92&"-"&AF92 -> 222-21 | AH92: DIRECCIÓN CORPORATIVA | AI92: =AG92=I92 -> TRUE | AK92: DIRECCIÓN DE GESTIÓN CORPORATIVA | AL92: =J92=AK92 -> TRUE
A93: 57 | B93: 52352995 | C93: SALAS SANCHEZ VANESSA | D93: 3 | E93: PROFESIONAL | F93: PROFESIONAL ESPECIALIZADO | G93: 222 | H93: 21 | I93: =G93&"-"&H93 -> 222-21 | J93: DIRECCIÓN DE GESTIÓN CORPORATIVA | K93: PROVISIONAL | L93: =C93=P93 -> TRUE | M93: =J93=AH93 -> FALSE | N93: 19 | O93: 52352995 | P93: SALAS SANCHEZ VANESSA | Q93: PROVISIONALIDAD | R93: EN PROVISIONALIDAD | S93: 42585 | T93: 42051 | U93: MUJER | V93: 43 | X93: VACANTE DEFINITIVA | AB93: OCUPADO | AC93: PROFESIONAL | AD93: PROFESIONAL ESPECIALIZADO | AE93: 222 | AF93: 21 | AG93: =AE93&"-"&AF93 -> 222-21 | AH93: DIRECCIÓN CORPORATIVA | AI93: =AG93=I93 -> TRUE | AK93: DIRECCIÓN DE GESTIÓN CORPORATIVA | AL93: =J93=AK93 -> TRUE
A94: 58 | C94: VACANTE DEFINITIVA | D94: 3 | E94: PROFESIONAL | F94: PROFESIONAL ESPECIALIZADO | G94: 222 | H94: 21 | I94: =G94&"-"&H94 -> 222-21 | J94: DIRECCIÓN DE GESTIÓN CORPORATIVA | L94: =C94=P94 -> TRUE | M94: =J94=AH94 -> FALSE | N94: 20 | P94: VACANTE DEFINITIVA | R94: VACANTE DEFINITIVA | X94: VACANTE DEFINITIVA | AB94: VACANTE DEFINITIVA | AC94: PROFESIONAL | AD94: PROFESIONAL ESPECIALIZADO | AE94: 222 | AF94: 21 | AG94: =AE94&"-"&AF94 -> 222-21 | AH94: DIRECCIÓN CORPORATIVA | AI94: =AG94=I94 -> TRUE | AK94: DIRECCIÓN DE GESTIÓN CORPORATIVA | AL94: =J94=AK94 -> TRUE
A95: 59 | B95: 3085860 | C95: CASTIBLANCO URQUIJO LUIS ALFONSO | D95: 3 | E95: PROFESIONAL | F95: PROFESIONAL ESPECIALIZADO | G95: 222 | H95: 21 | I95: =G95&"-"&H95 -> 222-21 | J95: DIRECCIÓN DISTRITAL DE GESTION JUDICIAL | K95: CARRERA ADMINISTRATIVA | L95: =C95=P95 -> TRUE | M95: =J95=AH95 -> FALSE | N95: 63 | O95: 3085860 | P95: CASTIBLANCO URQUIJO LUIS ALFONSO | Q95: CARRERA ADMINISTRATIVA | R95: CARRERA ADMINISTRATIVA | S95: 42585 | T95: 38443 | U95: HOMBRE | V95: 54 | AB95: OCUPADO | AC95: PROFESIONAL | AD95: PROFESIONAL ESPECIALIZADO | AE95: 222 | AF95: 21 | AG95: =AE95&"-"&AF95 -> 222-21 | AH95: DIRECCIÓN DISTRITAL DE DEFENSA JUDICIAL Y PREVENCIÓN DEL DAÑO ANTIJURÍDICO | AI95: =AG95=I95 -> TRUE | AK95: DIRECCIÓN DISTRITAL DE GESTION JUDICIAL | AL95: =J95=AK95 -> TRUE
A96: 60 | C96: VACANTE DEFINITIVA | D96: 3 | E96: PROFESIONAL | F96: PROFESIONAL ESPECIALIZADO | G96: 222 | H96: 21 | I96: =G96&"-"&H96 -> 222-21 | J96: DIRECCIÓN DISTRITAL DE DOCTRINA Y ASUNTOS NORMATIVOS | L96: =C96=P96 -> TRUE | M96: =J96=AH96 -> FALSE | N96: 64 | P96: VACANTE DEFINITIVA | R96: VACANTE DEFINITIVA | X96: VACANTE DEFINITIVA | AB96: VACANTE DEFINITIVA | AC96: PROFESIONAL | AD96: PROFESIONAL ESPECIALIZADO | AE96: 222 | AF96: 21 | AG96: =AE96&"-"&AF96 -> 222-21 | AH96: DIRECCIÓN DISTRITAL DE DOCTRINA JURÍDICA | AI96: =AG96=I96 -> TRUE | AK96: DIRECCIÓN DISTRITAL DE DOCTRINA Y ASUNTOS NORMATIVOS | AL96: =J96=AK96 -> TRUE
A97: 61 | C97: VACANTE DEFINITIVA | D97: 3 | E97: PROFESIONAL | F97: PROFESIONAL ESPECIALIZADO | G97: 222 | H97: 21 | I97: =G97&"-"&H97 -> 222-21 | J97: DIRECCIÓN DISTRITAL DE INSPECCIÓN, VIGILANCIA Y CONTROL | L97: =C97=P97 -> TRUE | M97: =J97=AH97 -> FALSE | N97: 66 | P97: VACANTE DEFINITIVA | R97: VACANTE DEFINITIVA | X97: VACANTE DEFINITIVA | AB97: VACANTE DEFINITIVA | AC97: PROFESIONAL | AD97: PROFESIONAL ESPECIALIZADO | AE97: 222 | AF97: 21 | AG97: =AE97&"-"&AF97 -> 222-21 | AH97: DIRECCIÓN DISTRITAL DE INSPECCIÓN VIGILANCIA Y CONTROL DE LAS ENTIDADES SIN ÁNIMO DE LUCRO | AI97: =AG97=I97 -> TRUE | AK97: DIRECCIÓN DISTRITAL DE INSPECCIÓN, VIGILANCIA Y CONTROL | AL97: =J97=AK97 -> TRUE
A98: 62 | C98: VACANTE DEFINITIVA | D98: 3 | E98: PROFESIONAL | F98: PROFESIONAL ESPECIALIZADO | G98: 222 | H98: 21 | I98: =G98&"-"&H98 -> 222-21 | J98: DIRECCIÓN DISTRITAL DE INSPECCIÓN, VIGILANCIA Y CONTROL | L98: =C98=P98 -> TRUE | M98: =J98=AH98 -> FALSE | N98: 65 | P98: VACANTE DEFINITIVA | R98: VACANTE DEFINITIVA | X98: VACANTE DEFINITIVA | AB98: VACANTE DEFINITIVA | AC98: PROFESIONAL | AD98: PROFESIONAL ESPECIALIZADO | AE98: 222 | AF98: 21 | AG98: =AE98&"-"&AF98 -> 222-21 | AH98: DIRECCIÓN DISTRITAL DE INSPECCIÓN VIGILANCIA Y CONTROL DE LAS ENTIDADES SIN ÁNIMO DE LUCRO | AI98: =AG98=I98 -> TRUE | AK98: DIRECCIÓN DISTRITAL DE INSPECCIÓN, VIGILANCIA Y CONTROL | AL98: =J98=AK98 -> TRUE
A99: 63 | B99: 79450267 | C99: GONZÁLEZ MOLINA HENRY ALBERTO | D99: 3 | E99: PROFESIONAL | F99: PROFESIONAL ESPECIALIZADO | G99: 222 | H99: 20 | I99: =G99&"-"&H99 -> 222-20 | J99: DIRECCIÓN DISTRITAL DE GESTION JUDICIAL | K99: CARRERA ADMINISTRATIVA | L99: =C99=P99 -> TRUE | M99: =J99=AH99 -> FALSE | N99: 68 | O99: 79450267 | P99: GONZÁLEZ MOLINA HENRY ALBERTO | Q99: CARRERA ADMINISTRATIVA | R99: CARRERA ADMINISTRATIVA | S99: 42585 | T99: 35062 | U99: HOMBRE | V99: 55 | AB99: OCUPADO | AC99: PROFESIONAL | AD99: PROFESIONAL ESPECIALIZADO | AE99: 222 | AF99: 20 | AG99: =AE99&"-"&AF99 -> 222-20 | AH99: DIRECCIÓN DISTRITAL DE DEFENSA JUDICIAL Y PREVENCIÓN DEL DAÑO ANTIJURÍDICO | AI99: =AG99=I99 -> TRUE | AK99: DIRECCIÓN DISTRITAL DE GESTION JUDICIAL | AL99: =J99=AK99 -> TRUE
A100: 64 | C100: VACANTE DEFINITIVA | D100: 3 | E100: PROFESIONAL | F100: PROFESIONAL ESPECIALIZADO | G100: 222 | H100: 20 | I100: =G100&"-"&H100 -> 222-20 | J100: DIRECCIÓN DISTRITAL DE GESTION JUDICIAL | L100: =C100=P100 -> TRUE | M100: =J100=AH100 -> FALSE | N100: 67 | P100: VACANTE DEFINITIVA | R100: VACANTE DEFINITIVA | X100: VACANTE DEFINITIVA | AB100: VACANTE DEFINITIVA | AC100: PROFESIONAL | AD100: PROFESIONAL ESPECIALIZADO | AE100: 222 | AF100: 20 | AG100: =AE100&"-"&AF100 -> 222-20 | AH100: DIRECCIÓN DISTRITAL DE DEFENSA JUDICIAL Y PREVENCIÓN DEL DAÑO ANTIJURÍDICO | AI100: =AG100=I100 -> TRUE | AK100: DIRECCIÓN DISTRITAL DE GESTION JUDICIAL | AL100: =J100=AK100 -> TRUE
...

Sheet ESCALERAS

Sheet Hoja4

Sheet PLANTA SJD
AI1: =1750905*2 -> 3501810 | AM1: TOPE | AN1: 1750905 | AO1: 2968261 | AP1: =AO1*1.07 -> 3176039.3 | AQ1: 2774076 | AR1: =AN1*2 -> 3501810
F2: =+TODAY() -> 46304 | AM2: VALOR | AN2: 249095 | AO2: 98931 | AP2: =AN1*2 -> 3501810
K3: =TODAY() -> 46304 | N3: ENCARGOS - ESCALERAS | AI3: =AI93/30 -> 218880.97
A4: ID | B4: ID SIDEAP | C4: ID PERNO | D4: CEDULA | E4: APELLIDOS Y NOMBRES | F4: TIPO DE VINCULACIÓN A LA ENTIDAD | G4: TIPO DE VINCULACIÓN AL CARGO/ SIDEAP | H4: FECHA INGRESO A LA ENTIDAD | I4: FECHA INGRESO AL DISTRITO | J4: SEXO | K4: EDAD | L4: SITUACIÓN ADMINISTRATIVA | M4: SITUACIÓN ADMINISTRATIVA TITULAR DEL CARGO | N4: CEDULA | O4: TITULAR CARGO | P4: ID-E | Q4: N | R4: PV | S4: PP OE | T4: VT LM | U4: VT LNR | V4: OPEC DIST_6 | W4: ESTADO DEL CARGO | X4: NIVEL | Y4: NOMENCLATURA_ADMIN | Z4: CÓDIGO | AA4: GRADO | AB4: U | AC4: DEPENDENCIA DEL CARGO | AD4: DEPENDENCIA FUNCIONAL | AE4: PROPOSITO | AF4: FUNCIONES | AG4: REQUISITOS | AH4: Páginas Manual de Funciones | AI4: ASIGNACIÓN BÁSICA 2026 | AJ4: GTOS REP | AK4: PRIMA DE ANTIGÜEDAD | AL4: PRIMA TECNICA | AM4: PRIMA SECRETARIAL | AN4: SUBSIDIO DE TRANSPORTE | AO4: AUXILIO DE ALIMENTACION | AP4: TOTAL DEVENGADOS MENSUAL | AQ4: Observaciones
A5: 1 | B5: 4998 | C5: 11 | D5: 80222608 | E5: =IF(D5>0,VLOOKUP(D5,'PLANTA PERNO'!A:D,4,0)&" "&VLOOKUP(D5,'PLANTA PERNO'!A:D,2,0)&" "&VLOOKUP(D5,'PLANTA PERNO'!A:D,3,0),IF(N5="","VACANTE DEFINITIVA","VACANTE TEMPORAL")) -> GERMAN ALBERTO PULIDO PULIDO | F5: LIBRE NOMBRAMIENTO Y REMOCIÓN | G5: =VLOOKUP(IF(AND($F5<>"",$L5=""),$F5,IF(AND($F5<>"",$L5<>""),$L5,$E5)),$AY$5:$AZ$16,2,0) -> NOMBRAMIENTO ORDINARIO | H5: =IFERROR(VLOOKUP($D5,PLANTA_PERNO,16,0)," ") -> 44294 | I5: =IFERROR(VLOOKUP($D5,PLANTA_PERNO,17,0),"") -> 40598 | J5: =IF(IFERROR((VLOOKUP($D5,PLANTA_PERNO,9,0)),"")="F","MUJER",IF(IFERROR((VLOOKUP($D5,PLANTA_PERNO,9,0)),"")="M","HOMBRE","")) -> HOMBRE | K5: =IFERROR(DATEDIF((VLOOKUP($D5,PLANTA_PERNO,6,0)),$K$3,"Y"),"") -> 43 | L5: =IF(AND(($Q5>=1),($E5<>"VACANTE TEMPORAL"),F5<>"PROVISIONALIDAD"),"ENCARGO",IF(F5="PROVISIONALIDAD","PROVISIONALIDAD",IF(F5="PERIODO DE PRUEBA","PERIODO DE PRUEBA",""))) | M5: =IF(O5="VACANTE DEFINITIVA","VACANTE DEFINITIVA",IF(AND(O5<>"VACANTE DEFINITVA",R5="CM"),"EN COMISIÓN EN EMPLEO DE L.N.R. O DE PERIODO",IF(AND(O5<>"VACANTE DEFINITVA",S5="PP"),"PERIODO DE PRUEBA EN OTRA ENTIDAD",IF(AND(O5<>"VACANTE DEFINITVA",T5="LM"),"VT LICENCIA MATERNIDAD",IF(AND(O5<>"VACANTE DEFINITIVA",Q5>0,U5=""),"EN ENCARGO",IF(AND(E5<>"",U5="LNR"),"LICENCIA NO REMUNERADA","EN PROPIEDAD")))))) -> VACANTE DEFINITIVA | O5: =IF(N5="","VACANTE DEFINITIVA",(VLOOKUP(N5,'PLANTA PERNO'!A:D,4,0)&" "&VLOOKUP(N5,'PLANTA PERNO'!A:D,2,0)&" "&VLOOKUP(N5,'PLANTA PERNO'!A:D,3,0))) -> VACANTE DEFINITIVA | W5: =IF(E5="VACANTE DEFINITIVA","VACANTE DEFINITIVA",IF(E5="VACANTE TEMPORAL","VACANTE TEMPORAL","OCUPADO")) -> OCUPADO | X5: ASESOR | Y5: JEFE DE OFICINA ASESORA | Z5: 115 | AA5: 6 | AB5: =Z5&"-"&AA5 -> 115-6 | AC5: OFICINA ASESORA DE PLANEACIÓN | AD5: OFICINA ASESORA DE PLANEACIÓN | AE5: Asesorar en el diseño de planes y estrategias de planeación para el cumplimiento de la misión y objetivos institucionales con criterios de eficiencia, eficacia y oportunidad. | AF5: 1. Asesorar y coordinar con las diferentes dependencias, la formulación y seguimiento de los proyectos de inversión de conformidad con los lineamientos del Plan de Desarrollo del Distrito Capital, el Plan Estratégico de la Entidad y dentro de la oportunidad requerida. 2. Dirigir la ejecución de las actividades operativas y técnicas de los proyectos de inversión de acuerdo con las instrucciones dadas por los gerentes de los proyectos, con criterios de efectividad y oportunidad. 3. Asesorar y coordinar la formulación, ejecución, seguimiento y evaluación del plan estratégico y los planes operativos para el cumplimiento de los objetivos de la entidad. 4. Coordinar la implementación, sostenibilidad y mejora continua del Sistema Integrado de Gestión de la Entidad y de los subsistemas que lo componen de acuerdo con la normatividad vigente. 5. Formular, coordinar y hacer seguimiento al anteproyecto anual de presupuesto de inversión y de funcionamiento, conjuntamente con la Dirección Corporativa, y en concordancia con el Plan estratégico y los planes de gestión de la Entidad. 6. Asesorar y coordinar con las diferentes dependencias la conformación y análisis de estadísticas de gestión, la formulación, aplicación de indicadores de gestión y de mecanismos de evaluación del cumplimiento de objetivos y metas definidos en los planes, programas y proyectos, proponiendo las recomendaciones que permitan mejorar la eficacia de la Entidad. 7. Dirigir el diseño de las metodologías para elaborar y/o actualizar los manuales de procesos y procedimientos de las dependencias de la Entidad, con criterios de efectividad. 8. Asesorar y coordinar la elaboración de los procesos y procedimientos de las dependencias de la Secretaría de manera oportuna. 9. Asesorar y proponer estrategias para el desarrollo administrativo, optimización y racionalización de trámites, y demás asuntos relacionados con la gestión de acuerdo con los principios de eficacia, eficiencia y efectividad de la gestión pública. 10. Asesorar a la Entidad en la formulación, implementación y medición de las políticas generadas en ejercicio de sus funciones. 11. Desempeñar las demás funciones que le asigne el superior inmediato de acuerdo a la naturaleza del cargo. | AG5: Titulo profesional en disciplina académica de uno de los diguintes los núcleos básicos de conocimiento - NBC-: Economía; Administración; Ciencia Política o Relaciones Internacionales; Ingeniería Industrial y afines; Ingeniería financiera y afines; Contaduría Pública. Titulo de posgrado en áreas relacionadas con la funciones del cargo. Tarjeta o matrícula profesional en los casos reglamentados por la Ley. | AH5: 34-37 RES. 085 de 2020 | AI5: =VLOOKUP(AR5,$AT$5:$AU$103,2,0) -> 10208470 | AJ5: =+AI5*0.4 -> 4083388 | AK5: =IFERROR(INT(($AI5*(VLOOKUP($D5,BASE_PORCENTAJES,10,0))/100)),0) -> 714592 | AL5: =IFERROR(INT(($AI5*(VLOOKUP($D5,'PORCENTAJES FACTORES'!B:N,12,0))/100)),0) -> 4083388 | AM5: =IFERROR(INT(($AI5*(VLOOKUP($D5,BASE_PORCENTAJES,13,0))/100)),0) -> 0 | AN5: =IF($AI5<=($AN$1*2),$AN$2,0) -> 0 | AO5: =IF($AI5<=$AO$1,$AO$2,0) -> 0 | AP5: =+AI5+AJ5+AK5+AL5+AM5+AN5+AO5 -> 19089838 | AR5: 6-ASESOR | AT5: 1-DIRECTIVO | AU5: 6802822 | AV5: =VLOOKUP(N5,D:D,1,0) -> #N/A | AW5: =VLOOKUP(D5,'PLANTA PERNO'!A:R,18,0) -> 0 | AY5: CARRERA ADMINISTRATIVA | AZ5: CARRERA ADMINISTRATIVA
A6: 2 | B6: 4999 | C6: 171 | D6: 2968815 | E6: =IF(D6>0,VLOOKUP(D6,'PLANTA PERNO'!A:D,4,0)&" "&VLOOKUP(D6,'PLANTA PERNO'!A:D,2,0)&" "&VLOOKUP(D6,'PLANTA PERNO'!A:D,3,0),IF(N6="","VACANTE DEFINITIVA","VACANTE TEMPORAL")) -> OSCAR JAVIER SUAREZ RAMOS | F6: LIBRE NOMBRAMIENTO Y REMOCIÓN | G6: =VLOOKUP(IF(AND($F6<>"",$L6=""),$F6,IF(AND($F6<>"",$L6<>""),$L6,$E6)),$AY$5:$AZ$16,2,0) -> NOMBRAMIENTO ORDINARIO | H6: =IFERROR(VLOOKUP($D6,PLANTA_PERNO,16,0)," ") -> 45923 | I6: =IFERROR(VLOOKUP($D6,PLANTA_PERNO,17,0),"") -> 45923 | J6: =IF(IFERROR((VLOOKUP($D6,PLANTA_PERNO,9,0)),"")="F","MUJER",IF(IFERROR((VLOOKUP($D6,PLANTA_PERNO,9,0)),"")="M","HOMBRE","")) -> HOMBRE | K6: =IFERROR(DATEDIF((VLOOKUP($D6,PLANTA_PERNO,6,0)),$K$3,"Y"),"") -> 48 | L6: =IF(AND(($Q6>=1),($E6<>"VACANTE TEMPORAL"),F6<>"PROVISIONALIDAD"),"ENCARGO",IF(F6="PROVISIONALIDAD","PROVISIONALIDAD",IF(F6="PERIODO DE PRUEBA","PERIODO DE PRUEBA",""))) | M6: =IF(O6="VACANTE DEFINITIVA","VACANTE DEFINITIVA",IF(AND(O6<>"VACANTE DEFINITVA",R6="CM"),"EN COMISIÓN EN EMPLEO DE L.N.R. O DE PERIODO",IF(AND(O6<>"VACANTE DEFINITVA",S6="PP"),"PERIODO DE PRUEBA EN OTRA ENTIDAD",IF(AND(O6<>"VACANTE DEFINITVA",T6="LM"),"VT LICENCIA MATERNIDAD",IF(AND(O6<>"VACANTE DEFINITIVA",Q6>0,U6=""),"EN ENCARGO",IF(AND(E6<>"",U6="LNR"),"LICENCIA NO REMUNERADA","EN PROPIEDAD")))))) -> EN PROPIEDAD | N6: 2968815 | O6: =IF(N6="","VACANTE DEFINITIVA",(VLOOKUP(N6,'PLANTA PERNO'!A:D,4,0)&" "&VLOOKUP(N6,'PLANTA PERNO'!A:D,2,0)&" "&VLOOKUP(N6,'PLANTA PERNO'!A:D,3,0))) -> OSCAR JAVIER SUAREZ RAMOS | W6: =IF(E6="VACANTE DEFINITIVA","VACANTE DEFINITIVA",IF(E6="VACANTE TEMPORAL","VACANTE TEMPORAL","OCUPADO")) -> OCUPADO | X6: DIRECTIVO | Y6: JEFE DE OFICINA | Z6: 6 | AA6: 6 | AB6: =Z6&"-"&AA6 -> 6-6 | AC6: OFICINA DE LAS TECNOLOGÍAS DE LA INFORMACIÓN Y LAS COMUNICACIONES | AD6: OFICINA DE LAS TECNOLOGÍAS DE LA INFORMACIÓN Y LAS COMUNICACIONES | AE6: Orientar a la Secretaría Jurídica Distrital en el fortalecimiento de la gerencia jurídica Distrital a través del uso e implementación de tecnologías de la información y comunicaciones con el propósito de hacer más eficiente y efectiva la defensa de los intereses jurídicos del Distrito. | AF6: 1. Liderar la gestión estratégica con tecnologías de la información y comunicaciones mediante la definición, implementación, ejecución, seguimiento y divulgación de un Plan Estratégico de Tecnología y Sistemas de Información (PETI), que esté alineado a la estrategia y al modelo integrado de gestión de la Secretaría Jurídica Distrital. 2. Dirigir el análisis para identificar las oportunidades para adoptar nuevas tendencias tecnológicas que generen impacto en el desarrollo del sector Administrativo de Gestión Jurídica del Distrito Capital, así como velar por el cumplimiento y actualización oportuna de las políticas y estándares en esta materia. 3. Definir, implementar y mantener la infraestructura tecnológica de la Secretaría Jurídica Distrital y del sector Administrativo de Gestión Jurídica del Distrito Capital. 4. Implementar los lineamientos en materia tecnológica, necesarios para definir estrategias y prácticas que habiliten la gestión de la Secretaría Jurídica Distrital y del sector Administrativo de Gestión Jurídica del Distrito Capital, en beneficio de la prestación efectiva de sus servicios. 5. Liderar los procesos de adquisición de bienes y servicios de tecnología, mediante la definición de criterios de optimización y métodos que direccionen la toma de decisiones de inversión en tecnologías de la información buscando el beneficio económico y de los servicios de la Secretaría Jurídica Distrital. 6. Coordinar la administración de las herramientas, las bases de datos, la plataforma tecnológica de información y comunicaciones de la Secretaría Jurídica Distrital; así como el desarrollo y mantenimiento de los sistemas administrativos y misionales de la Entidad para garantizar su funcionalidad y disponibilidad en su operación. 7. Dirigir y planear la implementación de las metodologías y procedimientos que adopte la Entidad para el desarrollo, instalación, administración y uso de la infraestructura tecnológica. 8. Dirigir la implementación y la prestación del soporte técnico a los portales web y redes sociales de la Secretaría Jurídica Distrital, garantizando el cumplimiento de los lineamientos del gobierno en línea. 9. Orientar la administración de los portales WEB y redes sociales de la Secretaría Jurídica Distrital, garantizando el cumplimiento de los lineamientos del gobierno en línea. 10. Dirigir y establecer los lineamientos para el diseño e implementación de un modelo de interoperatividad de sistemas y gestión de información misional, con el fin de permitir el acceso a la misma por parte de entidades y otros actores, de manera ordenada e integrada, para facilitar la toma de decisiones. 11. Dirigir la propuesta de los lineamientos técnicos del desarrollo de los contenidos y ambientes virtuales requeridos para el cumplimiento de las funciones y objetivos de la Secretaría. 12. Coordinar la implementación y actualización del Sistema de Seguridad de la Información y de activos de información de la Secretaría Jurídica Distrital para el cumplimiento de los objetivos de la Entidad y dentro de la oportunidad requerida. 13. Desempeñar las demás funciones que le asigne el superior inmediato de acuerdo a la naturaleza del cargo. | AG6: Titulo profesional en disciplina académica del núcleo básico de conocimiento -NBA- en Ingeniería de Sistemas, telemática y afines. Titulo profesional del núcleo básico del conocimiento en Ingeniería Electrónica, Telecomunicaciones y afines. Título de postgrado en áreas relacionadas con las funciones del cago. Tarjeta o matricula profesional en los casos reglamentados por la Ley. | AH6: 9-12 RES. 085 de 2020 | AI6: =VLOOKUP(AR6,$AT$5:$AU$103,2,0) -> 10208470 | AJ6: =+AI6*0.4 -> 4083388 | AK6: =IFERROR(INT(($AI6*(VLOOKUP($D6,BASE_PORCENTAJES,10,0))/100)),0) -> 0 | AL6: =IFERROR(INT(($AI6*(VLOOKUP($D6,'PORCENTAJES FACTORES'!B:N,12,0))/100)),0) -> 0 | AM6: =IFERROR(INT(($AI6*(VLOOKUP($D6,BASE_PORCENTAJES,13,0))/100)),0) -> 0 | AN6: =IF($AI6<=($AN$1*2),$AN$2,0) -> 0 | AO6: =IF($AI6<=$AO$1,$AO$2,0) -> 0 | AP6: =+AI6+AJ6+AK6+AL6+AM6+AN6+AO6 -> 14291858 | AR6: 6-DIRECTIVO | AT6: 2-DIRECTIVO | AU6: 7169759 | AV6: =VLOOKUP(N6,D:D,1,0) -> 2968815 | AW6: =VLOOKUP(D6,'PLANTA PERNO'!A:R,18,0) -> 0 | AY6: EN PERIODO DE PRUEBA EN ASCENSO | AZ6: EN PERIODO DE PRUEBA EN ASCENSO
A7: 3 | B7: 5000 | C7: 12 | D7: 64586540 | E7: =IF(D7>0,VLOOKUP(D7,'PLANTA PERNO'!A:D,4,0)&" "&VLOOKUP(D7,'PLANTA PERNO'!A:D,2,0)&" "&VLOOKUP(D7,'PLANTA PERNO'!A:D,3,0),IF(N7="","VACANTE DEFINITIVA","VACANTE TEMPORAL")) -> ALMA ROSA RAMOS MARIA | F7: CARRERA ADMINISTRATIVA | G7: =VLOOKUP(IF(AND($F7<>"",$L7=""),$F7,IF(AND($F7<>"",$L7<>""),$L7,$E7)),$AY$5:$AZ$16,2,0) -> EN ENCARGO | H7: =IFERROR(VLOOKUP($D7,PLANTA_PERNO,16,0)," ") -> 44603 | I7: =IFERROR(VLOOKUP($D7,PLANTA_PERNO,17,0),"") -> 44603 | J7: =IF(IFERROR((VLOOKUP($D7,PLANTA_PERNO,9,0)),"")="F","MUJER",IF(IFERROR((VLOOKUP($D7,PLANTA_PERNO,9,0)),"")="M","HOMBRE","")) -> MUJER | K7: =IFERROR(DATEDIF((VLOOKUP($D7,PLANTA_PERNO,6,0)),$K$3,"Y"),"") -> 46 | L7: =IF(AND(($Q7>=1),($E7<>"VACANTE TEMPORAL"),F7<>"PROVISIONALIDAD"),"ENCARGO",IF(F7="PROVISIONALIDAD","PROVISIONALIDAD",IF(F7="PERIODO DE PRUEBA","PERIODO DE PRUEBA",""))) -> ENCARGO | M7: =IF(O7="VACANTE DEFINITIVA","VACANTE DEFINITIVA",IF(AND(O7<>"VACANTE DEFINITVA",R7="CM"),"EN COMISIÓN EN EMPLEO DE L.N.R. O DE PERIODO",IF(AND(O7<>"VACANTE DEFINITVA",S7="PP"),"PERIODO DE PRUEBA EN OTRA ENTIDAD",IF(AND(O7<>"VACANTE DEFINITVA",T7="LM"),"VT LICENCIA MATERNIDAD",IF(AND(O7<>"VACANTE DEFINITIVA",Q7>0,U7=""),"EN ENCARGO",IF(AND(E7<>"",U7="LNR"),"LICENCIA NO REMUNERADA","EN PROPIEDAD")))))) -> VACANTE DEFINITIVA | O7: =IF(N7="","VACANTE DEFINITIVA",(VLOOKUP(N7,'PLANTA PERNO'!A:D,4,0)&" "&VLOOKUP(N7,'PLANTA PERNO'!A:D,2,0)&" "&VLOOKUP(N7,'PLANTA PERNO'!A:D,3,0))) -> VACANTE DEFINITIVA | P7: E04 | Q7: 1 | W7: =IF(E7="VACANTE DEFINITIVA","VACANTE DEFINITIVA",IF(E7="VACANTE TEMPORAL","VACANTE TEMPORAL","OCUPADO")) -> OCUPADO | X7: ASESOR | Y7: ASESOR | Z7: 105 | AA7: 5 | AB7: =Z7&"-"&AA7 -> 105-5 | AC7: DESPACHO SECRETARÍA JURÍDICA | AD7: DESPACHO SECRETARÍA JURÍDICA | AE7: Asesorar y apoyar al Secretario (a) Jurídico (a) en la toma de decisiones, formulación y desarrollo de políticas, estrategias, planes y programas, apoyo logístico, encaminados al logro de los objetivos de la entidad, según las áreas temáticas asignadas. | AF7: 1. Asesorar al/la secretario/a jurídico distrital en el proceso de formulación de políticas y estrategias encaminadas al logro de los objetivos institucionales, con criterios de objetividad, eficiencia y oportunidad. 2. Realizar la asistencia jurídica al Despacho del/la secretario/a jurídico/a distrital en los asuntos asignados de manera oportuna y con criterios de efectividad. 3. Asesorar en la formulación, implementación, seguimiento, evaluación y ajuste del direccionamiento estratégico de las dependencias con eficiencia y oportunidad. 4. Aportar elementos de juicio para la toma de decisiones relacionadas con la adopción, ejecución y control de los programas y actividades propias de la entidad con el fin de aportar a la construcción de los objetivos institucionales de la entidad. 5. Asesorar y participar en las investigaciones y estudios confiados por el/la secretario/a jurídico en las diferentes áreas temáticas, para garantizar la aplicación de la normatividad vigente. 6. Preparar y presentar los informes requeridos por el/la secretario/a de Despacho de conformidad con las instrucciones impartidas por el/la mismo. 7. Asesorar en la revisión y verificación de proposiciones, proyectos de acuerdo y de ley, actos legislativos, derechos de petición, solicitudes entre otros, del Concejo de Bogotá, asambleas departamentales y el Congreso de la República, con criterios de efectividad y oportunidad. 8. Asesorar al/la secretario/a jurídico/a distrital en el diseño y/o implementación de la política de comunicaciones, plan de comunicación y estrategias comunicacionales para la entidad, con calidad y oportunidad. 9. Asesorar al secretario/a jurídico/a distrital en la implementación de los programas, planes y programas relacionados con la implementación de los sistemas de información jurídica, con criterios de calidad y eficiencia en la gestión. 10. Proponer y desarrollar investigaciones y estudios relacionados con los temas propios de la Secretaría Jurídica Distrital con calidad y oportunidad. 11. Asesorar en el proceso de formulación, articulación y seguimiento de la política de gerencia jurídica pública, con el fin de garantizar la adecuada toma de decisiones y la prevención del daño antijurídico para las entidades y organismos Distritales. 12. Realizar la práctica de pruebas que le sean comisionadas y sustanciar todo aquello concerniente al proceso disciplinario de segunda instancia, de conformidad con la normativa vigente y el debido proceso. 13. Actualizar el Sistema de Información Disciplinaria de forma oportuna, veraz y confiable. 14. Desempeñar las demás funciones que le asigne el superior inmediato de acuerdo a la naturaleza del cargo. | AG7: Estudio: Título profesional en: Administración Pública, Administración de Empresas, Administración Financiera, Administración Financiera y de Sistemas, Finanzas y Relaciones Internacionales, Finanzas Internacionales o Administración de Negocios; del núcleo básico de conocimiento en Administración. Título profesional en: Economía, Comercio Exterior o Finanzas y Comercio Exterior; del núcleo básico de conocimiento en Economía. Título profesional en: Contaduría Pública; del núcleo básico de conocimiento en Contaduría Pública. Título profesional en: Derecho; Derecho y Ciencias Sociales; Derecho y Ciencias Políticas; Derecho y Ciencias Humanas; Derecho y Ciencias Administrativas; Derecho Ciencias Políticas y Relaciones Internacionales; Jurisprudencia; Justicia y Derecho; ó Leyes y Jurisprudencia; del núcleo básico de conocimiento en Derecho y afines. Título profesional en: Ingeniería Industrial o Ingeniería de Producción; del núcleo básico de conocimiento en Ingeniería Industrial. Título profesional en: Ingeniería Administrativa o Ingeniería Financiera; del núcleo básico de conocimiento en Ingeniería Financiera y afines.Título profesional en: Ingeniería de Sistemas; del núcleo básico de conocimiento en Ingeniería de Sistemas, Telemática y afines. Título profesional en: Ciencia Política o Gobierno y Relaciones Internacionales; del núcleo básico de conocimiento en Ciencia Política o Relaciones Internacionales. Título de posgrado en áreas relacionadas con las funciones del cargo. Tarjeta o matrícula profesional en los casos reg lamentados por la ley. | AH7: 15-19 RES. 074 de 2023 | AI7: =VLOOKUP(AR7,$AT$5:$AU$103,2,0) -> 9154873 | AJ7: =+AI7*0.3 -> 2746461.9 | AK7: =IFERROR(INT(($AI7*(VLOOKUP($D7,BASE_PORCENTAJES,10,0))/100)),0) -> 0 | AL7: =IFERROR(INT(($AI7*(VLOOKUP($D7,'PORCENTAJES FACTORES'!B:N,12,0))/100)),0) -> 3661949 | AM7: =IFERROR(INT(($AI7*(VLOOKUP($D7,BASE_PORCENTAJES,13,0))/100)),0) -> 0 | AN7: =IF($AI7<=($AN$1*2),$AN$2,0) -> 0 | AO7: =IF($AI7<=$AO$1,$AO$2,0) -> 0 | AP7: =+AI7+AJ7+AK7+AL7+AM7+AN7+AO7 -> 15563284 | AR7: 5-ASESOR | AT7: 3-DIRECTIVO | AU7: 7365003 | AV7: =VLOOKUP(N7,D:D,1,0) -> #N/A | AW7: =VLOOKUP(D7,'PLANTA PERNO'!A:R,18,0) -> 0 | AY7: PERÍODO DE PRUEBA | AZ7: EN PERIODO DE PRUEBA
A8: 4 | B8: 5001 | C8: 13 | D8: 1020810401 | E8: =IF(D8>0,VLOOKUP(D8,'PLANTA PERNO'!A:D,4,0)&" "&VLOOKUP(D8,'PLANTA PERNO'!A:D,2,0)&" "&VLOOKUP(D8,'PLANTA PERNO'!A:D,3,0),IF(N8="","VACANTE DEFINITIVA","VACANTE TEMPORAL")) -> MARIA PAULA ALBORNOZ CARDENAS | F8: LIBRE NOMBRAMIENTO Y REMOCIÓN | G8: =VLOOKUP(IF(AND($F8<>"",$L8=""),$F8,IF(AND($F8<>"",$L8<>""),$L8,$E8)),$AY$5:$AZ$16,2,0) -> NOMBRAMIENTO ORDINARIO | H8: =IFERROR(VLOOKUP($D8,PLANTA_PERNO,16,0)," ") -> 45880 | I8: =IFERROR(VLOOKUP($D8,PLANTA_PERNO,17,0),"") -> 45880 | J8: =IF(IFERROR((VLOOKUP($D8,PLANTA_PERNO,9,0)),"")="F","MUJER",IF(IFERROR((VLOOKUP($D8,PLANTA_PERNO,9,0)),"")="M","HOMBRE","")) -> MUJER | K8: =IFERROR(DATEDIF((VLOOKUP($D8,PLANTA_PERNO,6,0)),$K$3,"Y"),"") -> 30 | L8: =IF(AND(($Q8>=1),($E8<>"VACANTE TEMPORAL"),F8<>"PROVISIONALIDAD"),"ENCARGO",IF(F8="PROVISIONALIDAD","PROVISIONALIDAD",IF(F8="PERIODO DE PRUEBA","PERIODO DE PRUEBA",""))) | M8: =IF(O8="VACANTE DEFINITIVA","VACANTE DEFINITIVA",IF(AND(O8<>"VACANTE DEFINITVA",R8="CM"),"EN COMISIÓN EN EMPLEO DE L.N.R. O DE PERIODO",IF(AND(O8<>"VACANTE DEFINITVA",S8="PP"),"PERIODO DE PRUEBA EN OTRA ENTIDAD",IF(AND(O8<>"VACANTE DEFINITVA",T8="LM"),"VT LICENCIA MATERNIDAD",IF(AND(O8<>"VACANTE DEFINITIVA",Q8>0,U8=""),"EN ENCARGO",IF(AND(E8<>"",U8="LNR"),"LICENCIA NO REMUNERADA","EN PROPIEDAD")))))) -> EN PROPIEDAD | N8: 1020810401 | O8: =IF(N8="","VACANTE DEFINITIVA",(VLOOKUP(N8,'PLANTA PERNO'!A:D,4,0)&" "&VLOOKUP(N8,'PLANTA PERNO'!A:D,2,0)&" "&VLOOKUP(N8,'PLANTA PERNO'!A:D,3,0))) -> MARIA PAULA ALBORNOZ CARDENAS | W8: =IF(E8="VACANTE DEFINITIVA","VACANTE DEFINITIVA",IF(E8="VACANTE TEMPORAL","VACANTE TEMPORAL","OCUPADO")) -> OCUPADO | X8: ASESOR | Y8: ASESOR | Z8: 105 | AA8: 5 | AB8: =Z8&"-"&AA8 -> 105-5 | AC8: DESPACHO SECRETARÍA JURÍDICA | AD8: DESPACHO SECRETARÍA JURÍDICA | AE8: Asesorar y apoyar al Secretario (a) Jurídico (a) en la toma de decisiones, formulación y desarrollo de políticas, estrategias, planes y programas, apoyo logístico, encaminados al logro de los objetivos de la entidad, según las áreas temáticas asignadas. | AF8: 1. Asesorar al/la secretario/a jurídico distrital en el proceso de formulación de políticas y estrategias encaminadas al logro de los objetivos institucionales, con criterios de objetividad, eficiencia y oportunidad. 2. Realizar la asistencia jurídica al Despacho del/la secretario/a jurídico/a distrital en los asuntos asignados de manera oportuna y con criterios de efectividad. 3. Asesorar en la formulación, implementación, seguimiento, evaluación y ajuste del direccionamiento estratégico de las dependencias con eficiencia y oportunidad. 4. Aportar elementos de juicio para la toma de decisiones relacionadas con la adopción, ejecución y control de los programas y actividades propias de la entidad con el fin de aportar a la construcción de los objetivos institucionales de la entidad. 5. Asesorar y participar en las investigaciones y estudios confiados por el/la secretario/a jurídico en las diferentes áreas temáticas, para garantizar la aplicación de la normatividad vigente. 6. Preparar y presentar los informes requeridos por el/la secretario/a de Despacho de conformidad con las instrucciones impartidas por el/la mismo. 7. Asesorar en la revisión y verificación de proposiciones, proyectos de acuerdo y de ley, actos legislativos, derechos de petición, solicitudes entre otros, del Concejo de Bogotá, asambleas departamentales y el Congreso de la República, con criterios de efectividad y oportunidad. 8. Asesorar al/la secretario/a jurídico/a distrital en el diseño y/o implementación de la política de comunicaciones, plan de comunicación y estrategias comunicacionales para la entidad, con calidad y oportunidad. 9. Asesorar al secretario/a jurídico/a distrital en la implementación de los programas, planes y programas relacionados con la implementación de los sistemas de información jurídica, con criterios de calidad y eficiencia en la gestión. 10. Proponer y desarrollar investigaciones y estudios relacionados con los temas propios de la Secretaría Jurídica Distrital con calidad y oportunidad. 11. Asesorar en el proceso de formulación, articulación y seguimiento de la política de gerencia jurídica pública, con el fin de garantizar la adecuada toma de decisiones y la prevención del daño antijurídico para las entidades y organismos Distritales. 12. Realizar la práctica de pruebas que le sean comisionadas y sustanciar todo aquello concerniente al proceso disciplinario de segunda instancia, de conformidad con la normativa vigente y el debido proceso. 13. Actualizar el Sistema de Información Disciplinaria de forma oportuna, veraz y confiable. 14. Desempeñar las demás funciones que le asigne el superior inmediato de acuerdo a la naturaleza del cargo. | AG8: Estudio: Título profesional en: Administración Pública, Administración de Empresas, Administración Financiera, Administración Financiera y de Sistemas, Finanzas y Relaciones Internacionales, Finanzas Internacionales o Administración de Negocios; del núcleo básico de conocimiento en Administración. Título profesional en: Economía, Comercio Exterior o Finanzas y Comercio Exterior; del núcleo básico de conocimiento en Economía. Título profesional en: Contaduría Pública; del núcleo básico de conocimiento en Contaduría Pública. Título profesional en: Derecho; Derecho y Ciencias Sociales; Derecho y Ciencias Políticas; Derecho y Ciencias Humanas; Derecho y Ciencias Administrativas; Derecho Ciencias Políticas y Relaciones Internacionales; Jurisprudencia; Justicia y Derecho; ó Leyes y Jurisprudencia; del núcleo básico de conocimiento en Derecho y afines. Título profesional en: Ingeniería Industrial o Ingeniería de Producción; del núcleo básico de conocimiento en Ingeniería Industrial. Título profesional en: Ingeniería Administrativa o Ingeniería Financiera; del núcleo básico de conocimiento en Ingeniería Financiera y afines.Título profesional en: Ingeniería de Sistemas; del núcleo básico de conocimiento en Ingeniería de Sistemas, Telemática y afines. Título profesional en: Ciencia Política o Gobierno y Relaciones Internacionales; del núcleo básico de conocimiento en Ciencia Política o Relaciones Internacionales. Título de posgrado en áreas relacionadas con las funciones del cargo. Tarjeta o matrícula profesional en los casos reg lamentados por la ley. | AH8: 15-19 RES. 074 de 2023 | AI8: =VLOOKUP(AR8,$AT$5:$AU$103,2,0) -> 9154873 | AJ8: =+AI8*0.3 -> 2746461.9 | AK8: =IFERROR(INT(($AI8*(VLOOKUP($D8,BASE_PORCENTAJES,10,0))/100)),0) -> 0 | AL8: =IFERROR(INT(($AI8*(VLOOKUP($D8,'PORCENTAJES FACTORES'!B:N,12,0))/100)),0) -> 4577436 | AM8: =IFERROR(INT(($AI8*(VLOOKUP($D8,BASE_PORCENTAJES,13,0))/100)),0) -> 0 | AN8: =IF($AI8<=($AN$1*2),$AN$2,0) -> 0 | AO8: =IF($AI8<=$AO$1,$AO$2,0) -> 0 | AP8: =+AI8+AJ8+AK8+AL8+AM8+AN8+AO8 -> 16478771 | AR8: 5-ASESOR | AT8: 4-DIRECTIVO | AU8: 8295184 | AV8: =VLOOKUP(N8,D:D,1,0) -> 1020810401 | AW8: =VLOOKUP(D8,'PLANTA PERNO'!A:R,18,0) -> 0 | AY8: PERÍODO FIJO | AZ8: PERÍODO FIJO
A9: 5 | B9: 5002 | C9: 14 | D9: 1121857540 | E9: =IF(D9>0,VLOOKUP(D9,'PLANTA PERNO'!A:D,4,0)&" "&VLOOKUP(D9,'PLANTA PERNO'!A:D,2,0)&" "&VLOOKUP(D9,'PLANTA PERNO'!A:D,3,0),IF(N9="","VACANTE DEFINITIVA","VACANTE TEMPORAL")) -> MARIA TATIANA MEJIA ROJAS | F9: LIBRE NOMBRAMIENTO Y REMOCIÓN | G9: =VLOOKUP(IF(AND($F9<>"",$L9=""),$F9,IF(AND($F9<>"",$L9<>""),$L9,$E9)),$AY$5:$AZ$16,2,0) -> NOMBRAMIENTO ORDINARIO | H9: =IFERROR(VLOOKUP($D9,PLANTA_PERNO,16,0)," ") -> 45371 | I9: =IFERROR(VLOOKUP($D9,PLANTA_PERNO,17,0),"") -> 45371 | J9: =IF(IFERROR((VLOOKUP($D9,PLANTA_PERNO,9,0)),"")="F","MUJER",IF(IFERROR((VLOOKUP($D9,PLANTA_PERNO,9,0)),"")="M","HOMBRE","")) -> MUJER | K9: =IFERROR(DATEDIF((VLOOKUP($D9,PLANTA_PERNO,6,0)),$K$3,"Y"),"") -> 37 | L9: =IF(AND(($Q9>=1),($E9<>"VACANTE TEMPORAL"),F9<>"PROVISIONALIDAD"),"ENCARGO",IF(F9="PROVISIONALIDAD","PROVISIONALIDAD",IF(F9="PERIODO DE PRUEBA","PERIODO DE PRUEBA",""))) | M9: =IF(O9="VACANTE DEFINITIVA","VACANTE DEFINITIVA",IF(AND(O9<>"VACANTE DEFINITVA",R9="CM"),"EN COMISIÓN EN EMPLEO DE L.N.R. O DE PERIODO",IF(AND(O9<>"VACANTE DEFINITVA",S9="PP"),"PERIODO DE PRUEBA EN OTRA ENTIDAD",IF(AND(O9<>"VACANTE DEFINITVA",T9="LM"),"VT LICENCIA MATERNIDAD",IF(AND(O9<>"VACANTE DEFINITIVA",Q9>0,U9=""),"EN ENCARGO",IF(AND(E9<>"",U9="LNR"),"LICENCIA NO REMUNERADA","EN PROPIEDAD")))))) -> EN PROPIEDAD | N9: 1121857540 | O9: =IF(N9="","VACANTE DEFINITIVA",(VLOOKUP(N9,'PLANTA PERNO'!A:D,4,0)&" "&VLOOKUP(N9,'PLANTA PERNO'!A:D,2,0)&" "&VLOOKUP(N9,'PLANTA PERNO'!A:D,3,0))) -> MARIA TATIANA MEJIA ROJAS | W9: =IF(E9="VACANTE DEFINITIVA","VACANTE DEFINITIVA",IF(E9="VACANTE TEMPORAL","VACANTE TEMPORAL","OCUPADO")) -> OCUPADO | X9: ASESOR | Y9: ASESOR | Z9: 105 | AA9: 5 | AB9: =Z9&"-"&AA9 -> 105-5 | AC9: DESPACHO SECRETARÍA JURÍDICA | AD9: DESPACHO SECRETARÍA JURÍDICA | AE9: Asesorar y apoyar al Secretario (a) Jurídico (a) en la toma de decisiones, formulación y desarrollo de políticas, estrategias, planes y programas, apoyo logístico, encaminados al logro de los objetivos de la entidad, según las áreas temáticas asignadas. | AF9: 1. Asesorar al/la secretario/a jurídico distrital en el proceso de formulación de políticas y estrategias encaminadas al logro de los objetivos institucionales, con criterios de objetividad, eficiencia y oportunidad. 2. Realizar la asistencia jurídica al Despacho del/la secretario/a jurídico/a distrital en los asuntos asignados de manera oportuna y con criterios de efectividad. 3. Asesorar en la formulación, implementación, seguimiento, evaluación y ajuste del direccionamiento estratégico de las dependencias con eficiencia y oportunidad. 4. Aportar elementos de juicio para la toma de decisiones relacionadas con la adopción, ejecución y control de los programas y actividades propias de la entidad con el fin de aportar a la construcción de los objetivos institucionales de la entidad. 5. Asesorar y participar en las investigaciones y estudios confiados por el/la secretario/a jurídico en las diferentes áreas temáticas, para garantizar la aplicación de la normatividad vigente. 6. Preparar y presentar los informes requeridos por el/la secretario/a de Despacho de conformidad con las instrucciones impartidas por el/la mismo. 7. Asesorar en la revisión y verificación de proposiciones, proyectos de acuerdo y de ley, actos legislativos, derechos de petición, solicitudes entre otros, del Concejo de Bogotá, asambleas departamentales y el Congreso de la República, con criterios de efectividad y oportunidad. 8. Asesorar al/la secretario/a jurídico/a distrital en el diseño y/o implementación de la política de comunicaciones, plan de comunicación y estrategias comunicacionales para la entidad, con calidad y oportunidad. 9. Asesorar al secretario/a jurídico/a distrital en la implementación de los programas, planes y programas relacionados con la implementación de los sistemas de información jurídica, con criterios de calidad y eficiencia en la gestión. 10. Proponer y desarrollar investigaciones y estudios relacionados con los temas propios de la Secretaría Jurídica Distrital con calidad y oportunidad. 11. Asesorar en el proceso de formulación, articulación y seguimiento de la política de gerencia jurídica pública, con el fin de garantizar la adecuada toma de decisiones y la prevención del daño antijurídico para las entidades y organismos Distritales. 12. Realizar la práctica de pruebas que le sean comisionadas y sustanciar todo aquello concerniente al proceso disciplinario de segunda instancia, de conformidad con la normativa vigente y el debido proceso. 13. Actualizar el Sistema de Información Disciplinaria de forma oportuna, veraz y confiable. 14. Desempeñar las demás funciones que le asigne el superior inmediato de acuerdo a la naturaleza del cargo. | AG9: Estudio: Título profesional en: Administración Pública, Administración de Empresas, Administración Financiera, Administración Financiera y de Sistemas, Finanzas y Relaciones Internacionales, Finanzas Internacionales o Administración de Negocios; del núcleo básico de conocimiento en Administración. Título profesional en: Economía, Comercio Exterior o Finanzas y Comercio Exterior; del núcleo básico de conocimiento en Economía. Título profesional en: Contaduría Pública; del núcleo básico de conocimiento en Contaduría Pública. Título profesional en: Derecho; Derecho y Ciencias Sociales; Derecho y Ciencias Políticas; Derecho y Ciencias Humanas; Derecho y Ciencias Administrativas; Derecho Ciencias Políticas y Relaciones Internacionales; Jurisprudencia; Justicia y Derecho; ó Leyes y Jurisprudencia; del núcleo básico de conocimiento en Derecho y afines. Título profesional en: Ingeniería Industrial o Ingeniería de Producción; del núcleo básico de conocimiento en Ingeniería Industrial. Título profesional en: Ingeniería Administrativa o Ingeniería Financiera; del núcleo básico de conocimiento en Ingeniería Financiera y afines.Título profesional en: Ingeniería de Sistemas; del núcleo básico de conocimiento en Ingeniería de Sistemas, Telemática y afines. Título profesional en: Ciencia Política o Gobierno y Relaciones Internacionales; del núcleo básico de conocimiento en Ciencia Política o Relaciones Internacionales. Título de posgrado en áreas relacionadas con las funciones del cargo. Tarjeta o matrícula profesional en los casos reg lamentados por la ley. | AH9: 15-19 RES. 074 de 2023 | AI9: =VLOOKUP(AR9,$AT$5:$AU$103,2,0) -> 9154873 | AJ9: =+AI9*0.3 -> 2746461.9 | AK9: =IFERROR(INT(($AI9*(VLOOKUP($D9,BASE_PORCENTAJES,10,0))/100)),0) -> 0 | AL9: =IFERROR(INT(($AI9*(VLOOKUP($D9,'PORCENTAJES FACTORES'!B:N,12,0))/100)),0) -> 4577436 | AM9: =IFERROR(INT(($AI9*(VLOOKUP($D9,BASE_PORCENTAJES,13,0))/100)),0) -> 0 | AN9: =IF($AI9<=($AN$1*2),$AN$2,0) -> 0 | AO9: =IF($AI9<=$AO$1,$AO$2,0) -> 0 | AP9: =+AI9+AJ9+AK9+AL9+AM9+AN9+AO9 -> 16478771 | AR9: 5-ASESOR | AT9: 5-DIRECTIVO | AU9: 9154873 | AV9: =VLOOKUP(N9,D:D,1,0) -> 1121857540 | AW9: =VLOOKUP(D9,'PLANTA PERNO'!A:R,18,0) -> 0 | AY9: ENCARGO | AZ9: EN ENCARGO
